Workbook
Name AUMENTO: 'GASTOS ADMINISTRATIVOS'!#REF!
Name FACT: 'COMEDORES VALLE'!#REF!
Name INCREMENTO: 'GASTOS ADMINISTRATIVOS'!#REF!
Name Total_Acqui: #REF!
Name Total_Bogotá: #REF!
Name Total_Pari: #REF!
Name AUMENTO: 'GASTOS ADMINISTRATIVOS'!#REF!
Name FACT: 'COMEDORES VALLE'!#REF!
Name INCREMENTO: 'GASTOS ADMINISTRATIVOS'!#REF!
Name AUMENTO: 'GASTOS ADMINISTRATIVOS'!#REF!
Name FACT: 'COMEDORES VALLE'!#REF!
Name INCREMENTO: 'GASTOS ADMINISTRATIVOS'!#REF!

Sheet %DIST
A1: DISTRIBUCION PERSONAL OPERATIVO
E2: =E5/2 | G2: =G5/2 | I2: =I5/2 | K2: =K5/2 | M2: =M5/2 | O2: =O5/2 | Q2: =Q5/2 | S2: =S5/2 | U2: =U5/2 | W2: =W5/2
B3: ENE | C3: % | D3: FEB | E3: % | F3: MAR | G3: % | H3: ABR | I3: % | J3: MAY | K3: % | L3: JUN | M3: % | N3: JUL | O3: % | P3: AGO | Q3: % | R3: SEP | S3: % | T3: OCT | U3: % | V3: NOV | W3: % | X3: DIC | Y3: %
A4: CALI | C4: 0.15802632 | E4: 0.35073589 | F4: =CALI!I$12 | G4: =F4/F$14 | H4: =CALI!L$12 | I4: =H4/H$14 | J4: =CALI!O$12 | K4: =J4/J$14 | L4: =CALI!R$12 | M4: =L4/L$14 | N4: =CALI!U$12 | O4: =N4/N$14 | P4: =CALI!X$12 | Q4: =P4/P$14 | R4: =CALI!AA$12 | S4: =R4/R$14 | T4: =CALI!AD$12 | U4: =T4/T$14 | V4: =CALI!AG$12 | W4: =V4/V$14 | X4: =CALI!AJ$12 | Y4: =X4/X$14 | Z4: 0.082331474
A5: YUMBO | C5: 0.092315605 | E5: 0.21581822 | F5: =YUMBO!I$12 | G5: =F5/F$14 | H5: =YUMBO!L$12 | I5: =H5/H$14 | J5: =YUMBO!O$12 | K5: =J5/J$14 | L5: =YUMBO!R$12 | M5: =L5/L$14 | N5: =YUMBO!U$12 | O5: =N5/N$14 | P5: =YUMBO!X$12 | Q5: =P5/P$14 | R5: =YUMBO!AA$12 | S5: =R5/R$14 | T5: =YUMBO!AD$12 | U5: =T5/T$14 | V5: =YUMBO!AG$12 | W5: =V5/V$14 | X5: =YUMBO!AJ$12 | Y5: =X5/X$14 | Z5: 0.15465757
A6: GOBERNACION | C6: 0 | E6: 0 | G6: =F6/F$14 | I6: =H6/H$14 | K6: =J6/J$14 | M6: =L6/L$14 | O6: =N6/N$14 | Q6: =P6/P$14 | S6: =R6/R$14 | U6: =T6/T$14 | W6: =V6/V$14 | Y6: =X6/X$14 | Z6: 0
A7: BUGA | C7: 0 | E7: 0 | G7: =F7/F$14 | I7: =H7/H$14 | K7: =J7/J$14 | M7: =L7/L$14 | O7: =N7/N$14 | Q7: =P7/P$14 | S7: =R7/R$14 | U7: =T7/T$14 | W7: =V7/V$14 | Y7: =X7/X$14 | Z7: 0
A8: HUNGRIA | C8: 0 | E8: 0 | F8: =HUNGRIA!I$12 | G8: =F8/F$14 | H8: =HUNGRIA!L$5 | I8: =H8/H$14 | J8: =HUNGRIA!O$5 | K8: =J8/J$14 | L8: =HUNGRIA!R$12 | M8: =L8/L$14 | N8: =HUNGRIA!U$12 | O8: =N8/N$14 | P8: =HUNGRIA!X$12 | Q8: =P8/P$14 | R8: =HUNGRIA!AA$12 | S8: =R8/R$14 | T8: =HUNGRIA!AD$12 | U8: =T8/T$14 | V8: =HUNGRIA!AG$12 | W8: =V8/V$14 | X8: =HUNGRIA!AJ$12 | Y8: =X8/X$14
A9: COMEDORES CALI | C9: 0.7275737 | E9: 0.42310873 | F9: ='COMEDORES CALI'!$I$12 | G9: =F9/F$14 | H9: ='COMEDORES CALI'!$L$12 | I9: =H9/H$14 | J9: ='COMEDORES CALI'!O$12 | K9: =J9/J$14 | L9: ='COMEDORES CALI'!R$12 | M9: =L9/L$14 | N9: ='COMEDORES CALI'!U$12 | O9: =N9/N$14 | P9: ='COMEDORES CALI'!X$12 | Q9: =P9/P$14 | R9: ='COMEDORES CALI'!AA$12 | S9: =R9/R$14 | T9: ='COMEDORES CALI'!AD$12 | U9: =T9/T$14 | V9: ='COMEDORES CALI'!AG$12 | W9: =V9/V$14 | X9: ='COMEDORES CALI'!AJ$12 | Y9: =X9/X$14 | Z9: 0.02828364
A10: COMEDORES GOB | G10: =F10/F$14 | I10: =H10/H$14 | K10: =J10/J$14 | M10: =L10/L$14 | O10: =N10/N$14 | Q10: =P10/P$14 | S10: =R10/R$14 | U10: =T10/T$14 | W10: =V10/V$14 | Y10: =X10/X$14 | Z10: 0.0012929073
A11: COMEDORES PALMIRA | C11: 0.022084378 | E11: 0.010337164 | F11: ='COMEDORES PALMIRA'!I$12 | G11: =F11/F$14 | H11: ='COMEDORES PALMIRA'!L$12 | I11: =H11/H$14 | J11: ='COMEDORES PALMIRA'!O$12 | K11: =J11/J$14 | L11: ='COMEDORES PALMIRA'!R$12 | M11: =L11/L$14 | N11: ='COMEDORES PALMIRA'!U$12 | O11: =N11/N$14 | P11: ='COMEDORES PALMIRA'!X$12 | Q11: =P11/P$14 | R11: ='COMEDORES PALMIRA'!AA$12 | S11: =R11/R$14 | T11: ='COMEDORES PALMIRA'!AD$12 | U11: =T11/T$14 | V11: ='COMEDORES PALMIRA'!$AG$12 | W11: =V11/V$14 | X11: ='COMEDORES PALMIRA'!$AJ$12 | Y11: =X11/X$14 | Z11: 0.029041283
A12: ADULTO MAYOR | C12: 0 | E12: 0 | F12: ='ADULTO MAYOR'!I$12*20 | G12: =F12/F$14 | H12: ='ADULTO MAYOR'!L$12*20 | I12: =H12/H$14 | J12: ='ADULTO MAYOR'!O$12*20 | K12: =J12/J$14 | L12: ='ADULTO MAYOR'!R$12*20 | M12: =L12/L$14 | N12: ='ADULTO MAYOR'!U$12*20 | O12: =N12/N$14 | P12: ='ADULTO MAYOR'!X$12*20 | Q12: =P12/P$14 | R12: ='ADULTO MAYOR'!AA$12*20 | S12: =R12/R$14 | T12: ='ADULTO MAYOR'!AD$12*20 | U12: =T12/T$14 | V12: ='ADULTO MAYOR'!AG$12*20 | W12: =V12/V$14 | X12: ='ADULTO MAYOR'!AJ$12*20 | Y12: =X12/X$14 | Z12: 0.67336335
A13: IMDERTY | C13: 0 | E13: 0 | F13: =IMDERTY!I$12 | G13: =F13/F$14 | H13: =IMDERTY!L$12 | I13: =H13/H$14 | J13: =IMDERTY!O$12 | K13: =J13/J$14 | L13: =IMDERTY!R$12 | M13: =L13/L$14 | N13: =IMDERTY!$U$12 | O13: =N13/N$14 | P13: =IMDERTY!X$12 | Q13: =P13/P$14 | R13: =IMDERTY!AA$12 | S13: =R13/R$14 | T13: =IMDERTY!AD$12 | U13: =T13/T$14 | V13: =IMDERTY!AG$12 | W13: =V13/V$14 | X13: =IMDERTY!AJ$12 | Y13: =X13/X$14 | Z13: 0.031029775
B14: =SUM(B4:B13) | C14: =SUM(C4:C13) | D14: =SUM(D4:D13) | E14: =SUM(E4:E13) | F14: =SUM(F4:F13) | G14: =SUM(G4:G13) | H14: =SUM(H4:H13) | I14: =SUM(I4:I13) | ... Y14: =SUM(Y4:Y13)
A17: DISTRIBUCION FLETES INTERNOS
B19: ENE | D19: FEB | F19: MAR | H19: ABR | J19: MAY | L19: JUN | N19: JUL | P19: AGO | R19: SEP | T19: OCT | V19: NOV | X19: DIC
A20: CALI | B20: 0.22 | D20: 0.685 | F20: 0.64 | H20: 0.565 | J20: 0.47 | L20: 0.6 | N20: 0.23 | P20: 0.495 | R20: 0.53 | T20: 0.38 | V20: 0.52 | AA20: 0.2
A21: YUMBO | B21: 0.075 | D21: 0.2 | F21: 0.18 | H21: 0.19 | J21: 0.19 | L21: 0.09 | N21: 0.13 | P21: 0.175 | R21: 0.16 | T21: 0.12 | V21: 0.2
A22: GOBERNACION
A23: BUGA | B23: 0.015 | D23: 0.02 | F23: 0.02 | H23: 0.035 | J23: 0.04 | L23: 0.02 | N23: 0.01 | P23: 0.015 | R23: 0.01 | T23: 0.02 | V23: 0.01 | AA23: 0.15
A24: HUNGRIA | AA24: 0.55
A25: COMEDORES CALI | B25: 0.67 | D25: 0.085 | F25: 0.16 | H25: 0.175 | J25: 0.1 | L25: 0.09 | N25: 0.32 | P25: 0.115 | R25: 0.13 | T25: 0.21 | V25: 0.09 | X25: 0.89
A26: COMEDORES GOB | J26: 0.17 | L26: 0.15 | N26: 0.25 | P26: 0.15 | R26: 0.13 | T26: 0.15 | V26: 0.15 | AA26: 0.04
A27: COMEDORES PALMIRA | B27: 0.02 | D27: 0.01 | N27: 0.01 | P27: 0.005 | R27: 0.03 | T27: 0.04 | V27: 0.03 | X27: 0.11
A28: ADULTO MAYOR | H28: 0.035 | J28: 0.03 | L28: 0.05 | N28: 0.05 | P28: 0.045 | R28: 0.01 | T28: 0.08
A29: IMDERTY
B30: =SUM(B20:B29) | D30: =SUM(D20:D29) | F30: =SUM(F20:F29) | H30: =SUM(H20:H29) | J30: =SUM(J20:J29) | L30: =SUM(L20:L29) | N30: =SUM(N20:N29) | P30: =SUM(P20:P29) | R30: =SUM(R20:R29) | T30: =SUM(T20:T29) | V30: =SUM(V20:V29) | X30: =SUM(X20:X29)
A33: DISTRIBUCION PERSONAL ADMINISTRATIVO
B35: ENE | D35: FEB | F35: MAR | H35: ABR | J35: MAY | L35: JUN | N35: JUL | P35: AGO | R35: SEP | T35: OCT | V35: NOV | X35: DIC
A36: CALI | B36: =C52 | D36: =E52 | F36: =G52 | H36: =I52 | J36: =K52 | L36: =M52 | N36: =O52 | P36: =Q52 | R36: =S52 | T36: =U52 | V36: =W52 | X36: =Y52
A37: YUMBO | B37: =C53 | D37: =E53 | F37: =G53 | H37: =I53 | J37: =K53 | L37: =M53 | N37: =O53 | P37: =Q53 | R37: =S53 | T37: =U53 | V37: =W53 | X37: =Y53
A38: GOBERNACION | B38: =C54 | D38: =E54 | F38: =G54 | H38: =I54 | J38: =K54 | L38: =M54 | N38: =O54 | P38: =Q54 | R38: =S54 | T38: =U54 | V38: =W54 | X38: =Y54
A39: BUGA | B39: =C55 | D39: =E55 | F39: =G55 | H39: =I55 | J39: =K55 | L39: =M55 | N39: =O55 | P39: =Q55 | R39: =S55 | T39: =U55 | V39: =W55 | X39: =Y55
A40: HUNGRIA | B40: =C56 | D40: =E56 | F40: =G56 | H40: =I56 | J40: =K56 | L40: =M56 | N40: =O56 | P40: =Q56 | R40: =S56 | T40: =U56 | V40: =W56 | X40: =Y56
A41: COMEDORES CALI | B41: =C57-B45 | D41: =E57-D45 | F41: =G57-F45 | H41: =I57-H45 | J41: =K57-J45 | L41: =M57-L45 | N41: =O57-N45 | P41: =Q57-P45 | R41: =S57-R45 | T41: =U57-T45 | V41: =W57-V45 | X41: =Y57-X45
A42: COMEDORES GOB | B42: =C58 | D42: =E58 | F42: =G58 | H42: =I58 | J42: =K58 | L42: =M58 | N42: =O58 | P42: =Q58 | R42: =S58 | T42: =U58 | V42: =W58 | X42: =Y58
A43: COMEDORES PALMIRA | B43: =C59 | D43: =E59 | F43: =G59 | H43: =I59 | J43: =K59 | L43: =M59 | N43: =O59 | P43: =Q59 | R43: =S59 | T43: =U59 | V43: =W59 | X43: =Y59
A44: ADULTO MAYOR | B44: =C60 | D44: =E60 | F44: =G60 | H44: =I60 | J44: =K60 | L44: =M60 | N44: =O60 | P44: =Q60 | R44: =S60 | T44: =U60 | V44: =W60 | X44: =Y60
A45: CTAS PPACION | B45: 0.01 | D45: 0.01 | F45: 0.01 | H45: 0.01 | J45: 0.01 | L45: 0.01 | N45: 0.01 | P45: 0.01 | R45: 0.01 | T45: 0.01 | V45: 0.01 | X45: 0.01
B46: =SUM(B36:B45) | D46: =SUM(D36:D45) | F46: =SUM(F36:F45) | H46: =SUM(H36:H45) | J46: =SUM(J36:J45) | L46: =SUM(L36:L45) | N46: =SUM(N36:N45) | P46: =SUM(P36:P45) | R46: =SUM(R36:R45) | T46: =SUM(T36:T45) | V46: =SUM(V36:V45) | X46: =SUM(X36:X45)
A49: DISTRIBUCION GASTOS FINANCIEROS
B51: ENE | C51: % | D51: FEB | E51: % | F51: MAR | G51: % | H51: ABR | I51: % | J51: MAY | K51: % | L51: JUN | M51: % | N51: JUL | O51: % | P51: AGO | Q51: % | R51: SEP | S51: % | T51: OCT | U51: % | V51: NOV | W51: % | X51: DIC | Y51: %
A52: CALI | C52: 0.1346188 | E52: 0.29904422 | F52: =CALI!$I$42 | G52: =F52/F$62 | H52: =CALI!$L$42 | I52: =H52/H$62 | J52: =CALI!$O$42 | K52: =J52/J$62 | L52: =CALI!$R$42 | M52: =L52/L$62 | N52: =CALI!$U$42 | O52: =N52/N$62 | P52: =CALI!$X$42 | Q52: =P52/P$62 | R52: =CALI!$AA$42 | S52: =R52/R$62 | T52: =CALI!$AD$42 | U52: =T52/T$62 | V52: =CALI!$AG$42 | W52: =V52/V$62 | X52: =CALI!$AJ$42 | Y52: =X52/X$62
A53: YUMBO | C53: 0.081149115 | E53: 0.19128492 | F53: =YUMBO!$I$42 | G53: =F53/F$62 | H53: =YUMBO!$L$42 | I53: =H53/H$62 | J53: =YUMBO!$O$42 | K53: =J53/J$62 | L53: =YUMBO!$R$42 | M53: =L53/L$62 | N53: =YUMBO!$U$42 | O53: =N53/N$62 | P53: =YUMBO!$X$42 | Q53: =P53/P$62 | R53: =YUMBO!$AA$42 | S53: =R53/R$62 | T53: =YUMBO!$AD$42 | U53: =T53/T$62 | V53: =YUMBO!$AG$42 | W53: =V53/V$62 | X53: =YUMBO!$AJ$42 | Y53: =X53/X$62
A54: GOBERNACION | C54: 0 | E54: 0 | G54: =F54/F$62 | I54: =H54/H$62 | K54: =J54/J$62 | M54: =L54/L$62 | O54: =N54/N$62 | Q54: =P54/P$62 | S54: =R54/R$62 | U54: =T54/T$62 | W54: =V54/V$62 | Y54: =X54/X$62
A55: BUGA | C55: 0.098870788 | E55: 0.1194998 | F55: =BUGA!$I$42 | G55: =F55/F$62 | H55: =BUGA!L42 | I55: =H55/H$62 | J55: =BUGA!O42 | K55: =J55/J$62 | L55: =BUGA!R42 | M55: =L55/L$62 | N55: =BUGA!U42 | O55: =N55/N$62 | P55: =BUGA!X42 | Q55: =P55/P$62 | R55: =BUGA!AA42 | S55: =R55/R$62 | T55: =BUGA!AD42 | U55: =T55/T$62 | V55: =BUGA!AG42 | W55: =V55/V$62 | X55: =BUGA!AJ42 | Y55: =X55/X$62
A56: HUNGRIA | C56: 0 | E56: 0 | F56: =HUNGRIA!I42 | G56: =F56/F$62 | H56: =HUNGRIA!L42 | I56: =H56/H$62 | J56: =HUNGRIA!O42 | K56: =J56/J$62 | L56: =HUNGRIA!R42 | M56: =L56/L$62 | N56: =HUNGRIA!U42 | O56: =N56/N$62 | P56: =HUNGRIA!X42 | Q56: =P56/P$62 | R56: =HUNGRIA!AA42 | S56: =R56/R$62 | T56: =HUNGRIA!AD42 | U56: =T56/T$62 | V56: =HUNGRIA!AG42 | W56: =V56/V$62 | X56: =HUNGRIA!AJ42 | Y56: =X56/X$62
A57: COMEDORES CALI | C57: 0.66522724 | E57: 0.38081604 | F57: ='COMEDORES CALI'!I$42+'CTAS EN PPACION'!$I$42 | G57: =F57/F$62 | H57: ='COMEDORES CALI'!L$42+'CTAS EN PPACION'!L$42 | I57: =H57/H$62 | J57: ='COMEDORES CALI'!O$42+'CTAS EN PPACION'!$O$13 | K57: =J57/J$62 | L57: ='COMEDORES CALI'!R$42+'CTAS EN PPACION'!R$42 | M57: =L57/L$62 | N57: ='COMEDORES CALI'!U$42+'CTAS EN PPACION'!U$42 | O57: =N57/N$62 | P57: ='COMEDORES CALI'!X$42+'CTAS EN PPACION'!X$42 | Q57: =P57/P$62 | R57: ='COMEDORES CALI'!AA$42+'CTAS EN PPACION'!AA$42 | S57: =R57/R$62 | T57: ='COMEDORES CALI'!AD$42+'CTAS EN PPACION'!AD$42 | U57: =T57/T$62 | V57: ='COMEDORES CALI'!AG$42+'CTAS EN PPACION'!AG$42 | W57: =V57/V$62 | X57: ='COMEDORES CALI'!AJ$42+'CTAS EN PPACION'!AJ$42 | Y57: =X57/X$62
A58: COMEDORES GOB | C58: 0 | E58: 0 | G58: =F58/F$62 | I58: =H58/H$62 | J58: ='COMEDORES VALLE'!O13 | K58: =J58/J$62 | L58: ='COMEDORES VALLE'!R13 | M58: =L58/L$62 | N58: ='COMEDORES VALLE'!U13 | O58: =N58/N$62 | P58: ='COMEDORES VALLE'!$X$13 | Q58: =P58/P$62 | R58: ='COMEDORES VALLE'!$AA$13 | S58: =R58/R$62 | T58: ='COMEDORES VALLE'!$AD$13 | U58: =T58/T$62 | V58: ='COMEDORES VALLE'!AG13 | W58: =V58/V$62 | Y58: =X58/X$62
A59: COMEDORES PALMIRA | C59: 0.02013406 | E59: 0.009355013 | F59: ='COMEDORES PALMIRA'!I$42 | G59: =F59/F$62 | H59: ='COMEDORES PALMIRA'!L$42 | I59: =H59/H$62 | J59: ='COMEDORES PALMIRA'!O$42 | K59: =J59/J$62 | L59: ='COMEDORES PALMIRA'!R$42 | M59: =L59/L$62 | N59: ='COMEDORES PALMIRA'!U$42 | O59: =N59/N$62 | P59: ='COMEDORES PALMIRA'!X$42 | Q59: =P59/P$62 | R59: ='COMEDORES PALMIRA'!AA$42 | S59: =R59/R$62 | T59: ='COMEDORES PALMIRA'!AD$42 | U59: =T59/T$62 | V59: ='COMEDORES PALMIRA'!AG$42 | W59: =V59/V$62 | X59: ='COMEDORES PALMIRA'!AJ$42 | Y59: =X59/X$62
A60: ADULTO MAYOR | C60: 0 | E60: 0 | F60: ='ADULTO MAYOR'!I$42 | G60: =F60/F$62 | H60: ='ADULTO MAYOR'!L$42 | I60: =H60/H$62 | J60: ='ADULTO MAYOR'!O$42 | K60: =J60/J$62 | L60: ='ADULTO MAYOR'!R$42 | M60: =L60/L$62 | N60: ='ADULTO MAYOR'!U$42 | O60: =N60/N$62 | P60: ='ADULTO MAYOR'!X$42 | Q60: =P60/P$62 | R60: ='ADULTO MAYOR'!AA$42 | S60: =R60/R$62 | T60: ='ADULTO MAYOR'!AD$42 | U60: =T60/T$62 | V60: ='ADULTO MAYOR'!AG$42 | W60: =V60/V$62 | X60: ='ADULTO MAYOR'!AJ$42 | Y60: =X60/X$62
A61: IMDERTY | C61: 0 | E61: 0 | F61: =IMDERTY!I$42 | G61: =F61/F$62 | H61: =IMDERTY!L$42 | I61: =H61/H$62 | K61: =J61/J$62 | L61: =IMDERTY!R$42 | M61: =L61/L$62 | N61: =IMDERTY!U$42 | O61: =N61/N$62 | P61: =IMDERTY!X$42 | Q61: =P61/P$62 | R61: =IMDERTY!AA$42 | S61: =R61/R$62 | T61: =IMDERTY!AD$42 | U61: =T61/T$62 | V61: =IMDERTY!AG$42 | W61: =V61/V$62 | X61: =IMDERTY!AJ$42 | Y61: =X61/X$62
B62: =SUM(B52:B61) | C62: =SUM(C52:C61) | D62: =SUM(D52:D61) | E62: =SUM(E52:E61) | F62: =SUM(F52:F61) | G62: =SUM(G52:G61) | H62: =SUM(H52:H61) | I62: =SUM(I52:I61) | ... Y62: =SUM(Y52:Y61)

Sheet GASTOS ADMINISTRATIVOS
B2: CORPORACIÓN HACIA UN VALLE SOLIDARIO | C2: GASTOS ADMINISTRATIVOS 2026
C4: ENE | D4: FEB | E4: MAR | F4: ABR | G4: MAY | H4: JUN | I4: JUL | J4: AGO | K4: SEP | L4: OCT | M4: NOV | N4: DIC | O4: ACUMULADO
B5: GASTOS DE PERSONAL | C5: =SUM(C6:C12) | D5: =SUM(D6:D12) | E5: =SUM(E6:E12) | F5: =SUM(F6:F12) | G5: =SUM(G6:G12) | H5: =SUM(H6:H12) | I5: =SUM(I6:I12) | J5: =SUM(J6:J12) | ... O5: =SUM(O6:O12)
A6: 5105 | B6: Salarios | C6: ='[1]Hoja 1'!$I$9-921014+'[2]Hoja 1'!$I$9+'[3]Hoja 1'!$D$8 | D6: ='[4]Hoja 1'!$L$8-6457629+'[5]Hoja 1'!$I$9+'[6]Hoja 1'!$D$8+'[7]Hoja 1'!$D$10+'[8]Hoja 1'!$I$9 | E6: 241842440 | O6: =+SUM(C6:N6)
B7: Personal Decreto 1860/21 | C7: ='[1]Hoja 1'!$I$12 | D7: ='[4]Hoja 1'!$L$10 | E7: 241842440 | O7: =+SUM(C7:N7)
A8: 51055101 | B8: Dotacion y Suministro | C8: ='[9]Hoja 1'!$C$54-225638 | D8: ='[10]Hoja 1'!$C$54-59862 | E8: 241842440 | O8: =+SUM(C8:N8)
B9: Bonificaciones | E9: 241842440 | O9: =+SUM(C9:N9)
A10: 51056301 | B10: Capacitacion | C10: ='[9]Hoja 1'!$C$56 | D10: ='[10]Hoja 1'!$C$56 | E10: 241842440 | O10: =+SUM(C10:N10)
A11: 51058401 | B11: Gastos Medicos | C11: ='[9]Hoja 1'!$C$70 | D11: ='[10]Hoja 1'!$C$70 | E11: 241842440 | O11: =+SUM(C11:N11)
A12: 53954002 | B12: Incapacidades | D12: ='[11]Hoja 1'!$C$27 | E12: 241842440 | O12: =+SUM(C12:N12)
B13: HONORARIOS | C13: =SUM(C14:C18) | D13: =SUM(D14:D18) | E13: =SUM(E14:E18) | F13: =SUM(F14:F18) | G13: =SUM(G14:G18) | H13: =SUM(H14:H18) | I13: =SUM(I14:I18) | J13: =SUM(J14:J18) | ... O13: =SUM(O14:O18)
A14: 51101001 | B14: Revisoria Fiscal | C14: ='[9]Hoja 1'!$C$73 | D14: ='[10]Hoja 1'!$C$73 | E14: 241842440 | O14: =+SUM(C14:N14)
B15: Avaluos | E15: 241842440 | O15: =+SUM(C15:N15)
A16: 51102001 | B16: Asesoria Juridica | C16: ='[9]Hoja 1'!$C$75+'[12]Hoja 1'!$G$13 | D16: ='[10]Hoja 1'!$C$75+'[13]Hoja 1'!$G$14 | E16: 241842440 | O16: =+SUM(C16:N16)
A17: 51103001 | B17: Asesoria Financiera | E17: 241842440 | O17: =+SUM(C17:N17)
A18: 51103508 | B18: Asesoría Técnica | C18: ='[9]Hoja 1'!$C$77 | D18: ='[10]Hoja 1'!$C$76 | E18: 241842440 | O18: =+SUM(C18:N18)
B19: IMPUESTOS | C19: =SUM(C20:C21) | D19: =SUM(D20:D21) | E19: =SUM(E20:E21) | F19: =SUM(F20:F21) | G19: =SUM(G20:G21) | H19: =SUM(H20:H21) | I19: =SUM(I20:I21) | J19: =SUM(J20:J21) | ... O19: =SUM(O20:O21)
B20: Predial | E20: 241842440 | O20: =+SUM(C20:N20)
B21: Impuestos vehiculos | C21: 2676712 | E21: 241842440 | O21: =+SUM(C21:N21)
B22: ARRENDAMIENTOS | C22: =SUM(C23:C27) | D22: =SUM(D23:D27) | E22: =SUM(E23:E27) | F22: =SUM(F23:F27) | G22: =SUM(G23:G27) | H22: =SUM(H23:H27) | I22: =SUM(I23:I27) | J22: =SUM(J23:J27) | ... O22: =SUM(O23:O27)
A23: 51201001 - 51355001 | B23: Construcciones y Edificaciones | C23: ='[9]Hoja 1'!$C$85+'[12]Hoja 1'!$G$15+'[12]Hoja 1'!$G$17 | D23: ='[10]Hoja 1'!$C$84+'[13]Hoja 1'!$G$16+'[13]Hoja 1'!$G$18 | E23: 241842440 | O23: =+SUM(C23:N23)
A24: 51201501 - 73201501 | B24: Maquinaria y Equipo | C24: ='[9]Hoja 1'!$C$87 | D24: ='[10]Hoja 1'!$C$86 | E24: 241842440 | O24: =+SUM(C24:N24)
A25: 51202001 | B25: Equipo de Oficina | C25: ='[9]Hoja 1'!$C$89 | D25: ='[10]Hoja 1'!$C$88 | E25: 241842440 | O25: =+SUM(C25:N25)
B26: Equipo de Computacion y comunicaciones | D26: ='[10]Hoja 1'!$C$90 | E26: 241842440 | O26: =+SUM(C26:N26)
B27: Flota y Equipo de Transporte | E27: 241842440 | O27: =+SUM(C27:N27)
B28: SEGUROS | C28: =SUM(C29:C31) | D28: =SUM(D29:D31) | E28: =SUM(E29:E31) | F28: =SUM(F29:F31) | G28: =SUM(G29:G31) | H28: =SUM(H29:H31) | I28: =SUM(I29:I31) | J28: =SUM(J29:J31) | ... O28: =SUM(O29:O31)
B29: Cumplimiento | E29: 241842440 | O29: =+SUM(C29:N29)
B30: Responsabilidad Civil y Extracontractual | E30: 241842440 | O30: =+SUM(C30:N30)
B31: OTROS - Funerarios | D31: ='[10]Hoja 1'!$C$95 | E31: 241842440 | O31: =+SUM(C31:N31)
B32: SERVICIOS | C32: =SUM(C33:C45) | D32: =SUM(D33:D45) | E32: =SUM(E33:E45) | F32: =SUM(F33:F45) | G32: =SUM(G33:G45) | H32: =SUM(H33:H45) | I32: =SUM(I33:I45) | J32: =SUM(J33:J45) | ... O32: =SUM(O33:O45)
B33: Aseo y Vigilancia | C33: ='[12]Hoja 1'!$G$22 | D33: ='[13]Hoja 1'!$G$23 | E33: 241842440 | O33: =+SUM(C33:N33)
A34: 51351001 - 51351004 | B34: Temporales | C34: ='[9]Hoja 1'!$C$97 | D34: ='[10]Hoja 1'!$C$99 | E34: 241842440 | O34: =+SUM(C34:N34)
B35: Comunicaciones | E35: 241842440 | O35: =+SUM(C35:N35)
A36: 51351502 | B36: Laboratorio | D36: ='[10]Hoja 1'!C103 | E36: 241842440 | O36: =+SUM(C36:N36)
A37: 51351503 | B37: Fumigacion | C37: ='[9]Hoja 1'!$C$99 | D37: ='[10]Hoja 1'!C104 | E37: 241842440 | O37: =+SUM(C37:N37)
A38: 51352501 | B38: Acueducto y Alcantarillado | C38: ='[9]Hoja 1'!$C$101 | D38: ='[10]Hoja 1'!$C$106 | E38: 241842440 | O38: =+SUM(C38:N38)
A39: 51353001 | B39: Energía Electrica | C39: ='[9]Hoja 1'!$C$103 | D39: ='[10]Hoja 1'!$C$108 | E39: 241842440 | O39: =+SUM(C39:N39)
A40: 51353501 | B40: Telefono | C40: ='[9]Hoja 1'!C105 | D40: ='[10]Hoja 1'!C110-98250 | E40: 241842440 | O40: =+SUM(C40:N40)
A41: 51353502 | B41: Internet | C41: ='[9]Hoja 1'!C106 | D41: ='[10]Hoja 1'!C111 | E41: 241842440 | O41: =+SUM(C41:N41)
A42: 51354001 | B42: Correo, Portes, telegramas | C42: ='[9]Hoja 1'!$C$108 | D42: ='[10]Hoja 1'!$C$113 | E42: 241842440 | O42: =+SUM(C42:N42)
A43: 51355001 | B43: Transporte, fletes y acarreos | C43: ='[12]Hoja 1'!$G$11 | D43: ='[13]Hoja 1'!$G$11 | E43: 241842440 | O43: =+SUM(C43:N43)
B44: Gas | E44: 241842440 | O44: =+SUM(C44:N44)
A45: 51356501 | B45: Servicio Web-Hosting-Nube- Licencias Siesa y planeacion | C45: ='[9]Hoja 1'!$C$112+'[14]Hoja 1'!$C$70+'[15]Hoja 1'!$C$109+'[16]Hoja 1'!$D$133+'[17]Hoja 1'!$C$101 | D45: ='[10]Hoja 1'!$C$117+'[10]Hoja 1'!$C$312+'[18]Hoja 1'!$C$92+'[19]Hoja 1'!$C$89+'[20]Hoja 1'!$C$97 | E45: 241842440 | O45: =+SUM(C45:N45)
B46: GASTOS LEGALES | C46: =SUM(C47:C51) | D46: =SUM(D47:D51) | E46: =SUM(E47:E51) | F46: =SUM(F47:F51) | G46: =SUM(G47:G51) | H46: =SUM(H47:H51) | I46: =SUM(I47:I51) | J46: =SUM(J47:J51) | ... O46: =SUM(O47:O51)
B47: Notariales | C47: ='[9]Hoja 1'!$C$115 | E47: 241842440 | O47: =+SUM(C47:N47)
B48: Registro Mercantil y proponentes | D48: ='[10]Hoja 1'!$C$120 | E48: 241842440 | O48: =+SUM(C48:N48)
B49: Tramites y Licencias | C49: ='[9]Hoja 1'!$C$117 | E49: 241842440 | O49: =+SUM(C49:N49)
B50: Servicio de Registro BMC | E50: 241842440 | O50: =+SUM(C50:N50)
A51: 514095 | B51: Certificados Camara Comercio , proponentes y tradicion, JCC | C51: ='[9]Hoja 1'!$C$118 | D51: ='[10]Hoja 1'!$C$121 | E51: 241842440 | O51: =+SUM(C51:N51)
B52: MANTENIMIENTO Y REPARACIONES | C52: =SUM(C53:C58) | D52: =SUM(D53:D58) | E52: =SUM(E53:E58) | F52: =SUM(F53:F58) | G52: =SUM(G53:G58) | H52: =SUM(H53:H58) | I52: =SUM(I53:I58) | J52: =SUM(J53:J58) | ... O52: =SUM(O53:O58)
A53: 51451001 | B53: Construcciones y Edificaciones | C53: ='[9]Hoja 1'!$C$123 | D53: ='[10]Hoja 1'!$C$126 | E53: 241842440 | O53: =+SUM(C53:N53)
A54: 51451501 | B54: Maquinaria y Equipo | D54: ='[10]Hoja 1'!$C$128-318000+'[10]Hoja 1'!$C$129 | O54: =+SUM(C54:N54)
B55: Equipo de Oficina | E55: 241842440 | O55: =+SUM(C55:N55)
A56: 51451001 - 51451501 | B56: Planta Plan Basico de Saneamiento | C56: ='[9]Hoja 1'!$C$158 | D56: 318000 | E56: 241842440 | O56: =+SUM(C56:N56)
A57: 51452501 | B57: Equipo de Computacion y Comunic | C57: ='[9]Hoja 1'!$C$127 | E57: 241842440 | O57: =+SUM(C57:N57)
A58: 51451501 | B58: Plan SST | C58: ='[9]Hoja 1'!$C$125 | E58: 324993540 | O58: =+SUM(C58:N58)
B59: ADECUACIONES E INSTALACIONES | C59: =SUM(C60:C61) | D59: =SUM(D60:D61) | E59: =SUM(E60:E61) | F59: =SUM(F60:F61) | G59: =SUM(G60:G61) | H59: =SUM(H60:H61) | I59: =SUM(I60:I61) | J59: =SUM(J60:J61) | ... O59: =SUM(O60:O61)
B60: Inversion infraestructura | E60: 241842440 | O60: =+SUM(C60:N60)
B61: Reparaciones Locativas | E61: 241842440 | O61: =+SUM(C61:N61)
B62: GASTOS DE VIAJE | C62: =SUM(C63:C65) | D62: =SUM(D63:D65) | E62: =SUM(E63:E65) | F62: =SUM(F63:F65) | G62: =SUM(G63:G65) | H62: =SUM(H63:H65) | I62: =SUM(I63:I65) | J62: =SUM(J63:J65) | ... O62: =SUM(O63:O65)
A63: 51550501 | B63: Alojamiento y Manutencion | E63: 241842440 | O63: =+SUM(C63:N63)
A64: 51551501 | B64: Pasajes Aereos | E64: 241842440 | O64: =+SUM(C64:N64)
B65: Pasajes Terrestres | E65: 241842440 | O65: =+SUM(C65:N65)
B66: DIVERSOS | C66: =SUM(C67:C88) | D66: =SUM(D67:D88) | E66: =SUM(E67:E88) | F66: =SUM(F67:F88) | G66: =SUM(G67:G88) | H66: =SUM(H67:H88) | I66: =SUM(I67:I88) | J66: =SUM(J67:J88) | ... O66: =SUM(O67:O88)
A67: 51951001 | B67: Libros, suscripciones, period | C67: ='[9]Hoja 1'!$C$133 | D67: ='[10]Hoja 1'!$C$135 | E67: 241842440 | O67: =+SUM(C67:N67)
B68: Seguros Funerarios | E68: 241842440 | O68: =+SUM(C68:N68)
A69: 51952501 | B69: Elementos de Aseo y Cafeteria | C69: ='[9]Hoja 1'!$C$135 | D69: ='[10]Hoja 1'!$C$137 | E69: 241842440 | O69: =+SUM(C69:N69)
A70: 51953001 | B70: Papeleria | C70: ='[9]Hoja 1'!$C$137+'[9]Hoja 1'!$C$402 | D70: ='[10]Hoja 1'!$C$139 | E70: 241842440 | O70: =+SUM(C70:N70)
A71: 51953002 | B71: Fotocopias | E71: 241842440 | O71: =+SUM(C71:N71)
A72: 51953501 | B72: Combustible y Lubricantes | C72: 964175 | D72: 1186883 | E72: 241842440 | O72: =+SUM(C72:N72)
A73: 51954001 - '71100501 | B73: Envases y Empaques | C73: ='[9]Hoja 1'!$C$141 | D73: ='[10]Hoja 1'!$C$143 | E73: 243115937 | O73: =+SUM(C73:N73)
A74: 51954501 | B74: Taxis y Buses | C74: ='[9]Hoja 1'!$C$143 | D74: ='[10]Hoja 1'!$C$145 | E74: 241842440 | O74: =+SUM(C74:N74)
A75: 51956001 | B75: Casino y Restaurante (Refrigerios) | C75: ='[9]Hoja 1'!$C$145 | D75: ='[10]Hoja 1'!$C$147 | E75: 241842440 | O75: =+SUM(C75:N75)
A76: 51956501 | B76: Parqueaderos | C76: ='[9]Hoja 1'!$C$148 | D76: ='[10]Hoja 1'!$C$150 | E76: 241842440 | O76: =+SUM(C76:N76)
A77: 51956601 | B77: Peajes | C77: ='[9]Hoja 1'!$C$150 | D77: ='[10]Hoja 1'!$C$152 | E77: 241842440 | O77: =+SUM(C77:N77)
A78: 51959501 | B78: Otros | C78: ='[9]Hoja 1'!$C$152 | D78: ='[10]Hoja 1'!$C$154 | E78: 241842440 | O78: =+SUM(C78:N78)
A79: 51959502 | B79: Compra Equipos de Oficina | C79: ='[9]Hoja 1'!$C$153 | D79: ='[10]Hoja 1'!$C$155 | E79: 241842440 | O79: =+SUM(C79:N79)
A80: 51959503 | B80: Compra Suministros | C80: ='[9]Hoja 1'!$C$154 | D80: ='[10]Hoja 1'!$C$156 | E80: 241842440 | O80: =+SUM(C80:N80)
A81: 51959510 | B81: Herramientas y articulos ferreteria | C81: ='[9]Hoja 1'!$C$156 | D81: ='[10]Hoja 1'!$C$159 | E81: 241842440 | O81: =+SUM(C81:N81)
A82: 51959512 | B82: Reuniones Fiestas y Detalles | C82: ='[9]Hoja 1'!$C$157 | D82: ='[10]Hoja 1'!$C$160 | E82: 241842440 | O82: =+SUM(C82:N82)
A83: 51959514 | B83: Equipos de Bodega | C83: ='[9]Hoja 1'!$C$159 | D83: ='[10]Hoja 1'!$C$161 | E83: 241842440 | O83: =+SUM(C83:N83)
A84: 51959515 | B84: Compra Equipos de computo y comunicación | C84: ='[9]Hoja 1'!$C$160 | D84: ='[10]Hoja 1'!$C$162 | E84: 241842440 | O84: =+SUM(C84:N84)
A85: 51959504 | B85: Cuota de Apoyo y Sostenimiento (SENA) | C85: ='[9]Hoja 1'!$C$155 | D85: ='[10]Hoja 1'!$C$157 | E85: 241842440 | O85: =+SUM(C85:N85)
B86: Menaje - Basculas-Canastillas-Estibas | E86: 241842440 | O86: =+SUM(C86:N86)
A87: 51959518 | B87: Compra Mercado IVH | D87: ='[10]Hoja 1'!$C$164 | E87: 241842440 | O87: =+SUM(C87:N87)
A88: 51959517 | B88: Convenios medicos - EMI | C88: ='[9]Hoja 1'!$C$161 | D88: ='[10]Hoja 1'!$C$163 | E88: 241842440 | O88: =+SUM(C88:N88)
B89: CASINO | C89: =CASINO!$C$144 | D89: =CASINO!$F$144 | O89: =+SUM(C89:N89)
B90: OTROS GASTOS DIVERSOS | C90: =SUM(C91:C95) | D90: =SUM(D91:D95) | E90: =SUM(E91:E95) | F90: =SUM(F91:F95) | G90: =SUM(G91:G95) | H90: =SUM(H91:H95) | I90: =SUM(I91:I95) | J90: =SUM(J91:J95) | ... O90: =SUM(O91:O95)
B91: Demandas por Incumplimiento de Contrato | E91: 241842440 | O91: =+SUM(C91:N91)
B92: Indemnizaciones | E92: 241842440 | O92: =+SUM(C92:N92)
B93: Multas, Sanciones y Litigios | C93: ='[9]Hoja 1'!$C$180 | D93: ='[10]Hoja 1'!$C$183 | E93: 241842440 | O93: =+SUM(C93:N93)
A94: 51956002 | B94: Donaciones | C94: ='[9]Hoja 1'!$C$146 | D94: ='[10]Hoja 1'!$C$148 | E94: 241842440 | O94: =+SUM(C94:N94)
A95: 53954001 | B95: Ajuste al peso | C95: ='[9]Hoja 1'!$C$182 | D95: ='[10]Hoja 1'!$C$186 | E95: 241842440 | O95: =+SUM(C95:N95)
B96: TOTAL ADMINISTRATIVOS | C96: =C5+C13+C19+C22+C28+C32+C46+C52+C59+C62+C66+C89+C90 | D96: =D5+D13+D19+D22+D28+D32+D46+D52+D59+D62+D66+D89+D90 | E96: =E5+E13+E19+E22+E28+E32+E46+E52+E59+E62+E66+E89+E90 | F96: =F5+F13+F19+F22+F28+F32+F46+F52+F59+F62+F66+F89+F90 | G96: =G5+G13+G19+G22+G28+G32+G46+G52+G59+G62+G66+G89+G90 | H96: =H5+H13+H19+H22+H28+H32+H46+H52+H59+H62+H66+H89+H90 | I96: =I5+I13+I19+I22+I28+I32+I46+I52+I59+I62+I66+I89+I90 | J96: =J5+J13+J19+J22+J28+J32+J46+J52+J59+J62+J66+J89+J90 | ... O96: =O5+O13+O19+O22+O28+O32+O46+O52+O59+O62+O66+O89+O90
B98: FINANCIEROS | C98: =SUM(C99:C107) | D98: =SUM(D99:D107) | E98: =SUM(E99:E107) | F98: =SUM(F99:F107) | G98: =SUM(G99:G107) | H98: =SUM(H99:H107) | I98: =SUM(I99:I107) | J98: =SUM(J99:J107) | ... O98: =SUM(O99:O107)
A99: 530505 | B99: Gastos Bancarios | C99: ='[9]Hoja 1'!$C$164 | D99: ='[10]Hoja 1'!$C$167 | E99: 241842440 | O99: =+SUM(C99:N99)
A100: 530515 | B100: Comisiones | C100: ='[9]Hoja 1'!$C$167 | D100: ='[10]Hoja 1'!$C$170 | E100: 241842440 | O100: =+SUM(C100:N100)
A101: 53052001 | B101: Intereses Corrientes Obligaciones | C101: ='[9]Hoja 1'!$C$172 | D101: ='[10]Hoja 1'!$C$175 | E101: 241842440 | O101: =+SUM(C101:N101)
A102: 53052002 | B102: Intereses Moratorios | C102: ='[9]Hoja 1'!$C$173 | E102: 241842440 | O102: =+SUM(C102:N102)
B103: Intereses Sobregiro | E103: 241842440 | O103: =+SUM(C103:N103)
...

Sheet GASTOS OPERATIVOS
B2: CORPORACIÓN HACIA UN VALLE SOLIDARIO | C2: 242070540
C4: ENE | D4: FEB | E4: MAR | F4: ABR | G4: MAY | H4: JUN | I4: JUL | J4: AGO | K4: SEP | L4: OCT | M4: NOV | N4: DIC | O4: ACUMULADO
B5: GASTOS DE PERSONAL | C5: =SUM(C6:C10) | D5: =SUM(D6:D10) | G5: =SUM(G6:G10) | H5: =SUM(H6:H10) | I5: =SUM(I6:I10) | J5: =SUM(J6:J10) | K5: =SUM(K6:K10) | L5: =SUM(L6:L10) | M5: =SUM(M6:M10) | N5: =SUM(N6:N10) | O5: =SUM(O6:O10)
A6: 7205 | B6: Salarios | C6: ='[21]Hoja 1'!$I$8-C9+'[22]Hoja 1'!$I$9+'[23]Hoja 1'!$D$9+'[24]Hoja 1'!$D$9+'[25]Hoja 1'!$C$91+'[26]Hoja 1'!$D$9+'[27]Hoja 1'!$E$9+'[28]Hoja 1'!$E$10 | D6: ='[29]Hoja 1'!$I$8+'[30]Hoja 1'!$I$8-D9+'[31]Hoja 1'!$I$9+'[32]Hoja 1'!$D$9+'[33]Hoja 1'!$D$9+'[34]Hoja 1'!$D$9+'[35]Hoja 1'!$I$9 | E6: 55134543 | O6: =SUM(C6:N6)
B7: Casos Especiales | C7: ='[21]Hoja 1'!$I$9+'[23]Hoja 1'!$D$10 | D7: ='[29]Hoja 1'!$I$9+'[29]Hoja 1'!$D$32+'[32]Hoja 1'!$D$10+'[36]Hoja 1'!$D$10 | E7: 241842440 | O7: =SUM(C7:N7)
B8: Incapacidades Especiales | E8: 241842440 | O8: =SUM(C8:N8)
A9: 72055101 | B9: Dotacion y Suministro | C9: ='[9]Hoja 1'!$C$218 | D9: ='[18]Hoja 1'!$C$76+'[20]Hoja 1'!$C$81-152082 | E9: 23992227 | O9: =SUM(C9:N9)
A10: 72058401 | B10: Gastos Medicos | D10: ='[10]Hoja 1'!$C$239 | E10: 23992227 | O10: =SUM(C10:N10)
B11: CUOTA DE APOYO Y SOSTENIMIENTO | E11: 23734730 | K11: 0
B12: DIVERSOS | C12: =SUM(C13:C16) | D12: =SUM(D13:D16) | G12: =SUM(G13:G16) | H12: =SUM(H13:H16) | I12: =SUM(I13:I16) | J12: =SUM(J13:J16) | K12: =SUM(K13:K16) | L12: =SUM(L13:L16) | M12: =SUM(M13:M16) | N12: =SUM(N13:N16) | O12: =SUM(O13:O16)
A13: 71101001 - 73952501 | B13: Aseo | C13: ='[9]Hoja 1'!$C$196+'[9]Hoja 1'!$C$234 | D13: ='[10]Hoja 1'!$C$201+'[10]Hoja 1'!$C$243 | E13: 23734730 | O13: =SUM(C13:N13)
A14: 73959504 | B14: Averias | C14: ='[9]Hoja 1'!$C$236 | D14: ='[10]Hoja 1'!$C$245 | O14: =SUM(C14:N14)
B15: Equipos de Bodega | E15: 23734730 | O15: =SUM(C15:N15)
A16: 51959509 - 71102001 | B16: Bioseguridad + EPP | C16: ='[9]Hoja 1'!$C$198 | D16: ='[10]Hoja 1'!$C$158+'[10]Hoja 1'!$C$203 | E16: 4115810 | O16: =SUM(C16:N16)
B17: TOTAL GASTOS | C17: =C5+C11+C12 | D17: =D5+D11+D12 | G17: =G5+G11+G12 | H17: =H5+H11+H12 | I17: =I5+I11+I12 | J17: =J5+J11+J12 | K17: =K5+K11+K12 | L17: =L5+L11+L12 | M17: =M5+M11+M12 | N17: =N5+N11+N12 | O17: =O5+O11+O12
C20: 83159889 | D20: 148056842 | E20: 166932975 | F20: 194850261 | G20: 219335066 | I20: 177744901 | J20: 217896905 | K20: 262294276 | L20: 262819240 | M20: 251102591 | N20: 223519101 | O20: =SUM(C20:N20)
C21: =C6-C20 | D21: =D6-D20 | E21: =E6-E20 | F21: =F6-F20 | G21: =G6-G20 | I21: =I6-I20 | J21: =J6-J20 | K21: =K6-K20 | L21: =L6-L20 | M21: =M6-M20 | N21: =N6-N20 | O21: =SUM(C21:N21)
C22: =C21/C20 | D22: =D21/D20 | E22: =E21/E20 | F22: =F21/F20 | G22: =G21/G20 | I22: =I21/I20 | J22: =J21/J20 | K22: =K21/K20 | L22: =L21/L20 | M22: =M21/M20 | N22: =N21/N20 | O22: =O21/O20
K25: =K20-J20 | L25: dif ago y sep 2024
K27: =K25*8 | L27: dif * 8 meses
K28: =K27+O20 | L28: 2024+dif
K29: =K28*11% | L29: incremento 11%
K30: =K28+K29 | L30: incr + 2024
K31: 535655289 | L31: 17 personas
K32: =K30+K31 | L32: 17 p +inc +2024
K33: =O6-K32 | L33: dif 2024 vs ppto
K34: =8%*K6*12 | L34: bonificacion 2025
K35: =K33-K34 | L35: dif + bonificacion

Sheet GASTOS VEHICULOS
B2: CORPORACIÓN HACIA UN VALLE SOLIDARIO | C2: PRESUPUESTO GASTOS VEHICULOS 2026
C4: ENE | D4: FEB | E4: MAR | F4: ABR | G4: MAY | H4: JUN | I4: JUL | J4: AGO | K4: SEP | L4: OCT | M4: NOV | N4: DIC | O4: ACUMULADO
B5: GASTOS DE PERSONAL | C5: =SUM(C6:C8) | D5: =SUM(D6:D8) | E5: =SUM(E6:E8) | F5: =SUM(F6:F8) | G5: =SUM(G6:G8) | H5: =SUM(H6:H8) | I5: =SUM(I6:I8) | J5: =SUM(J6:J8) | ... O5: =SUM(O6:O8)
A6: 7205 | B6: Salarios | C6: ='[22]Hoja 1'!$I$10+'[27]Hoja 1'!$E$10 | D6: ='[30]Hoja 1'!$I$9+'[31]Hoja 1'!$I$10+'[35]Hoja 1'!$I$10-D7 | O6: =SUM(C6:N6)
A7: 72055101 | B7: Dotacion | D7: 152082 | O7: =SUM(C7:N7)
B8: Gastos Medicos | O8: =SUM(C8:N8)
B9: IMPUESTOS | C9: =SUM(C10) | D9: =SUM(D10) | G9: =SUM(G10) | H9: =SUM(H10) | I9: =SUM(I10) | J9: =SUM(J10) | K9: =SUM(K10) | L9: =SUM(L10) | M9: =SUM(M10) | N9: =SUM(N10) | O9: =SUM(O10)
B10: Impuestos Vehiculo | C10: ='[9]Hoja 1'!$C$80-2676712 | E10: 241842440 | O10: =SUM(C10:N10)
B11: SEGUROS | C11: =SUM(C12:C14) | D11: =SUM(D12:D14) | G11: =SUM(G12:G14) | H11: =SUM(H12:H14) | I11: =SUM(I12:I14) | J11: =SUM(J12:J14) | K11: =SUM(K12:K14) | L11: =SUM(L12:L14) | M11: =SUM(M12:M14) | N11: =SUM(N12:N14) | O11: =SUM(O12:O14)
A12: 51303501 | B12: Sustraccion y Hurto | E12: 241842440 | O12: =SUM(C12:N12)
A13: 51304001 | B13: Flota y Equipo de Transporte | D13: ='[10]Hoja 1'!$C$93 | E13: 241842440 | O13: =SUM(C13:N13)
B14: Obligatorio Accidente de transito | C14: ='[9]Hoja 1'!$C$92 | E14: 241842440 | O14: =SUM(C14:N14)
B15: SERVICIOS | C15: =SUM(C16:C18) | D15: =SUM(D16:D18) | G15: =SUM(G16:G18) | H15: =SUM(H16:H18) | I15: =SUM(I16:I18) | J15: =SUM(J16:J18) | K15: =SUM(K16:K18) | L15: =SUM(L16:L18) | M15: =SUM(M16:M18) | N15: =SUM(N16:N18) | O15: =SUM(O16:O18)
A16: 51350502 | B16: Monitoreo | C16: ='[9]Hoja 1'!$C$95 | D16: ='[10]Hoja 1'!$C$98 | E16: 241842440 | O16: =SUM(C16:N16)
B17: Seguridad | C17: ='[12]Hoja 1'!$G$26 | D17: ='[13]Hoja 1'!$G$26 | E17: 241842440 | O17: =SUM(C17:N17)
A18: 51355001 | B18: Transporte, fletes y acarreos | C18: ='[12]Hoja 1'!$G$29 | D18: ='[13]Hoja 1'!$G$29 | O18: =SUM(C18:N18)
B19: MANTENIMIENTO Y REPARACIONES | C19: =SUM(C20:C21) | D19: =SUM(D20:D21) | G19: =SUM(G20:G21) | H19: =SUM(H20:H21) | I19: =SUM(I20:I21) | J19: =SUM(J20:J21) | K19: =SUM(K20:K21) | L19: =SUM(L20:L21) | M19: =SUM(M20:M21) | N19: =SUM(N20:N21) | O19: =SUM(O20:O21)
A20: 51454001 | B20: Mtto Preventivo | C20: 3549011 | D20: ='[10]Hoja 1'!C131 | E20: 241842440 | O20: =SUM(C20:N20)
A21: 51454002 | B21: Mtto Correctivo | C21: 2232440 | D21: ='[10]Hoja 1'!C132 | E21: 241842440 | O21: =SUM(C21:N21)
B22: DIVERSOS | C22: =SUM(C23:C24) | D22: =SUM(D23:D24) | G22: =SUM(G23:G24) | H22: =SUM(H23:H24) | I22: =SUM(I23:I24) | J22: =SUM(J23:J24) | K22: =SUM(K23:K24) | L22: =SUM(L23:L24) | M22: =SUM(M23:M24) | N22: =SUM(N23:N24) | O22: =SUM(O23:O24)
A23: 51953501 | B23: Combustible | C23: ='[9]Hoja 1'!$C$139-964175 | D23: ='[10]Hoja 1'!$C$141-1186883 | O23: =SUM(C23:N23)
B24: Compra Equipo de Transporte | C24: 8904646 | D24: 8972985 | E24: 241842440 | O24: =SUM(C24:N24)
B25: GASTOS TOTALES | C25: =C5+C9+C11+C15+C19+C22 | D25: =D5+D9+D11+D15+D19+D22 | E25: 241842440 | G25: =G5+G9+G11+G15+G19+G22 | H25: =H5+H9+H11+H15+H19+H22 | I25: =I5+I9+I11+I15+I19+I22 | J25: =J5+J9+J11+J15+J19+J22 | K25: =K5+K9+K11+K15+K19+K22 | L25: =L5+L9+L11+L15+L19+L22 | M25: =M5+M9+M11+M15+M19+M22 | N25: =N5+N9+N11+N15+N19+N22 | O25: =O5+O9+O11+O15+O19+O22

Sheet CASINO
B2: CORPORACIÓN HACIA UN VALLE SOLIDARIO | C2: PYG CASINO 2026
B3: DIAS DE ATENCIÓN | F3: 20 | I3: 20 | L3: 20 | O3: 20 | R3: 20 | U3: 20 | X3: 20 | AA3: 20 | AD3: 20 | AG3: 20 | AJ3: 20 | AM3: =SUM(C3:AL3) | AR3: VALOR RACION | AS3: COSTO | AT3: CUPOS
C4: ENE | D4: x racion | E4: % | F4: FEB | G4: x racion | H4: % | I4: MAR | J4: x racion | K4: % | L4: ABR | M4: x racion | N4: % | O4: MAY | P4: x racion | Q4: % | R4: JUN | S4: x racion | T4: % | U4: JUL | V4: x racion | W4: % | X4: AGO | Y4: x racion | Z4: % | AA4: SEP | AB4: x racion | AC4: % | AD4: OCT | AE4: x racion | AF4: % | AG4: NOV | AH4: x racion | AI4: % | AJ4: DIC | AK4: x racion | AL4: % | AM4: ACUMULADO | AN4: x racion | AO4: %
B5: Cupos | C5: =C$3*$AR$7*$AT$4 | AM5: =C5+F5+I5+L5+O5+R5+U5+X5+AA5+AD5+AG5+AJ5 | AQ5: ALMUERZO
AM6: =C6+F6+I6+L6+O6+R6+U6+X6+AA6+AD6+AG6+AJ6 | AQ6: DESAYUNO
AM7: =C7+F7+I7+L7+O7+R7+U7+X7+AA7+AD7+AG7+AJ7 | AQ7: % Facturacion | AR7: 1
AM8: =C8+F8+I8+L8+O8+R8+U8+X8+AA8+AD8+AG8+AJ8
AM9: =C9+F9+I9+L9+O9+R9+U9+X9+AA9+AD9+AG9+AJ9
AM10: =C10+F10+I10+L10+O10+R10+U10+X10+AA10+AD10+AG10+AJ10
AM11: =C11+F11+I11+L11+O11+R11+U11+X11+AA11+AD11+AG11+AJ11
B12: TOTAL RACIONES | C12: =SUM(C5:C11) | F12: =SUM(F5:F11) | I12: =SUM(I5:I11) | L12: =SUM(L5:L11) | O12: =SUM(O5:O11) | R12: =SUM(R5:R11) | U12: =SUM(U5:U11) | X12: =SUM(X5:X11) | AA12: =SUM(AA5:AA11) | AD12: =SUM(AD5:AD11) | AG12: =SUM(AG5:AG11) | AJ12: =SUM(AJ5:AJ11) | AM12: =C12+F12+I12+L12+O12+R12+U12+X12+AA12+AD12+AG12+AJ12
B13: INGRESOS BRUTOS | C13: =C14+C23 | F13: =F14+F23 | I13: =I14+I23 | L13: =L14+L23 | O13: =O14+O23 | R13: =R14+R23 | U13: =U14+U23 | X13: =X14+X23 | AA13: =AA14+AA23 | AD13: =AD14+AD23 | AG13: =AG14+AG23 | AJ13: =AJ14+AJ23 | AM13: =C13+F13+I13+L13+O13+R13+U13+X13+AA13+AD13+AG13+AJ13
B14: OPERACIONALES | C14: =C15 | F14: =F15 | I14: =I15 | L14: =L15 | O14: =O15 | R14: =R15 | U14: =U15 | X14: =X15 | AA14: =AA15 | AD14: =AD15 | AG14: =AG15 | AJ14: =AJ15 | AM14: =C14+F14+I14+L14+O14+R14+U14+X14+AA14+AD14+AG14+AJ14
B15: INDUSTRIAS MANUFACTURERAS | C15: =SUM(C16:C22) | F15: =SUM(F16:F22) | I15: =SUM(I16:I22) | L15: =SUM(L16:L22) | O15: =SUM(O16:O22) | R15: =SUM(R16:R22) | U15: =SUM(U16:U22) | X15: =SUM(X16:X22) | AA15: =SUM(AA16:AA22) | AD15: =SUM(AD16:AD22) | AG15: =SUM(AG16:AG22) | AJ15: =SUM(AJ16:AJ22) | AM15: =C15+F15+I15+L15+O15+R15+U15+X15+AA15+AD15+AG15+AJ15
A16: 42959502 | C16: ='[9]Hoja 1'!$E$24+'[9]Hoja 1'!$E$327+'[9]Hoja 1'!$E$540+'[9]Hoja 1'!$E$604+'[9]Hoja 1'!$E$643+'[37]Hoja 1'!$E$21+'[37]Hoja 1'!$E$107+'[37]Hoja 1'!$E$144+'[37]Hoja 1'!$E$181+'[37]Hoja 1'!$E$253+'[38]Hoja 1'!$E$21+'[25]Hoja 1'!$E$23+'[39]Hoja 1'!$E$23+'[16]Hoja 1'!$F$23+'[17]Hoja 1'!$E$24 | F16: ='[10]Hoja 1'!$E$26+'[10]Hoja 1'!$E$321+'[10]Hoja 1'!$E$503+'[10]Hoja 1'!$E$575+'[18]Hoja 1'!$E$20+'[18]Hoja 1'!$E$101+'[18]Hoja 1'!$E$142+'[11]Hoja 1'!$E$21+'[40]Hoja 1'!$E$21+'[19]Hoja 1'!$E$19+'[19]Hoja 1'!$E$98+'[41]Hoja 1'!$E$23+'[42]Hoja 1'!$E$27+'[20]Hoja 1'!$E$23+'[20]Hoja 1'!$E$106+'[20]Hoja 1'!$E$147 | I16: 241842441 | L16: 241842441 | AM16: =C16+F16+I16+L16+O16+R16+U16+X16+AA16+AD16+AG16+AJ16
AM17: =C17+F17+I17+L17+O17+R17+U17+X17+AA17+AD17+AG17+AJ17
I18: =I7*$AR$6 | L18: =L7*$AR$6 | O18: =O7*$AR$6 | R18: =R7*$AR$6 | U18: =U7*$AR$6 | AM18: =C18+F18+I18+L18+O18+R18+U18+X18+AA18+AD18+AG18+AJ18
B19: NOVEDADES | AM19: =C19+F19+I19+L19+O19+R19+U19+X19+AA19+AD19+AG19+AJ19
AM20: =C20+F20+I20+L20+O20+R20+U20+X20+AA20+AD20+AG20+AJ20
AM21: =C21+F21+I21+L21+O21+R21+U21+X21+AA21+AD21+AG21+AJ21
AM22: =C22+F22+I22+L22+O22+R22+U22+X22+AA22+AD22+AG22+AJ22
B23: NO OPERACIONALES | C23: =C24 | F23: =F24 | I23: =I24 | L23: =L24 | O23: =O24 | R23: =R24 | U23: =U24 | X23: =X24 | AA23: =AA24 | AM23: =C23+F23+I23+L23+O23+R23+U23+X23+AA23+AD23+AG23+AJ23
B24: FINANCIEROS | C24: =SUM(C25:C27) | F24: =SUM(F25:F27) | I24: =SUM(I25:I27) | L24: =SUM(L25:L27) | O24: =SUM(O25:O27) | R24: =SUM(R25:R27) | U24: =SUM(U25:U27) | X24: =SUM(X25:X27) | AA24: =SUM(AA25:AA27) | AD24: =SUM(AD25:AD27) | AG24: =SUM(AG25:AG27) | AJ24: =SUM(AJ25:AJ27) | AM24: =C24+F24+I24+L24+O24+R24+U24+X24+AA24+AD24+AG24+AJ24
B25: Intereses | AM25: =C25+F25+I25+L25+O25+R25+U25+X25+AA25+AD25+AG25+AJ25
B26: Descuentos Comerciales | AM26: =C26+F26+I26+L26+O26+R26+U26+X26+AA26+AD26+AG26+AJ26
B27: otros | AM27: =C27+F27+I27+L27+O27+R27+U27+X27+AA27+AD27+AG27+AJ27
B28: DESCUENTOS - GASTO OPERACIONAL | C28: =+C29 | F28: =+F29 | I28: =+I29 | L28: =+L29 | O28: =+O29 | R28: =+R29 | U28: =+U29 | X28: =+X29 | AA28: =+AA29 | AD28: =+AD29 | AG28: =+AG29 | AJ28: =+AJ29 | AM28: =C28+F28+I28+L28+O28+R28+U28+X28+AA28+AD28+AG28+AJ28
B29: OTROS | C29: =SUM(C30:C35) | F29: =SUM(F30:F35) | H29: =F29/F13 | I29: =SUM(I30:I35) | K29: =I29/I13 | L29: =SUM(L30:L35) | N29: =L29/L13 | O29: =SUM(O30:O35) | Q29: =O29/O13 | R29: =SUM(R30:R35) | T29: =R29/R13 | U29: =SUM(U30:U35) | W29: =U29/U13 | X29: =SUM(X30:X35) | Z29: =X29/X13 | AA29: =SUM(AA30:AA35) | AC29: =AA29/AA13 | AD29: =SUM(AD30:AD35) | AF29: =AD29/AD13 | AG29: =SUM(AG30:AG35) | AI29: =AG29/AG13 | AJ29: =SUM(AJ30:AJ35) | AM29: =C29+F29+I29+L29+O29+R29+U29+X29+AA29+AD29+AG29+AJ29 | AO29: =AM29/AM13
AM30: =C30+F30+I30+L30+O30+R30+U30+X30+AA30+AD30+AG30+AJ30
AM31: =C31+F31+I31+L31+O31+R31+U31+X31+AA31+AD31+AG31+AJ31
AM32: =C32+F32+I32+L32+O32+R32+U32+X32+AA32+AD32+AG32+AJ32
AM33: =C33+F33+I33+L33+O33+R33+U33+X33+AA33+AD33+AG33+AJ33
AM34: =C34+F34+I34+L34+O34+R34+U34+X34+AA34+AD34+AG34+AJ34
AM35: =C35+F35+I35+L35+O35+R35+U35+X35+AA35+AD35+AG35+AJ35
B42: TOTAL INGRESOS NETOS | C42: =+C14+C23-C28 | F42: =+F14+F23-F28 | I42: =+I14+I23-I28 | L42: =+L14+L23-L28 | O42: =+O14+O23-O28 | R42: =+R14+R23-R28 | U42: =+U14+U23-U28 | X42: =+X14+X23-X28 | AA42: =+AA14+AA23-AA28 | AD42: =+AD14+AD23-AD28 | AG42: =+AG14+AG23-AG28 | AJ42: =+AJ14+AJ23-AJ28 | AM42: =C42+F42+I42+L42+O42+R42+U42+X42+AA42+AD42+AG42+AJ42
B44: COSTOS DE PRODUCCION | C44: =+C45+C60+C78 | F44: =+F45+F60+F78 | I44: =+I45+I60+I78 | L44: =+L45+L60+L78 | O44: =+O45+O60+O78 | R44: =+R45+R60+R78 | U44: =+U45+U60+U78 | X44: =+X45+X60+X78 | AA44: =+AA45+AA60+AA78 | AD44: =+AD45+AD60+AD78 | AG44: =+AG45+AG60+AG78 | AJ44: =+AJ45+AJ60+AJ78 | AM44: =C44+F44+I44+L44+O44+R44+U44+X44+AA44+AD44+AG44+AJ44
B45: COSTOS INDUSTRIALIZADOS | AM45: =C45+F45+I45+L45+O45+R45+U45+X45+AA45+AD45+AG45+AJ45 | AO45: =AM45/AM$13
B46: INSUMOS | AM46: =C46+F46+I46+L46+O46+R46+U46+X46+AA46+AD46+AG46+AJ46
AM47: =C47+F47+I47+L47+O47+R47+U47+X47+AA47+AD47+AG47+AJ47 | AO47: =AM47/AM$16
AM48: =C48+F48+I48+L48+O48+R48+U48+X48+AA48+AD48+AG48+AJ48
AM49: =C49+F49+I49+L49+O49+R49+U49+X49+AA49+AD49+AG49+AJ49
AM50: =C50+F50+I50+L50+O50+R50+U50+X50+AA50+AD50+AG50+AJ50
AM51: =C51+F51+I51+L51+O51+R51+U51+X51+AA51+AD51+AG51+AJ51
AM52: =C52+F52+I52+L52+O52+R52+U52+X52+AA52+AD52+AG52+AJ52
AM53: =C53+F53+I53+L53+O53+R53+U53+X53+AA53+AD53+AG53+AJ53
AM57: =C57+F57+I57+L57+O57+R57+U57+X57+AA57+AD57+AG57+AJ57
B58: Flete Industrializados PROPIOS | I58: 241842441 | L58: 241842441 | AM58: =C58+F58+I58+L58+O58+R58+U58+X58+AA58+AD58+AG58+AJ58 | AO58: =AM58/AM$16
B59: Flete Industrializados TERCEROS | AM59: =C59+F59+I59+L59+O59+R59+U59+X59+AA59+AD59+AG59+AJ59 | AO59: =AM59/(AM16)
B60: COSTOS ALMUERZO | C60: =+C61+C73+C74+C75+C76+C77 | F60: =+F61+F73+F74+F75+F76+F77 | I60: =+I61+I73+I74+I75+I76+I77 | L60: =+L61+L73+L74+L75+L76+L77 | O60: =+O61+O73+O74+O75+O76+O77 | R60: =+R61+R73+R74+R75+R76+R77 | U60: =+U61+U73+U74+U75+U76+U77 | X60: =+X61+X73+X74+X75+X76+X77 | AA60: =+AA61+AA73+AA74+AA75+AA76+AA77 | AD60: =+AD61+AD73+AD74+AD75+AD76+AD77 | AG60: =+AG61+AG73+AG74+AG75+AG76+AG77 | AJ60: =+AJ61+AJ73+AJ74+AJ75+AJ76+AJ77 | AM60: =C60+F60+I60+L60+O60+R60+U60+X60+AA60+AD60+AG60+AJ60
B61: INSUMOS | C61: =SUM(C62:C71)+C72 | F61: =SUM(F62:F71)+F72 | I61: =SUM(I62:I71)+I72 | L61: =SUM(L62:L71)+L72 | O61: =SUM(O62:O71)+O72 | R61: =SUM(R62:R71)+R72 | U61: =SUM(U62:U71)+U72 | X61: =SUM(X62:X71)+X72 | AA61: =SUM(AA62:AA71)+AA72 | AD61: =SUM(AD62:AD71)+AD72 | AG61: =SUM(AG62:AG71)+AG72 | AJ61: =SUM(AJ62:AJ71)+AJ72 | AM61: =C61+F61+I61+L61+O61+R61+U61+X61+AA61+AD61+AG61+AJ61
A62: 51956001 | B62: Desayuno y Almuerzo | C62: ='[9]Hoja 1'!$C$245 | F62: ='[10]Hoja 1'!$C$254 | I62: 241842440 | L62: 241842440 | AM62: =C62+F62+I62+L62+O62+R62+U62+X62+AA62+AD62+AG62+AJ62
A63: 7105 | C63: ='[9]Hoja 1'!$C$251 | F63: ='[10]Hoja 1'!$C$260 | I63: 241842440 | L63: 241842440 | AM63: =C63+F63+I63+L63+O63+R63+U63+X63+AA63+AD63+AG63+AJ63
AM64: =C64+F64+I64+L64+O64+R64+U64+X64+AA64+AD64+AG64+AJ64
AM65: =C65+F65+I65+L65+O65+R65+U65+X65+AA65+AD65+AG65+AJ65
AM66: =C66+F66+I66+L66+O66+R66+U66+X66+AA66+AD66+AG66+AJ66
AM71: =C71+F71+I71+L71+O71+R71+U71+X71+AA71+AD71+AG71+AJ71
B72: Transporte Materia Prima - Cavasa | AM72: =C72+F72+I72+L72+O72+R72+U72+X72+AA72+AD72+AG72+AJ72 | AO72: =AM72/(AM17+AM18)
B73: Flete Preparados PROPIOS | AM73: =C73+F73+I73+L73+O73+R73+U73+X73+AA73+AD73+AG73+AJ73 | AO73: =AM73/(AM17+AM18)
B74: Flete Preparados TERCEROS | AM74: =C74+F74+I74+L74+O74+R74+U74+X74+AA74+AD74+AG74+AJ74 | AO74: =AM74/(AM17+AM18)
B75: Material de empaque | AM75: =C75+F75+I75+L75+O75+R75+U75+X75+AA75+AD75+AG75+AJ75
B76: Menaje | C76: ='[9]Hoja 1'!$C$256 | F76: ='[10]Hoja 1'!$C$265 | I76: 241842440 | L76: 241842440 | AM76: =C76+F76+I76+L76+O76+R76+U76+X76+AA76+AD76+AG76+AJ76
A77: 73355501 | B77: Servicio de Gas | C77: ='[9]Hoja 1'!$C$260 | F77: ='[10]Hoja 1'!$C$269 | I77: 241842440 | L77: 241842440 | AM77: =C77+F77+I77+L77+O77+R77+U77+X77+AA77+AD77+AG77+AJ77
B78: MANO DE OBRA DIRECTA | C78: =SUM(C79:C81) | F78: =SUM(F79:F81) | I78: =SUM(I79:I81) | L78: =SUM(L79:L81) | O78: =SUM(O79:O81) | R78: =SUM(R79:R81) | U78: =SUM(U79:U81) | X78: =SUM(X79:X81) | AA78: =SUM(AA79:AA81) | AD78: =SUM(AD79:AD81) | AG78: =SUM(AG79:AG81) | AJ78: =SUM(AJ79:AJ81) | AM78: =C78+F78+I78+L78+O78+R78+U78+X78+AA78+AD78+AG78+AJ78 | AO78: =AM78/(AM$13)
B79: Manipuladoras | C79: ='[1]Hoja 1'!$I$11-C86+'[2]Hoja 1'!$I$10+'[43]Hoja 1'!$D$9 | F79: ='[4]Hoja 1'!$I$10-F86+'[5]Hoja 1'!$I$10+'[8]Hoja 1'!$I$10 | I79: 241842440 | L79: 241842440 | AM79: =C79+F79+I79+L79+O79+R79+U79+X79+AA79+AD79+AG79+AJ79 | AO79: =AM79/(AM$13)
AM80: =C80+F80+I80+L80+O80+R80+U80+X80+AA80+AD80+AG80+AJ80
AM81: =C81+F81+I81+L81+O81+R81+U81+X81+AA81+AD81+AG81+AJ81
B83: OTROS COSTOS Y GASTOS INDIRECTOS | C83: =+C84+C88+C91+C95+C98+C108+C113+C119+C122+C126 | F83: =+F84+F88+F91+F95+F98+F108+F113+F119+F122+F126 | H83: =F83/(F$13) | I83: =+I84+I88+I91+I95+I98+I108+I113+I119+I122+I126 | K83: =I83/(I$13) | L83: =+L84+L88+L91+L95+L98+L108+L113+L119+L122+L126 | N83: =L83/(L$13) | O83: =+O84+O88+O91+O95+O98+O108+O113+O119+O122+O126 | R83: =+R84+R88+R91+R95+R98+R108+R113+R119+R122+R126 | U83: =+U84+U88+U91+U95+U98+U108+U113+U119+U122+U126 | W83: =U83/(U$13) | X83: =+X84+X88+X91+X95+X98+X108+X113+X119+X122+X126 | Z83: =X83/(X$13) | AA83: =+AA84+AA88+AA91+AA95+AA98+AA108+AA113+AA119+AA122+AA126 | AC83: =AA83/(AA$13) | AD83: =+AD84+AD88+AD91+AD95+AD98+AD108+AD113+AD119+AD122+AD126 | AF83: =AD83/(AD$13) | AG83: =+AG84+AG88+AG91+AG95+AG98+AG108+AG113+AG119+AG122+AG126 | AI83: =AG83/(AG$13) | AJ83: =+AJ84+AJ88+AJ91+AJ95+AJ98+AJ108+AJ113+AJ119+AJ122+AJ126 | AM83: =C83+F83+I83+L83+O83+R83+U83+X83+AA83+AD83+AG83+AJ83 | AO83: =AM83/(AM$13)
B84: COSTOS DE PERSONAL | C84: =SUM(C85:C87) | F84: =SUM(F85:F87) | H84: =F84/(F$13) | I84: =SUM(I85:I87) | K84: =I84/(I$13) | L84: =SUM(L85:L87) | N84: =L84/(L$13) | O84: =SUM(O85:O87) | R84: =SUM(R85:R87) | U84: =SUM(U85:U87) | W84: =U84/(U$13) | X84: =SUM(X85:X87) | Z84: =X84/(X$13) | AA84: =SUM(AA85:AA87) | AC84: =AA84/(AA$13) | AD84: =SUM(AD85:AD87) | AF84: =AD84/(AD$13) | AG84: =SUM(AG85:AG87) | AI84: =AG84/(AG$13) | AJ84: =SUM(AJ85:AJ87) | AM84: =C84+F84+I84+L84+O84+R84+U84+X84+AA84+AD84+AG84+AJ84 | AO84: =AM84/(AM$13)
B85: Costos Indirectos de Personal | I85: 241842440 | L85: 241842440 | AM85: =C85+F85+I85+L85+O85+R85+U85+X85+AA85+AD85+AG85+AJ85 | AO85: =AM85/(AM$13)
B86: Dotación y Suministros | C86: 225638 | F86: 59862 | I86: 241842440 | L86: 241842440 | AM86: =C86+F86+I86+L86+O86+R86+U86+X86+AA86+AD86+AG86+AJ86
B87: Gastos Medicos | I87: 241842440 | L87: 241842440 | AM87: =C87+F87+I87+L87+O87+R87+U87+X87+AA87+AD87+AG87+AJ87
B88: HONORARIOS | C88: =SUM(C89:C90) | F88: =SUM(F89:F90) | H88: =F88/(F$13) | I88: =SUM(I89:I90) | K88: =I88/(I$13) | L88: =SUM(L89:L90) | N88: =L88/(L$13) | O88: =SUM(O89:O90) | R88: =SUM(R89:R90) | U88: =SUM(U89:U90) | W88: =U88/(U$13) | X88: =SUM(X89:X90) | Z88: =X88/(X$13) | AA88: =SUM(AA89:AA90) | AC88: =AA88/(AA$13) | AD88: =SUM(AD89:AD90) | AF88: =AD88/(AD$13) | AG88: =SUM(AG89:AG90) | AI88: =AG88/(AG$13) | AJ88: =SUM(AJ89:AJ90) | AM88: =C88+F88+I88+L88+O88+R88+U88+X88+AA88+AD88+AG88+AJ88 | AO88: =AM88/(AM$13)
B89: Asesoría Juridica | I89: 241842440 | L89: 241842440 | AM89: =C89+F89+I89+L89+O89+R89+U89+X89+AA89+AD89+AG89+AJ89
B90: Asesoría Tecnica | I90: 241842440 | L90: 241842440 | AM90: =C90+F90+I90+L90+O90+R90+U90+X90+AA90+AD90+AG90+AJ90
B91: ARRENDAMIENTOS | C91: =SUM(C92:C94) | F91: =SUM(F92:F94) | H91: =F91/(F$13) | I91: =SUM(I92:I94) | K91: =I91/(I$13) | L91: =SUM(L92:L94) | N91: =L91/(L$13) | O91: =SUM(O92:O94) | R91: =SUM(R92:R94) | U91: =SUM(U92:U94) | W91: =U91/(U$13) | X91: =SUM(X92:X94) | Z91: =X91/(X$13) | AA91: =SUM(AA92:AA94) | AC91: =AA91/(AA$13) | AD91: =SUM(AD92:AD94) | AF91: =AD91/(AD$13) | AG91: =SUM(AG92:AG94) | AI91: =AG91/(AG$13) | AJ91: =SUM(AJ92:AJ94) | AM91: =C91+F91+I91+L91+O91+R91+U91+X91+AA91+AD91+AG91+AJ91 | AO91: =AM91/(AM$13)
B92: Construcciones y Edificaciones | AM92: =C92+F92+I92+L92+O92+R92+U92+X92+AA92+AD92+AG92+AJ92
B93: Maquinaria y Equipo | AM93: =C93+F93+I93+L93+O93+R93+U93+X93+AA93+AD93+AG93+AJ93
B94: Equipo de Oficina | AM94: =C94+F94+I94+L94+O94+R94+U94+X94+AA94+AD94+AG94+AJ94
B95: SEGUROS | C95: =SUM(C96:C97) | F95: =SUM(F96:F97) | H95: =F95/(F$13) | I95: =SUM(I96:I97) | K95: =I95/(I$13) | L95: =SUM(L96:L97) | N95: =L95/(L$13) | O95: =SUM(O96:O97) | R95: =SUM(R96:R97) | U95: =SUM(U96:U97) | W95: =U95/(U$13) | X95: =SUM(X96:X97) | Z95: =X95/(X$13) | AA95: =SUM(AA96:AA97) | AC95: =AA95/(AA$13) | AD95: =SUM(AD96:AD97) | AF95: =AD95/(AD$13) | AG95: =SUM(AG96:AG97) | AI95: =AG95/(AG$13) | AJ95: =SUM(AJ96:AJ97) | AM95: =C95+F95+I95+L95+O95+R95+U95+X95+AA95+AD95+AG95+AJ95 | AO95: =AM95/(AM$13)
B96: Cumplimiento | I96: 241842440 | L96: 241842440 | AM96: =C96+F96+I96+L96+O96+R96+U96+X96+AA96+AD96+AG96+AJ96
B97: Respomsabilidad Civil Y Extracontractual | I97: 241842440 | L97: 241842440 | AM97: =C97+F97+I97+L97+O97+R97+U97+X97+AA97+AD97+AG97+AJ97
B98: SERVICIOS | C98: =SUM(C99:C107) | F98: =SUM(F99:F107) | H98: =F98/(F$13) | I98: =SUM(I99:I105) | K98: =I98/(I$13) | L98: =SUM(L99:L107) | N98: =L98/(L$13) | O98: =SUM(O99:O107) | R98: =SUM(R99:R107) | U98: =SUM(U99:U107) | W98: =U98/(U$13) | X98: =SUM(X99:X107) | Z98: =X98/(X$13) | AA98: =SUM(AA99:AA107) | AC98: =AA98/(AA$13) | AD98: =SUM(AD99:AD107) | AF98: =AD98/(AD$13) | AG98: =SUM(AG99:AG107) | AI98: =AG98/(AG$13) | AJ98: =SUM(AJ99:AJ107) | AM98: =C98+F98+I98+L98+O98+R98+U98+X98+AA98+AD98+AG98+AJ98 | AO98: =AM98/(AM$13)
B99: Aseo y Vigilancia | I99: 241842440 | L99: 241842440 | AM99: =C99+F99+I99+L99+O99+R99+U99+X99+AA99+AD99+AG99+AJ99
B100: Temporales | I100: 241842440 | L100: 241842440 | AM100: =C100+F100+I100+L100+O100+R100+U100+X100+AA100+AD100+AG100+AJ100
B101: Mensajeria | I101: 241842440 | L101: 241842440 | AM101: =C101+F101+I101+L101+O101+R101+U101+X101+AA101+AD101+AG101+AJ101
B102: Laboratorio | I102: 241842440 | L102: 241842440 | AM102: =C102+F102+I102+L102+O102+R102+U102+X102+AA102+AD102+AG102+AJ102
B103: Fumigacion | I103: 241842440 | L103: 241842440 | AM103: =C103+F103+I103+L103+O103+R103+U103+X103+AA103+AD103+AG103+AJ103
B104: Acueducto y Alcantarillado | I104: 241842440 | L104: 241842440 | AM104: =C104+F104+I104+L104+O104+R104+U104+X104+AA104+AD104+AG104+AJ104
B105: Energia | I105: 241842440 | L105: 241842440 | AM105: =C105+F105+I105+L105+O105+R105+U105+X105+AA105+AD105+AG105+AJ105
B106: Telefono e Internet | I106: 241842440 | L106: 241842440 | AM106: =C106+F106+I106+L106+O106+R106+U106+X106+AA106+AD106+AG106+AJ106
B107: Correo, porte y telegramas | I107: 241842440 | L107: 241842440 | AM107: =C107+F107+I107+L107+O107+R107+U107+X107+AA107+AD107+AG107+AJ107
B108: GASTOS LEGALES | C108: =SUM(C109:C112) | F108: =SUM(F109:F112) | H108: =F108/(F$13) | I108: =SUM(I109:I112) | K108: =I108/(I$13) | L108: =SUM(L109:L112) | N108: =L108/(L$13) | O108: =SUM(O109:O112) | R108: =SUM(R109:R112) | U108: =SUM(U109:U112) | W108: =U108/(U$13) | X108: =SUM(X109:X112) | Z108: =X108/(X$13) | AA108: =SUM(AA109:AA112) | AC108: =AA108/(AA$13) | AD108: =SUM(AD109:AD112) | AF108: =AD108/(AD$13) | AG108: =SUM(AG109:AG112) | AI108: =AG108/(AG$13) | AJ108: =SUM(AJ109:AJ112) | AM108: =C108+F108+I108+L108+O108+R108+U108+X108+AA108+AD108+AG108+AJ108 | AO108: =AM108/(AM$13)
B109: Notariales | I109: 241842440 | L109: 241842440 | AM109: =C109+F109+I109+L109+O109+R109+U109+X109+AA109+AD109+AG109+AJ109
B110: Registro Mercantil | I110: 241842440 | L110: 241842440 | AM110: =C110+F110+I110+L110+O110+R110+U110+X110+AA110+AD110+AG110+AJ110
B111: Trámites y Licencias | I111: 241842440 | L111: 241842440 | AM111: =C111+F111+I111+L111+O111+R111+U111+X111+AA111+AD111+AG111+AJ111
B112: Certificados Camara Comercio | I112: 241842440 | L112: 241842440 | AM112: =C112+F112+I112+L112+O112+R112+U112+X112+AA112+AD112+AG112+AJ112
B113: MANTENIMIENTO Y REPARACIONES | C113: =SUM(C114:C118) | F113: =SUM(F114:F118) | H113: =F113/(F$13) | I113: =SUM(I114:I118) | K113: =I113/(I$13) | L113: =SUM(L114:L118) | N113: =L113/(L$13) | O113: =SUM(O114:O115) | R113: =SUM(R114:R118) | U113: =SUM(U114:U118) | W113: =U113/(U$13) | X113: =SUM(X114:X115) | Z113: =X113/(X$13) | AA113: =SUM(AA114:AA118) | AC113: =AA113/(AA$13) | AD113: =SUM(AD114:AD118) | AF113: =AD113/(AD$13) | AG113: =SUM(AG114:AG118) | AI113: =AG113/(AG$13) | AJ113: =SUM(AJ114:AJ118) | AM113: =C113+F113+I113+L113+O113+R113+U113+X113+AA113+AD113+AG113+AJ113 | AO113: =AM113/(AM$13)
B114: Construcciones y Edificaciones | I114: 286665474 | L114: 286665474 | AM114: =C114+F114+I114+L114+O114+R114+U114+X114+AA114+AD114+AG114+AJ114
B115: Maquinaria y Equipo | I115: 245958250 | L115: 245958250 | AM115: =C115+F115+I115+L115+O115+R115+U115+X115+AA115+AD115+AG115+AJ115
A116: 73451502 | B116: Equipos de Cocina | I116: 5705110 | L116: 5705110 | AM116: =C116+F116+I116+L116+O116+R116+U116+X116+AA116+AD116+AG116+AJ116
...

Sheet HUNGRIA
B2: CORPORACIÓN HACIA UN VALLE SOLIDARIO | C2: PRESUPUESTO SANTA ISABEL DE HUNGRIA 2024
B3: DIAS DE ATENCIÓN | I3: 18 | L3: 15 | O3: 21 | R3: 20 | U3: 6 | X3: 21 | AA3: 21 | AD3: 16 | AG3: 20 | AM3: =SUM(I3:AL3)
C4: ENE | D4: x racion | E4: % | F4: FEB | G4: x racion | H4: % | I4: MAR | J4: x racion | K4: % | L4: ABR | M4: x racion | N4: % | O4: MAY | P4: x racion | Q4: % | R4: JUN | S4: x racion | T4: % | U4: JUL | V4: x racion | W4: % | X4: AGO | Y4: x racion | Z4: % | AA4: SEP | AB4: x racion | AC4: % | AD4: OCT | AE4: x racion | AF4: % | AG4: NOV | AH4: x racion | AI4: % | AJ4: DIC | AK4: x racion | AL4: % | AM4: ACUMULADO | AN4: x racion | AO4: % | AQ4: REAL 2024
B5: COMPLEMENTO INDUSTRIALIZADO (Rac) | AM5: =C5+F5+I5+L5+O5+R5+U5+X5+AA5+AD5+AG5+AJ5
AM6: =C6+F6+I6+L6+O6+R6+U6+X6+AA6+AD6+AG6+AJ6
AM7: =C7+F7+I7+L7+O7+R7+U7+X7+AA7+AD7+AG7+AJ7
AM8: =C8+F8+I8+L8+O8+R8+U8+X8+AA8+AD8+AG8+AJ8
B9: NOVEDADES (Rac) | AM9: =C9+F9+I9+L9+O9+R9+U9+X9+AA9+AD9+AG9+AJ9
B12: TOTAL RACIONES | C12: =SUM(C5:C11) | F12: =SUM(F5:F11) | I12: =SUM(I5:I11) | L12: =SUM(L5:L11) | O12: =SUM(O5:O11) | R12: =SUM(R5:R11) | U12: =SUM(U5:U11) | X12: =SUM(X5:X11) | AA12: =SUM(AA5:AA11) | AD12: =SUM(AD5:AD11) | AG12: =SUM(AG5:AG11) | AJ12: =SUM(AJ5:AJ11) | AM12: =C12+F12+I12+L12+O12+R12+U12+X12+AA12+AD12+AG12+AJ12 | AQ12: =SUM(AQ5:AQ11)
B13: INGRESOS BRUTOS | C13: =C14+C23 | F13: =F14+F23 | I13: =I14+I23 | L13: =L14+L23 | O13: =O14+O23 | R13: =R14+R23 | U13: =U14+U23 | X13: =X14+X23 | AA13: =AA14+AA23 | AD13: =AD14+AD23 | AG13: =AG14+AG23 | AM13: =C13+F13+I13+L13+O13+R13+U13+X13+AA13+AD13+AG13+AJ13 | AQ13: =AQ14+AQ23
B14: OPERACIONALES | C14: =C15 | F14: =F15 | I14: =I15 | L14: =L15 | O14: =O15 | R14: =R15 | U14: =U15 | X14: =X15 | AA14: =AA15 | AD14: =AD15 | AG14: =AG15 | AM14: =C14+F14+I14+L14+O14+R14+U14+X14+AA14+AD14+AG14+AJ14 | AQ14: =AQ15
B15: INDUSTRIAS MANUFACTURERAS | C15: =C16+C17+C18+C19+C20 | F15: =F16+F17+F18+F19+F20 | H15: =F15/F15 | I15: =I16+I17+I18+I19+I20 | K15: =I15/I15 | L15: =L16+L17+L18+L19+L20 | N15: =L15/L15 | O15: =O16+O17+O18+O19+O20 | Q15: =O15/O15 | R15: =R16+R17+R18+R19+R20 | T15: =R15/R15 | U15: =U16+U17+U18+U19+U20 | X15: =X16+X17+X18+X19+X20 | Z15: =X15/X15 | AA15: =AA16+AA17+AA18+AA19+AA20 | AD15: =AD16+AD17+AD18+AD19+AD20 | AG15: =AG16+AG17+AG18+AG19+AG20 | AM15: =C15+F15+I15+L15+O15+R15+U15+X15+AA15+AD15+AG15+AJ15 | AO15: =AM15/AM15 | AQ15: =SUM(AQ16:AQ22)
B16: COMPLEMENTO INDUSTRIALIZADO (Fac) | G16: =F16/F5 | J16: =I16/I5 | M16: =L16/L5 | S16: =R16/R5 | Y16: =X16/X5 | AB16: =AA16/AA5 | AE16: =AD16/AD5 | AH16: =AG16/AG5 | AM16: =C16+F16+I16+L16+O16+R16+U16+X16+AA16+AD16+AG16+AJ16 | AO16: =AM16/AM$13 | AR16: =AQ16/AQ5
AM17: =C17+F17+I17+L17+O17+R17+U17+X17+AA17+AD17+AG17+AJ17
AM18: =C18+F18+I18+L18+O18+R18+U18+X18+AA18+AD18+AG18+AJ18
AM19: =C19+F19+I19+L19+O19+R19+U19+X19+AA19+AD19+AG19+AJ19
B20: NOVEDADES (Fac) | J20: =I20/I9 | M20: =L20/L9 | P20: =O20/O9 | S20: =R20/R9 | V20: =U20/U9 | AG20: =AG9*2497 | AM20: =C20+F20+I20+L20+O20+R20+U20+X20+AA20+AD20+AG20+AJ20
B23: NO OPERACIONALES | C23: =C24 | F23: =F24 | I23: =I24 | L23: =L24 | O23: =O24 | R23: =R24 | U23: =U24 | X23: =X24 | AA23: =AA24 | AD23: =AD24 | AG23: =AG24 | AM23: =C23+F23+I23+L23+O23+R23+U23+X23+AA23+AD23+AG23+AJ23
B24: FINANCIEROS | C24: =SUM(C25:C27) | F24: =SUM(F25:F27) | I24: =SUM(I25:I27) | L24: =SUM(L25:L27) | O24: =SUM(O25:O27) | R24: =SUM(R25:R27) | U24: =SUM(U25:U27) | X24: =X25+X26+X27 | AA24: =AA25+AA26+AA27 | AD24: =AD25+AD26+AD27 | AG24: =AG25+AG26+AG27 | AM24: =C24+F24+I24+L24+O24+R24+U24+X24+AA24+AD24+AG24+AJ24
B25: Intereses | AM25: =C25+F25+I25+L25+O25+R25+U25+X25+AA25+AD25+AG25+AJ25
B26: Descuentos Comerciales | AM26: =C26+F26+I26+L26+O26+R26+U26+X26+AA26+AD26+AG26+AJ26
B27: otros Fin | AM27: =C27+F27+I27+L27+O27+R27+U27+X27+AA27+AD27+AG27+AJ27
B28: DESCUENTOS - GASTO OPERACIONAL | C28: =+C29 | F28: =+F29 | I28: =+I29 | L28: =+L29 | O28: =+O29 | R28: =+R29 | U28: =+U29 | X28: =+X29 | AA28: =+AA29 | AD28: =+AD29 | AG28: =+AG29 | AM28: =C28+F28+I28+L28+O28+R28+U28+X28+AA28+AD28+AG28+AJ28 | AQ28: =+AQ29
B29: OTROS | C29: =SUM(C30:C35) | F29: =SUM(F30:F35) | H29: =F29/F13 | I29: =SUM(I30:I35) | K29: =I29/I13 | L29: =SUM(L30:L35) | N29: =L29/L13 | O29: =SUM(O30:O35) | R29: =SUM(R30:R35) | U29: =SUM(U30:U35) | X29: =SUM(X30:X35) | AA29: =SUM(AA30:AA35) | AD29: =SUM(AD30:AD35) | AG29: =SUM(AG30:AG35) | AM29: =C29+F29+I29+L29+O29+R29+U29+X29+AA29+AD29+AG29+AJ29 | AO29: =AM29/AM13 | AQ29: =SUM(AQ30:AQ35)
B30: ICA (0.77%) | C30: =C15*0.77% | F30: =F13*0.77% | I30: =I13*0.77% | L30: =L13*0.77% | O30: =O13*0.77% | R30: =R13*0.77% | U30: =U13*0.77% | AA30: =AA13*0.77% | AD30: =AD13*0.77% | AG30: =AG13*0.77% | AM30: =C30+F30+I30+L30+O30+R30+U30+X30+AA30+AD30+AG30+AJ30
AM31: =C31+F31+I31+L31+O31+R31+U31+X31+AA31+AD31+AG31+AJ31
AM32: =C32+F32+I32+L32+O32+R32+U32+X32+AA32+AD32+AG32+AJ32
AM33: =C33+F33+I33+L33+O33+R33+U33+X33+AA33+AD33+AG33+AJ33
AM34: =C34+F34+I34+L34+O34+R34+U34+X34+AA34+AD34+AG34+AJ34
AM35: =C35+F35+I35+L35+O35+R35+U35+X35+AA35+AD35+AG35+AJ35
B42: TOTAL INGRESOS NETOS | C42: =+C14+C23-C28 | F42: =+F14+F23-F28 | I42: =+I14+I23-I28 | L42: =+L14+L23-L28 | O42: =+O14+O23-O28 | R42: =+R14+R23-R28 | U42: =+U14+U23-U28 | X42: =+X14+X23-X28 | AA42: =+AA14+AA23-AA28 | AD42: =+AD14+AD23-AD28 | AG42: =+AG14+AG23-AG28 | AM42: =C42+F42+I42+L42+O42+R42+U42+X42+AA42+AD42+AG42+AJ42 | AQ42: =+AQ14+AQ23-AQ28
AS43: =(AQ46+AQ61)/(AQ13)
B44: COSTOS DE PRODUCCION | C44: =+C45+C60+C78 | F44: =+F45+F60+F78 | H44: =F44/F$13 | I44: =+I45+I60+I78 | K44: =I44/I$13 | L44: =+L45+L60+L78 | N44: =L44/L$13 | O44: =+O45+O60+O78 | Q44: =O44/O$13 | R44: =+R45+R60+R78 | T44: =R44/R$13 | U44: =+U45+U60+U78 | W44: =U44/U$13 | X44: =+X45+X60+X78 | Z44: =X44/X$13 | AA44: =+AA45+AA60+AA78 | AD44: =+AD45+AD60+AD78 | AG44: =+AG45+AG60+AG78 | AJ44: =+AJ45+AJ60+AJ78 | AM44: =C44+F44+I44+L44+O44+R44+U44+X44+AA44+AD44+AG44+AJ44 | AO44: =AM44/AM$13 | AQ44: =+AQ45+AQ60+AQ78 | AS44: =AQ44/AQ$13
B45: COSTOS INDUSTRIALIZADOS | C45: =+C46+C58+C59 | F45: =+F46+F57 | I45: =+I46+I57 | L45: =+L46+L57 | O45: =+O46+O57 | R45: =+R46+R57 | U45: =+U46+U57 | X45: =+X46+X57 | AA45: =+AA46+AA57 | AD45: =+AD46+AD57 | AG45: =+AG46+AG57 | AJ45: =+AJ46+AJ57 | AM45: =C45+F45+I45+L45+O45+R45+U45+X45+AA45+AD45+AG45+AJ45 | AO45: =AM45/AM$13 | AQ45: =+AQ46+AQ57
B46: INSUMOS CI | C46: =SUM(C47:C56)+C57 | F46: =SUM(F47:F56) | I46: =SUM(I47:I56) | L46: =SUM(L47:L56) | O46: =SUM(O47:O56) | R46: =SUM(R47:R56) | U46: =SUM(U47:U56) | X46: =SUM(X47:X56) | AA46: =SUM(AA47:AA56) | AD46: =SUM(AD47:AD56) | AG46: =SUM(AG47:AG56) | AJ46: =SUM(AJ47:AJ56) | AM46: =C46+F46+I46+L46+O46+R46+U46+X46+AA46+AD46+AG46+AJ46 | AO46: =AM46/AM13 | AQ46: =SUM(AQ47:AQ56)
B47: COMPLEMENTO INDUSTRIALIZADO (Ins) | G47: =F47/F5 | H47: =F47/F16 | J47: =I47/I5 | K47: =I47/I16 | M47: =L47/L5 | N47: =L47/L16 | P47: =O47/O12 | Q47: =O47/O15 | S47: =R47/R5 | T47: =R47/R16 | V47: =U47/U12 | W47: =U47/U15 | Y47: =X47/X5 | Z47: =X47/X16 | AB47: =AA47/AA12 | AC47: =AA47/AA15 | AE47: =AD47/AD12 | AF47: =AD47/AD15 | AH47: =AG47/AG5 | AI47: =AG47/AG15 | AM47: =C47+F47+I47+L47+O47+R47+U47+X47+AA47+AD47+AG47+AJ47 | AN47: =AM47/AM5 | AO47: =AM47/AM16 | AR47: =AQ47/AQ5 | AS47: =AQ47/AQ16
AM48: =C48+F48+I48+L48+O48+R48+U48+X48+AA48+AD48+AG48+AJ48
AM49: =C49+F49+I49+L49+O49+R49+U49+X49+AA49+AD49+AG49+AJ49
AM50: =C50+F50+I50+L50+O50+R50+U50+X50+AA50+AD50+AG50+AJ50
AM51: =C51+F51+I51+L51+O51+R51+U51+X51+AA51+AD51+AG51+AJ51
B52: REFRIGERIOS | AM52: =C52+F52+I52+L52+O52+R52+U52+X52+AA52+AD52+AG52+AJ52
B53: PAQUETES MANIPULADORAS | AM53: =C53+F53+I53+L53+O53+R53+U53+X53+AA53+AD53+AG53+AJ53
AM56: =C56+F56+I56+L56+O56+R56+U56+X56+AA56+AD56+AG56+AJ56
B57: FLETES CI | F57: =SUM(F58:F59) | I57: =SUM(I58:I59) | J57: =I57/I12 | K57: =I57/I16 | L57: =SUM(L58:L59) | M57: =L57/L5 | N57: =L57/L16 | O57: =SUM(O58:O59) | P57: =O57/O5 | Q57: =O57/O16 | R57: =SUM(R58:R59) | S57: =R57/R5 | T57: =R57/R16 | U57: =SUM(U58:U59) | V57: =U57/U5 | W57: =U57/U16 | X57: =SUM(X58:X59) | Y57: =X57/X5 | Z57: =X57/X16 | AA57: =SUM(AA58:AA59) | AB57: =AA57/AA5 | AC57: =AA57/AA16 | AD57: =SUM(AD58:AD59) | AE57: =AD57/AD5 | AF57: =AD57/AD16 | AG57: =SUM(AG58:AG59) | AH57: =AG57/AG5 | AI57: =AG57/AG16 | AJ57: =SUM(AJ58:AJ59) | AM57: =C57+F57+I57+L57+O57+R57+U57+X57+AA57+AD57+AG57+AJ57 | AN57: =AM57/AM12 | AO57: =AM57/AM16
B58: INDUSTRIALIZADOS PROPIOS | U58: ='%DIST'!N22*'GASTOS VEHICULOS'!I25 | AJ58: ='%DIST'!X22*'GASTOS VEHICULOS'!N27 | AM58: =C58+F58+I58+L58+O58+R58+U58+X58+AA58+AD58+AG58+AJ58 | AO58: =AM58/AM$13
B59: INDUSTRIALIZADOS TERCEROS | AM59: =C59+F59+I59+L59+O59+R59+U59+X59+AA59+AD59+AG59+AJ59 | AN59: =AM59/AM12 | AO59: =AM59/(AM13)
B60: COSTOS PREPARADOS | C60: =+C61+C73+C74+C75+C76+C77 | F60: =+F61+F72+F75+F76+F77 | I60: =+I61+I72+I75+I76+I77 | L60: =+L61+L72+L75+L76+L77 | O60: =+O61+O72+O75+O76+O77 | R60: =+R61+R72+R75+R76+R77 | U60: =+U61+U72+U75+U76+U77 | X60: =+X61+X72+X75+X76+X77 | AA60: =+AA61+AA72+AA75+AA76+AA77 | AD60: =+AD61+AD72+AD75+AD76+AD77 | AG60: =+AG61+AG72+AG75+AG76+AG77 | AJ60: =+AJ61+AJ72+AJ75+AJ76+AJ77 | AM60: =C60+F60+I60+L60+O60+R60+U60+X60+AA60+AD60+AG60+AJ60 | AO60: =AM60/AM$13 | AQ60: =+AQ61+AQ72+AQ75+AQ76+AQ77
B61: INSUMOS CP | C61: =SUM(C62:C66)+C72 | F61: =SUM(F62:F71) | I61: =SUM(I62:I71) | L61: =SUM(L62:L71) | O61: =SUM(O62:O71) | R61: =SUM(R62:R71) | U61: =SUM(U62:U71) | X61: =SUM(X62:X71) | AA61: =SUM(AA62:AA71) | AD61: =SUM(AD62:AD71) | AG61: =SUM(AG62:AG71) | AJ61: =SUM(AJ62:AJ71) | AM61: =C61+F61+I61+L61+O61+R61+U61+X61+AA61+AD61+AG61+AJ61 | AQ61: =SUM(AQ62:AQ71)
B62: COMPLEMENTO PREPARADO (Ins) | AM62: =C62+F62+I62+L62+O62+R62+U62+X62+AA62+AD62+AG62+AJ62 | AR62: =AQ62/AQ6 | AS62: =AQ62/AQ17
B63: ALMUERZO JORNADA UNICA (Ins) | AM63: =C63+F63+I63+L63+O63+R63+U63+X63+AA63+AD63+AG63+AJ63 | AR63: =AQ63/AQ7 | AS63: =AQ63/AQ18
AM64: =C64+F64+I64+L64+O64+R64+U64+X64+AA64+AD64+AG64+AJ64 | AR64: =AQ64/AQ8 | AS64: =AQ64/AQ19
B65: RACION MANIPULADORAS | AM65: =C65+F65+I65+L65+O65+R65+U65+X65+AA65+AD65+AG65+AJ65
B66: MENU ESPECIAL | AM66: =C66+F66+I66+L66+O66+R66+U66+X66+AA66+AD66+AG66+AJ66
B72: FLETES CP | F72: =SUM(F73:F74) | G72: =F72/F12 | H72: =F72/F13 | I72: =SUM(I73:I74) | J72: =I72/I12 | K72: =I72/I13 | L72: =SUM(L73:L74) | M72: =L72/L12 | N72: =L72/L13 | O72: =SUM(O73:O74) | P72: =O72/O12 | Q72: =O72/O13 | R72: =SUM(R73:R74) | S72: =R72/R12 | T72: =R72/R13 | U72: =SUM(U73:U74) | V72: =U72/U12 | W72: =U72/U13 | X72: =SUM(X73:X74) | Y72: =X72/X12 | Z72: =X72/X13 | AA72: =SUM(AA73:AA74) | AB72: =AA72/AA12 | AC72: =AA72/AA13 | AD72: =SUM(AD73:AD74) | AE72: =AD72/AD12 | AF72: =AD72/AD13 | AG72: =SUM(AG73:AG74) | AH72: =AG72/AG12 | AI72: =AG72/AG13 | AJ72: =SUM(AJ73:AJ74) | AM72: =C72+F72+I72+L72+O72+R72+U72+X72+AA72+AD72+AG72+AJ72 | AN72: =AM72/AM12 | AO72: =AM72/AM13 | AQ72: =SUM(AQ73:AQ74) | AR72: =AQ72/(AQ$12-AQ$8) | AS72: =AQ72/(AQ$13-AQ$19)
B73: PREPARADOS PROPIOS | AM73: =C73+F73+I73+L73+O73+R73+U73+X73+AA73+AD73+AG73+AJ73
B74: PREPARADOS TERCEROS | AM74: =C74+F74+I74+L74+O74+R74+U74+X74+AA74+AD74+AG74+AJ74
B75: Material de empaque | AM75: =C75+F75+I75+L75+O75+R75+U75+X75+AA75+AD75+AG75+AJ75
B76: Menaje | AM76: =C76+F76+I76+L76+O76+R76+U76+X76+AA76+AD76+AG76+AJ76 | AR76: =AQ76/(AQ$12-AQ$8) | AS76: =AQ76/(AQ$13-AQ$19)
B77: Servicio de Gas | AM77: =C77+F77+I77+L77+O77+R77+U77+X77+AA77+AD77+AG77+AJ77 | AR77: =AQ77/(AQ$12-AQ$8) | AS77: =AQ77/(AQ$13-AQ$19)
B78: MANO DE OBRA DIRECTA | C78: =SUM(C79:C81) | F78: =SUM(F79:F81) | H78: =F78/F$13 | I78: =SUM(I79:I81) | K78: =I78/I$13 | L78: =SUM(L79:L81) | N78: =L78/L$13 | O78: =SUM(O79:O81) | Q78: =O78/O$13 | R78: =SUM(R79:R81) | T78: =R78/R$13 | U78: =SUM(U79:U81) | X78: =SUM(X79:X81) | Z78: =X78/X$13 | AA78: =SUM(AA79:AA81) | AD78: =SUM(AD79:AD81) | AG78: =SUM(AG79:AG81) | AM78: =C78+F78+I78+L78+O78+R78+U78+X78+AA78+AD78+AG78+AJ78 | AO78: =AM78/(AM$13) | AQ78: =SUM(AQ79:AQ81) | AR78: =AQ78/(AQ$12-AQ$8) | AS78: =AQ78/(AQ$13-AQ$19)
B79: Manipuladoras | AM79: =C79+F79+I79+L79+O79+R79+U79+X79+AA79+AD79+AG79+AJ79 | AO79: =AM79/(AM$13) | AR79: =AQ79/(AQ$12-AQ$8) | AS79: =AQ79/(AQ$13-AQ$19)
B80: Personal Supervisor - Coordinadores | AM80: =C80+F80+I80+L80+O80+R80+U80+X80+AA80+AD80+AG80+AJ80 | AR80: =AQ80/(AQ$12-AQ$8) | AS80: =AQ80/(AQ$13-AQ$19)
B81: Temporales MOD | AM81: =C81+F81+I81+L81+O81+R81+U81+X81+AA81+AD81+AG81+AJ81
B83: OTROS COSTOS Y GASTOS INDIRECTOS | C83: =+C84+C89+C92+C96+C99+C109+C114+C120+C123+C127 | F83: =+F84+F89+F92+F96+F99+F109+F114+F120+F123+F127 | H83: =F83/F$13 | I83: =+I84+I89+I92+I96+I99+I109+I114+I120+I123+I127 | K83: =I83/I$13 | L83: =+L84+L89+L92+L96+L99+L109+L114+L120+L123+L127 | N83: =L83/L$13 | O83: =+O84+O89+O92+O96+O99+O109+O114+O120+O123+O127 | Q83: =O83/O$13 | R83: =+R84+R89+R92+R96+R99+R109+R114+R120+R123+R127 | T83: =R83/R$13 | U83: =+U84+U89+U92+U96+U99+U109+U114+U120+U123+U127 | X83: =+X84+X89+X92+X96+X99+X109+X114+X120+X123+X127 | Z83: =X83/X$13 | AA83: =+AA84+AA89+AA92+AA96+AA99+AA109+AA114+AA120+AA123+AA127 | AD83: =+AD84+AD89+AD92+AD96+AD99+AD109+AD114+AD120+AD123+AD127 | AF83: =AD83/(AD$13) | AG83: =+AG84+AG89+AG92+AG96+AG99+AG109+AG114+AG120+AG123+AG127 | AI83: =AG83/(AG$13) | AJ83: =+AJ84+AJ89+AJ92+AJ96+AJ99+AJ109+AJ114+AJ120+AJ123+AJ127 | AM83: =C83+F83+I83+L83+O83+R83+U83+X83+AA83+AD83+AG83+AJ83 | AO83: =AM83/(AM$13) | AQ83: =+AQ84+AQ89+AQ92+AQ96+AQ99+AQ109+AQ114+AQ120+AQ123+AQ127 | AR83: =AQ83/(AQ$12-AQ$8) | AS83: =AQ83/(AQ$13-AQ$19)
B84: COSTOS DE PERSONAL | C84: =SUM(C85:C88) | F84: =SUM(F85:F88) | H84: =F84/F$13 | I84: =SUM(I85:I88) | K84: =I84/I$13 | L84: =SUM(L85:L88) | N84: =L84/L$13 | O84: =SUM(O85:O88) | Q84: =O84/O$13 | R84: =SUM(R85:R88) | T84: =R84/R$13 | U84: =SUM(U85:U88) | X84: =SUM(X85:X88) | Z84: =X84/X$13 | AA84: =SUM(AA85:AA88) | AD84: =SUM(AD85:AD88) | AG84: =SUM(AG85:AG88) | AJ84: =SUM(AJ85:AJ88) | AM84: =C84+F84+I84+L84+O84+R84+U84+X84+AA84+AD84+AG84+AJ84 | AO84: =AM84/(AM$13) | AQ84: =SUM(AQ85:AQ88) | AR84: =AQ84/(AQ$12-AQ$8) | AS84: =AQ84/(AQ$13-AQ$19)
B85: Costos Indirectos de Personal | AM85: =C85+F85+I85+L85+O85+R85+U85+X85+AA85+AD85+AG85+AJ85 | AO85: =AM85/(AM$13) | AS85: =AQ85/(AQ$13-AQ$19)
B86: Dotación y Suministros | AM86: =C86+F86+I86+L86+O86+R86+U86+X86+AA86+AD86+AG86+AJ86 | AS86: =AQ86/(AQ$13-AQ$19)
B87: Gastos Medicos | AM87: =C87+F87+I87+L87+O87+R87+U87+X87+AA87+AD87+AG87+AJ87 | AS87: =AQ87/(AQ$13-AQ$19)
B88: Incapacidades
B89: HONORARIOS | C89: =SUM(C90:C91) | F89: =SUM(F90:F91) | H89: =F89/F$13 | I89: =SUM(I90:I91) | K89: =I89/I$13 | L89: =SUM(L90:L91) | N89: =L89/L$13 | O89: =SUM(O90:O91) | Q89: =O89/O$13 | R89: =SUM(R90:R91) | T89: =R89/R$13 | U89: =SUM(U90:U91) | X89: =SUM(X90:X91) | Z89: =X89/X$13 | AA89: =SUM(AA90:AA91) | AM89: =C89+F89+I89+L89+O89+R89+U89+X89+AA89+AD89+AG89+AJ89 | AO89: =AM89/(AM$13) | AR89: =AQ89/(AQ$12-AQ$8) | AS89: =AQ89/(AQ$13-AQ$19)
B90: Asesoría Juridica | AM90: =C90+F90+I90+L90+O90+R90+U90+X90+AA90+AD90+AG90+AJ90
B91: Asesoría Tecnica | AM91: =C91+F91+I91+L91+O91+R91+U91+X91+AA91+AD91+AG91+AJ91
B92: ARRENDAMIENTOS | C92: =SUM(C93:C95) | F92: =SUM(F93:F95) | H92: =F92/F$13 | I92: =SUM(I93:I95) | K92: =I92/I$13 | L92: =SUM(L93:L95) | N92: =L92/L$13 | O92: =SUM(O93:O95) | Q92: =O92/O$13 | R92: =SUM(R93:R95) | T92: =R92/R$13 | U92: =SUM(U93:U95) | X92: =SUM(X93:X95) | Z92: =X92/X$13 | AA92: =SUM(AA93:AA95) | AM92: =C92+F92+I92+L92+O92+R92+U92+X92+AA92+AD92+AG92+AJ92 | AO92: =AM92/(AM$13) | AR92: =AQ92/(AQ$12-AQ$8) | AS92: =AQ92/(AQ$13-AQ$19)
B93: Construcciones y Edificaciones | AM93: =C93+F93+I93+L93+O93+R93+U93+X93+AA93+AD93+AG93+AJ93
B94: Maquinaria y Equipo | AM94: =C94+F94+I94+L94+O94+R94+U94+X94+AA94+AD94+AG94+AJ94
B95: Equipo de Oficina | AM95: =C95+F95+I95+L95+O95+R95+U95+X95+AA95+AD95+AG95+AJ95
B96: SEGUROS | C96: =SUM(C97:C98) | F96: =SUM(F97:F98) | H96: =F96/F$13 | I96: =SUM(I97:I98) | K96: =I96/I$13 | L96: =SUM(L97:L98) | N96: =L96/L$13 | O96: =SUM(O97:O98) | Q96: =O96/O$13 | R96: =SUM(R97:R98) | T96: =R96/R$13 | U96: =SUM(U97:U98) | X96: =SUM(X97:X98) | Z96: =X96/X$13 | AA96: =SUM(AA97:AA98) | AG96: =SUM(AG97:AG98) | AM96: =C96+F96+I96+L96+O96+R96+U96+X96+AA96+AD96+AG96+AJ96 | AO96: =AM96/(AM$13) | AQ96: =SUM(AQ97:AQ98) | AR96: =AQ96/(AQ$12-AQ$8) | AS96: =AQ96/(AQ$13-AQ$19)
A97: 73301001 | B97: Cumplimiento | AM97: =C97+F97+I97+L97+O97+R97+U97+X97+AA97+AD97+AG97+AJ97
A98: 73306001 | B98: Responsabilidad Civil Y Extracontractual | AM98: =C98+F98+I98+L98+O98+R98+U98+X98+AA98+AD98+AG98+AJ98
B99: SERVICIOS | C99: =SUM(C100:C108) | F99: =SUM(F100:F108) | H99: =F99/F$13 | I99: =SUM(I100:I106) | K99: =I99/I$13 | L99: =SUM(L100:L106) | N99: =L99/L$13 | O99: =SUM(O100:O106) | Q99: =O99/O$13 | R99: =SUM(R100:R106) | T99: =R99/R$13 | U99: =SUM(U100:U106) | X99: =SUM(X100:X106) | Z99: =X99/X$13 | AA99: =SUM(AA100:AA106) | AM99: =C99+F99+I99+L99+O99+R99+U99+X99+AA99+AD99+AG99+AJ99 | AO99: =AM99/(AM$13) | AQ99: =SUM(AQ100:AQ108) | AR99: =AQ99/(AQ$12-AQ$8) | AS99: =AQ99/(AQ$13-AQ$19)
B100: Aseo y Vigilancia | AM100: =C100+F100+I100+L100+O100+R100+U100+X100+AA100+AD100+AG100+AJ100
B101: Temporales Serv | AM101: =C101+F101+I101+L101+O101+R101+U101+X101+AA101+AD101+AG101+AJ101
B102: Mensajeria | AM102: =C102+F102+I102+L102+O102+R102+U102+X102+AA102+AD102+AG102+AJ102
B103: Laboratorio | AM103: =C103+F103+I103+L103+O103+R103+U103+X103+AA103+AD103+AG103+AJ103
B104: Fumigacion | AM104: =C104+F104+I104+L104+O104+R104+U104+X104+AA104+AD104+AG104+AJ104
B105: Acueducto y Alcantarillado | AM105: =C105+F105+I105+L105+O105+R105+U105+X105+AA105+AD105+AG105+AJ105
B106: Energia | AM106: =C106+F106+I106+L106+O106+R106+U106+X106+AA106+AD106+AG106+AJ106
B107: Telefono e Internet
B108: Correo, porte y telegramas
B109: GASTOS LEGALES | C109: =SUM(C110:C113) | F109: =SUM(F110:F113) | H109: =F109/F$13 | I109: =SUM(I110:I113) | K109: =I109/I$13 | L109: =SUM(L110:L113) | N109: =L109/L$13 | O109: =SUM(O110:O113) | Q109: =O109/O$13 | R109: =SUM(R110:R113) | T109: =R109/R$13 | U109: =SUM(U110:U113) | X109: =SUM(X110:X113) | Z109: =X109/X$13 | AA109: =SUM(AA110:AA113) | AM109: =C109+F109+I109+L109+O109+R109+U109+X109+AA109+AD109+AG109+AJ109 | AO109: =AM109/(AM$13) | AQ109: =SUM(AQ110:AQ113) | AR109: =AQ109/(AQ$12-AQ$8) | AS109: =AQ109/(AQ$13-AQ$19)
A110: 73400501 | B110: Notariales | AM110: =C110+F110+I110+L110+O110+R110+U110+X110+AA110+AD110+AG110+AJ110
A111: 73401001 | B111: Registro Mercantil | AM111: =C111+F111+I111+L111+O111+R111+U111+X111+AA111+AD111+AG111+AJ111
A112: 73401501 | B112: Trámites y Licencias | AM112: =C112+F112+I112+L112+O112+R112+U112+X112+AA112+AD112+AG112+AJ112
A113: 73409501 | B113: Certificados Camara Comercio | AM113: =C113+F113+I113+L113+O113+R113+U113+X113+AA113+AD113+AG113+AJ113
B114: MANTENIMIENTO Y REPARACIONES | C114: =SUM(C115:C116) | F114: =SUM(F115:F116) | H114: =F114/F$13 | I114: =SUM(I115:I116) | K114: =I114/I$13 | L114: =SUM(L115:L116) | N114: =L114/L$13 | O114: =SUM(O115:O116) | Q114: =O114/O$13 | R114: =SUM(R115:R116) | T114: =R114/R$13 | U114: =SUM(U115:U116) | X114: =SUM(X115:X116) | Z114: =X114/X$13 | AA114: =SUM(AA115:AA116) | AM114: =C114+F114+I114+L114+O114+R114+U114+X114+AA114+AD114+AG114+AJ114 | AO114: =AM114/(AM$13) | AQ114: =SUM(AQ115:AQ119) | AR114: =AQ114/(AQ$12-AQ$8) | AS114: =AQ114/(AQ$13-AQ$19)
A115: 73451001 | B115: Construcciones y Edificaciones | AM115: =C115+F115+I115+L115+O115+R115+U115+X115+AA115+AD115+AG115+AJ115
A116: 73451501 | B116: Maquinaria y Equipo | AM116: =C116+F116+I116+L116+O116+R116+U116+X116+AA116+AD116+AG116+AJ116
A117: 73451502 | B117: Equipos de Cocina | AM117: =C117+F117+I117+L117+O117+R117+U117+X117+AA117+AD117+AG117+AJ117
A118: 73452001 | B118: Equipo de Oficina | AM118: =C118+F118+I118+L118+O118+R118+U118+X118+AA118+AD118+AG118+AJ118
A119: 73456001 | B119: Acueductos, planta y redes | AM119: =C119+F119+I119+L119+O119+R119+U119+X119+AA119+AD119+AG119+AJ119
...

Sheet CALI
B2: CORPORACIÓN HACIA UN VALLE SOLIDARIO | C2: PYG CALI 2026
B3: DIAS DE ATENCIÓN | C3: 5 | F3: 20 | I3: 19 | L3: 19 | O3: 19 | R3: 18 | U3: 9 | X3: 19 | AA3: 22 | AD3: 16 | AG3: 19 | AJ3: 4 | AM3: =SUM(C3:AJ3)
C4: ENE | D4: x racion | E4: % | F4: FEB | G4: x racion | H4: % | I4: MAR | J4: x racion | K4: % | L4: ABR | M4: x racion | N4: % | O4: MAY | P4: x racion | Q4: % | R4: JUN | S4: x racion | T4: % | U4: JUL | V4: x racion | W4: % | X4: AGO | Y4: x racion | Z4: % | AA4: SEP | AB4: x racion | AC4: % | AD4: OCT | AE4: x racion | AF4: % | AG4: NOV | AH4: x racion | AI4: % | AJ4: DIC | AK4: x racion | AL4: % | AM4: ACUMULADO | AN4: x racion | AO4: %
B5: COMPLEMENTO INDUSTRIALIZADO | AM5: =C5+F5+I5+L5+O5+R5+U5+X5+AA5+AD5+AG5+AJ5 | AO5: =AM5/AM12
B6: COMPLEMENTO PREPARADO AM | AM6: =C6+F6+I6+L6+O6+R6+U6+X6+AA6+AD6+AG6+AJ6 | AO6: =AM6/AM12
B7: COMPLEMENTO PREPARADO PM | AM7: =C7+F7+I7+L7+O7+R7+U7+X7+AA7+AD7+AG7+AJ7 | AO7: =AM7/AM12
B8: ALMUERZO JORNADA UNICA | AM8: =C8+F8+I8+L8+O8+R8+U8+X8+AA8+AD8+AG8+AJ8
B9: NOVEDADES | AM9: =C9+F9+I9+L9+O9+R9+U9+X9+AA9+AD9+AG9+AJ9
AM10: =C10+F10+I10+L10+O10+R10+U10+X10+AA10+AD10+AG10+AJ10
AM11: =C11+F11+I11+L11+O11+R11+U11+X11+AA11+AD11+AG11+AJ11
B12: TOTAL RACIONES | C12: =SUM(C5:C11) | F12: =SUM(F5:F11) | I12: =SUM(I5:I11) | L12: =SUM(L5:L11) | O12: =SUM(O5:O11) | R12: =SUM(R5:R11) | U12: =SUM(U5:U11) | X12: =SUM(X5:X11) | AA12: =SUM(AA5:AA11) | AD12: =SUM(AD5:AD11) | AG12: =SUM(AG5:AG11) | AJ12: =SUM(AJ5:AJ11) | AM12: =C12+F12+I12+L12+O12+R12+U12+X12+AA12+AD12+AG12+AJ12
B13: INGRESOS BRUTOS | C13: =C14+C23 | F13: =F14+F23 | I13: =I14+I23 | L13: =L14+L23 | O13: =O14+O23 | R13: =R14+R23 | U13: =U14+U23 | X13: =X14+X23 | AA13: =AA14+AA23 | AD13: =AD14+AD23 | AG13: =AG14+AG23 | AJ13: =AJ14+AJ23 | AM13: =C13+F13+I13+L13+O13+R13+U13+X13+AA13+AD13+AG13+AJ13
B14: OPERACIONALES | C14: =C15 | F14: =F15 | I14: =I15 | L14: =L15 | O14: =O15 | R14: =R15 | U14: =U15 | X14: =X15 | AA14: =AA15 | AD14: =AD15 | AG14: =AG15 | AJ14: =AJ15 | AM14: =C14+F14+I14+L14+O14+R14+U14+X14+AA14+AD14+AG14+AJ14
B15: INDUSTRIAS MANUFACTURERAS | C15: =SUM(C16:C22) | F15: =SUM(F16:F22) | I15: =SUM(I16:I22) | L15: =SUM(L16:L22) | O15: =SUM(O16:O22) | R15: =SUM(R16:R22) | U15: =SUM(U16:U22) | X15: =SUM(X16:X22) | AA15: =SUM(AA16:AA22) | AC15: =AA15/AA15 | AD15: =SUM(AD16:AD22) | AG15: =SUM(AG16:AG22) | AI15: =AG15/AG15 | AJ15: =SUM(AJ16:AJ22) | AM15: =C15+F15+I15+L15+O15+R15+U15+X15+AA15+AD15+AG15+AJ15 | AO15: =AM15/AM15
B16: COMPLEMENTO INDUSTRIALIZADO | D16: =C16/C5 | AM16: =C16+F16+I16+L16+O16+R16+U16+X16+AA16+AD16+AG16+AJ16 | AO16: =AM16/AM$13
B17: COMPLEMENTO PREPARADO AM | D17: =C17/C6 | AM17: =C17+F17+I17+L17+O17+R17+U17+X17+AA17+AD17+AG17+AJ17 | AO17: =AM17/AM$13
B18: COMPLEMENTO PREPARADO PM | D18: =C18/C7 | AM18: =C18+F18+I18+L18+O18+R18+U18+X18+AA18+AD18+AG18+AJ18 | AO18: =AM18/AM$13
B19: ALMUERZO JORNADA UNICA | D19: =C19/C8 | AM19: =C19+F19+I19+L19+O19+R19+U19+X19+AA19+AD19+AG19+AJ19 | AO19: =AM19/AM$13
B20: NOVEDADES | AM20: =C20+F20+I20+L20+O20+R20+U20+X20+AA20+AD20+AG20+AJ20
AM21: =C21+F21+I21+L21+O21+R21+U21+X21+AA21+AD21+AG21+AJ21
AM22: =C22+F22+I22+L22+O22+R22+U22+X22+AA22+AD22+AG22+AJ22
B23: NO OPERACIONALES | C23: =C24 | F23: =F24 | I23: =I24 | L23: =L24 | O23: =O24 | R23: =R24 | U23: =U24 | X23: =X24 | AA23: =AA24 | AD23: =AD24 | AG23: =AG24 | AJ23: =AJ24 | AM23: =C23+F23+I23+L23+O23+R23+U23+X23+AA23+AD23+AG23+AJ23
B24: FINANCIEROS | C24: =SUM(C25:C27) | F24: =SUM(F25:F27) | I24: =SUM(I25:I27) | L24: =SUM(L25:L27) | O24: =SUM(O25:O27) | R24: =SUM(R25:R27) | U24: =SUM(U25:U27) | X24: =SUM(X25:X27) | AA24: =SUM(AA25:AA27) | AD24: =SUM(AD25:AD27) | AG24: =SUM(AG25:AG27) | AJ24: =SUM(AJ25:AJ27) | AM24: =C24+F24+I24+L24+O24+R24+U24+X24+AA24+AD24+AG24+AJ24
B25: Intereses | AM25: =C25+F25+I25+L25+O25+R25+U25+X25+AA25+AD25+AG25+AJ25
B26: Descuentos Comerciales | AM26: =C26+F26+I26+L26+O26+R26+U26+X26+AA26+AD26+AG26+AJ26
B27: otros Fin | AM27: =C27+F27+I27+L27+O27+R27+U27+X27+AA27+AD27+AG27+AJ27
B28: DESCUENTOS - GASTO OPERACIONAL | C28: =+C29 | F28: =+F29 | I28: =+I29 | L28: =+L29 | O28: =+O29 | R28: =+R29 | U28: =+U29 | X28: =+X29 | AA28: =+AA29 | AD28: =+AD29 | AG28: =+AG29 | AJ28: =+AJ29 | AM28: =C28+F28+I28+L28+O28+R28+U28+X28+AA28+AD28+AG28+AJ28
B29: OTROS | C29: =SUM(C30:C35) | E29: =C29/C13 | F29: =SUM(F30:F35) | H29: =F29/F13 | I29: =SUM(I30:I35) | K29: =I29/I13 | L29: =SUM(L30:L35) | N29: =L29/L13 | O29: =SUM(O30:O35) | Q29: =O29/O13 | R29: =SUM(R30:R35) | T29: =R29/R13 | U29: =SUM(U30:U35) | W29: =U29/U13 | X29: =SUM(X30:X35) | Z29: =X29/X13 | AA29: =SUM(AA30:AA35) | AC29: =AA29/AA13 | AD29: =SUM(AD30:AD35) | AF29: =AD29/AD13 | AG29: =SUM(AG30:AG35) | AI29: =AG29/AG13 | AJ29: =SUM(AJ30:AJ41) | AM29: =C29+F29+I29+L29+O29+R29+U29+X29+AA29+AD29+AG29+AJ29 | AO29: =AM29/AM13
B30: 2% Estampillas Prounivalle | C30: =C$13*2% | F30: =F$13*2% | I30: =I$13*2% | L30: =L$13*2% | O30: =O$13*2% | R30: =R$13*2% | U30: =U$13*2% | X30: =X$13*2% | AA30: =AA$13*2% | AD30: =AD$13*2% | AG30: =AG$13*2% | AJ30: =AJ$13*2% | AM30: =C30+F30+I30+L30+O30+R30+U30+X30+AA30+AD30+AG30+AJ30
B31: 0,88% Rte Ica | C31: =C$13*0.88% | F31: =F$13*0.88% | I31: =I$13*0.88% | L31: =L$13*0.88% | O31: =O$13*0.88% | R31: =R$13*0.88% | U31: =U$13*0.88% | X31: =X$13*0.88% | AA31: =AA$13*0.88% | AD31: =AD$13*0.88% | AG31: =AG$13*0.88% | AJ31: =AJ$13*0.88% | AM31: =C31+F31+I31+L31+O31+R31+U31+X31+AA31+AD31+AG31+AJ31
B32: 1% Estampilla Prohospital | C32: =C$13*1% | F32: =F$13*1% | I32: =I$13*1% | L32: =L$13*1% | O32: =O$13*1% | R32: =R$13*1% | U32: =U$13*1% | X32: =X$13*1% | AA32: =AA$13*1% | AD32: =AD$13*1% | AG32: =AG$13*1% | AJ32: =AJ$13*1% | AM32: =C32+F32+I32+L32+O32+R32+U32+X32+AA32+AD32+AG32+AJ32
B33: 0,5% Propacifico | C33: =C$13*0.5% | F33: =F$13*0.5% | I33: =I$13*0.5% | L33: =L$13*0.5% | O33: =O$13*0.5% | R33: =R$13*0.5% | U33: =U$13*0.5% | X33: =X$13*0.5% | AA33: =AA$13*0.5% | AD33: =AD$13*0.5% | AG33: =AG$13*0.5% | AJ33: =AJ$13*0.5% | AM33: =C33+F33+I33+L33+O33+R33+U33+X33+AA33+AD33+AG33+AJ33
B34: Retefuente | C34: =(C$13*3.5%)*1% | F34: =(F$13*3.5%)*1% | I34: =(I$13*3.5%)*1% | L34: =(L$13*3.5%)*1% | O34: =(O$13*3.5%)*1% | R34: =(R$13*3.5%)*1% | U34: =(U$13*3.5%)*1% | X34: =(X$13*3.5%)*1% | AA34: =(AA$13*3.5%)*1% | AD34: =(AD$13*3.5%)*1% | AG34: =(AG$13*3.5%)*1% | AJ34: =(AJ$13*3.5%)*1% | AM34: =C34+F34+I34+L34+O34+R34+U34+X34+AA34+AD34+AG34+AJ34
B35: 2% Juzgado de Familia | C35: =C13*2% | F35: =F13*2% | I35: =I13*2% | L35: =L13*2% | O35: =O13*2% | R35: =R13*2% | U35: =U13*2% | X35: =X13*2% | AA35: =AA13*2% | AD35: =AD13*2% | AG35: =AG13*2% | AJ35: =AJ13*2% | AM35: =C35+F35+I35+L35+O35+R35+U35+X35+AA35+AD35+AG35+AJ35
AM36: =C36+F36+I36+L36+O36+R36+U36+X36+AA36+AD36+AG36+AJ36
B42: TOTAL INGRESOS NETOS | C42: =+C14+C23-C28 | F42: =+F14+F23-F28 | I42: =+I14+I23-I28 | L42: =+L14+L23-L28 | O42: =+O14+O23-O28 | R42: =+R14+R23-R28 | U42: =+U14+U23-U28 | X42: =+X14+X23-X28 | AA42: =+AA14+AA23-AA28 | AD42: =+AD14+AD23-AD28 | AG42: =+AG14+AG23-AG28 | AJ42: =+AJ14+AJ23-AJ28 | AM42: =C42+F42+I42+L42+O42+R42+U42+X42+AA42+AD42+AG42+AJ42
E43: =(C46+C61)/(C13-C20) | H43: =(F46+F61)/(F13-F20) | K43: =(I46+I61)/(I13-I20) | N43: =(L46+L61)/(L13-L20) | Q43: =(O46+O61)/(O13-O20) | T43: =(R46+R61)/(R13-R20) | W43: =(U46+U61)/U13 | Z43: =(X46+X61)/X13 | AC43: =(AA46+AA61)/AA13 | AF43: =(AD46+AD61)/AD13 | AI43: =(AG46+AG61)/(AG13-AG20) | AL43: =(AJ46+AJ61)/(AJ13-AJ20) | AO43: =(AM46+AM61)/(AM13-AM20)
B44: COSTOS DE PRODUCCION | C44: =+C45+C60+C78 | E44: =C44/C$13 | F44: =+F45+F60+F78 | H44: =F44/F$13 | I44: =+I45+I60+I78 | K44: =I44/I$13 | L44: =+L45+L60+L78 | N44: =L44/L$13 | O44: =+O45+O60+O78 | Q44: =O44/O$13 | R44: =+R45+R60+R78 | T44: =R44/R$13 | U44: =+U45+U60+U78 | W44: =U44/U$13 | X44: =+X45+X60+X78 | Z44: =X44/X$13 | AA44: =+AA45+AA60+AA78 | AC44: =AA44/AA$13 | AD44: =+AD45+AD60+AD78 | AF44: =AD44/AD$13 | AG44: =+AG45+AG60+AG78 | AI44: =AG44/AG$13 | AJ44: =+AJ45+AJ60+AJ78 | AM44: =C44+F44+I44+L44+O44+R44+U44+X44+AA44+AD44+AG44+AJ44 | AO44: =AM44/AM$13
B45: COSTOS INDUSTRIALIZADOS | C45: =+C46+C57 | E45: =C45/C13 | F45: =+F46+F57 | H45: =F45/F13 | I45: =+I46+I57 | K45: =I45/I13 | L45: =+L46+L57 | N45: =L45/L13 | O45: =+O46+O57 | Q45: =O45/O13 | R45: =+R46+R57 | T45: =R45/R13 | U45: =+U46+U57 | W45: =U45/U13 | X45: =+X46+X57 | Z45: =X45/X13 | AA45: =+AA46+AA57 | AC45: =AA45/AA13 | AD45: =+AD46+AD57 | AF45: =AD45/AD13 | AG45: =+AG46+AG57 | AI45: =AG45/AG13 | AJ45: =+AJ46+AJ57 | AM45: =C45+F45+I45+L45+O45+R45+U45+X45+AA45+AD45+AG45+AJ45
B46: INSUMOS CI | C46: =SUM(C47:C56) | F46: =SUM(F47:F56) | I46: =SUM(I47:I56) | L46: =SUM(L47:L56) | O46: =SUM(O47:O56) | R46: =SUM(R47:R56) | U46: =SUM(U47:U56) | X46: =SUM(X47:X56) | Z46: =X46/X13 | AA46: =SUM(AA47:AA56) | AC46: =AA46/AA13 | AD46: =SUM(AD47:AD56) | AF46: =AD46/AD13 | AG46: =SUM(AG47:AG56) | AI46: =AG46/AG13 | AJ46: =SUM(AJ47:AJ56) | AM46: =C46+F46+I46+L46+O46+R46+U46+X46+AA46+AD46+AG46+AJ46
A47: 7105 | B47: COMPLEMENTO INDUSTRIALIZADO | C47: ='[44]Hoja 1'!$I$41 | D47: =C47/C5 | E47: =C47/C16 | F47: ='[45]Hoja 1'!$I$50 | G47: =F47/F5 | H47: =F47/F16 | J47: =I47/I5 | K47: =I47/I16 | M47: =L47/L5 | N47: =L47/L16 | P47: =O47/O5 | Q47: =O47/O16 | S47: =R47/R5 | T47: =R47/R16 | V47: =U47/U5 | W47: =U47/U16 | Y47: =X47/X5 | Z47: =X47/X16 | AB47: =AA47/AA5 | AC47: =AA47/AA16 | AE47: =AD47/AD5 | AF47: =AD47/AD16 | AH47: =AG47/AG5 | AI47: =AG47/AG16 | AK47: =AJ47/AJ5 | AL47: =AJ47/AJ16 | AM47: =C47+F47+I47+L47+O47+R47+U47+X47+AA47+AD47+AG47+AJ47 | AN47: =AM47/AM5 | AO47: =AM47/AM16
AM48: =C48+F48+I48+L48+O48+R48+U48+X48+AA48+AD48+AG48+AJ48 | AN48: =AM48/AM6
AM49: =C49+F49+I49+L49+O49+R49+U49+X49+AA49+AD49+AG49+AJ49
AM50: =C50+F50+I50+L50+O50+R50+U50+X50+AA50+AD50+AG50+AJ50
AM51: =C51+F51+I51+L51+O51+R51+U51+X51+AA51+AD51+AG51+AJ51
AM52: =C52+F52+I52+L52+O52+R52+U52+X52+AA52+AD52+AG52+AJ52
AM53: =C53+F53+I53+L53+O53+R53+U53+X53+AA53+AD53+AG53+AJ53
AM54: =C54+F54+I54+L54+O54+R54+U54+X54+AA54+AD54+AG54+AJ54
AM55: =C55+F55+I55+L55+O55+R55+U55+X55+AA55+AD55+AG55+AJ55
AM56: =C56+F56+I56+L56+O56+R56+U56+X56+AA56+AD56+AG56+AJ56
B57: FLETES CI | C57: =SUM(C58:C59) | D57: =C57/C12 | E57: =C57/C13 | F57: =SUM(F58:F59) | G57: =F57/(F5+F6) | H57: =F57/(F16+F17) | I57: =SUM(I58:I59) | J57: =I57/(I5+I6) | K57: =I57/I17 | L57: =SUM(L58:L59) | M57: =L57/(L5+L6) | N57: =L57/L17 | O57: =SUM(O58:O59) | P57: =O57/(O5+O6) | Q57: =O57/O17 | R57: =SUM(R58:R59) | S57: =R57/(R5+R6) | T57: =R57/R17 | U57: =SUM(U58:U59) | V57: =U57/(U5+U6) | W57: =U57/U17 | X57: =SUM(X58:X59) | Y57: =X57/(X5+X6) | Z57: 0.062445678 | AA57: =SUM(AA58:AA59) | AB57: =AA57/(AA5+AA6) | AC57: 0.062445678 | AD57: =SUM(AD58:AD59) | AE57: =AD57/(AD5+AD6) | AF57: 0.062445678 | AG57: =SUM(AG58:AG59) | AH57: =AG57/(AG5+AG6) | AI57: 0.062445678 | AJ57: =SUM(AJ58:AJ59) | AM57: =C57+F57+I57+L57+O57+R57+U57+X57+AA57+AD57+AG57+AJ57 | AN57: =AM57/(AM5+AM6) | AO57: 0.062445678
B58: INDUSTRIALIZADOS PROPIOS | AM58: =C58+F58+I58+L58+O58+R58+U58+X58+AA58+AD58+AG58+AJ58
B59: INDUSTRIALIZADOS TERCEROS | AM59: =C59+F59+I59+L59+O59+R59+U59+X59+AA59+AD59+AG59+AJ59
B60: COSTOS PREPARADOS | C60: =+C61+C72+C75+C76+C77 | F60: =+F61+F72+F75+F76+F77 | I60: =+I61+I72+I75+I76+I77 | L60: =+L61+L72+L75+L76+L77 | O60: =+O61+O72+O75+O76+O77 | R60: =+R61+R72+R75+R76+R77 | U60: =+U61+U72+U75+U76+U77 | X60: =+X61+X72+X75+X76+X77 | AA60: =+AA61+AA72+AA75+AA76+AA77 | AD60: =+AD61+AD72+AD75+AD76+AD77 | AG60: =+AG61+AG72+AG75+AG76+AG77 | AJ60: =+AJ61+AJ72+AJ75+AJ76+AJ77 | AM60: =C60+F60+I60+L60+O60+R60+U60+X60+AA60+AD60+AG60+AJ60
B61: INSUMOS CP | C61: =SUM(C62:C71) | F61: =SUM(F62:F71) | I61: =SUM(I62:I71) | L61: =SUM(L62:L71) | O61: =SUM(O62:O71) | R61: =SUM(R62:R71) | U61: =SUM(U62:U71) | W61: =U61/(U17+U18+U19) | X61: =SUM(X62:X71) | AA61: =SUM(AA62:AA71) | AD61: =SUM(AD62:AD71) | AG61: =SUM(AG62:AG71) | AJ61: =SUM(AJ62:AJ71) | AM61: =C61+F61+I61+L61+O61+R61+U61+X61+AA61+AD61+AG61+AJ61
A62: 7105 | B62: COMPLEMENTO PREPARADO AM | C62: ='[44]Hoja 1'!$I$40 | D62: =C62/C6 | E62: =C62/C17 | F62: ='[45]Hoja 1'!$I$49-'[45]Hoja 1'!$E$45 | G62: =F62/F6 | H62: =F62/F17 | J62: =I62/I6 | K62: =I62/I17 | M62: =L62/L6 | N62: =L62/L17 | P62: =O62/O6 | Q62: =O62/O17 | S62: =R62/R6 | T62: =R62/R17 | V62: =U62/U6 | W62: =U62/U17 | Y62: =X62/X6 | Z62: =X62/X17 | AB62: =AA62/AA6 | AC62: =AA62/AA17 | AE62: =AD62/AD6 | AF62: =AD62/AD17 | AH62: =AG62/AG6 | AI62: =AG62/AG17 | AK62: =AJ62/AJ6 | AL62: =AJ62/AJ17 | AM62: =C62+F62+I62+L62+O62+R62+U62+X62+AA62+AD62+AG62+AJ62 | AN62: =AM62/AM6 | AO62: =AM62/AM17
A63: 7105 | B63: COMPLEMENTO PREPARADO PM | C63: ='[44]Hoja 1'!$I$42 | D63: =C63/C7 | E63: =C63/C18 | F63: ='[45]Hoja 1'!$I$51 | G63: =F63/F7 | H63: =F63/F18 | J63: =I63/I7 | K63: =I63/I18 | M63: =L63/L7 | N63: =L63/L18 | P63: =O63/O7 | Q63: =O63/O18 | S63: =R63/R7 | T63: =R63/R18 | V63: =U63/U7 | W63: =U63/U18 | Y63: =X63/X7 | Z63: =X63/X18 | AB63: =AA63/AA7 | AC63: =AA63/AA18 | AE63: =AD63/AD7 | AF63: =AD63/AD18 | AH63: =AG63/AG7 | AI63: =AG63/AG18 | AK63: =AJ63/AJ7 | AL63: =AJ63/AJ18 | AM63: =C63+F63+I63+L63+O63+R63+U63+X63+AA63+AD63+AG63+AJ63 | AN63: =AM63/AM7 | AO63: =AM63/AM18
B64: ALMUERZO JORNADA UNICA | C64: ='[44]Hoja 1'!$I$43 | D64: =C64/C8 | E64: =C64/C19 | F64: ='[45]Hoja 1'!$I$52 | G64: =F64/F8 | H64: =F64/F19 | J64: =I64/I8 | K64: =I64/I19 | M64: =L64/L8 | N64: =L64/L19 | P64: =O64/O8 | Q64: =O64/O19 | S64: =R64/R8 | T64: =R64/R19 | V64: =U64/U8 | W64: =U64/U19 | Y64: =X64/X8 | Z64: =X64/X19 | AB64: =AA64/AA8 | AC64: =AA64/AA19 | AE64: =AD64/AD8 | AF64: =AD64/AD19 | AH64: =AG64/AG8 | AI64: =AG64/AG19 | AK64: =AJ64/AJ8 | AL64: =AJ64/AJ19 | AM64: =C64+F64+I64+L64+O64+R64+U64+X64+AA64+AD64+AG64+AJ64 | AN64: =AM64/AM8 | AO64: =AM64/AM19
B65: RACION MANIPULADORAS | AM65: =C65+F65+I65+L65+O65+R65+U65+X65+AA65+AD65+AG65+AJ65
B66: MEJORAMIENTO DE MENU | AM66: =C66+F66+I66+L66+O66+R66+U66+X66+AA66+AD66+AG66+AJ66
B67: REFRIGERIOS | AM67: =C67+F67+I67+L67+O67+R67+U67+X67+AA67+AD67+AG67+AJ67
AM71: =C71+F71+I71+L71+O71+R71+U71+X71+AA71+AD71+AG71+AJ71
B72: FLETES CP | C72: =SUM(C73:C74) | D72: =C72/C12 | E72: =C72/C13 | F72: =SUM(F73:F74) | G72: =F72/F12 | H72: =F72/F13 | I72: =SUM(I73:I74) | J72: =I72/I12 | K72: =I72/I13 | L72: =SUM(L73:L74) | M72: =L72/L12 | N72: =L72/L13 | O72: =SUM(O73:O74) | P72: =O72/O12 | Q72: =O72/O13 | R72: =SUM(R73:R74) | S72: =R72/R12 | T72: =R72/R13 | U72: =SUM(U73:U74) | V72: =U72/U12 | W72: =U72/U13 | X72: =SUM(X73:X74) | Y72: =X72/X12 | Z72: =X72/X13 | AA72: =SUM(AA73:AA74) | AB72: =AA72/AA12 | AC72: =AA72/AA13 | AD72: =SUM(AD73:AD74) | AE72: =AD72/AD12 | AF72: =AD72/AD13 | AG72: =SUM(AG73:AG74) | AH72: =AG72/AG12 | AI72: =AG72/AG13 | AJ72: =SUM(AJ73:AJ74) | AM72: =C72+F72+I72+L72+O72+R72+U72+X72+AA72+AD72+AG72+AJ72 | AN72: =AM72/AM12 | AO72: =AM72/AM13
B73: PREPARADOS PROPIOS | C73: ='GASTOS VEHICULOS'!C25*'%DIST'!B20 | F73: ='GASTOS VEHICULOS'!D25*'%DIST'!D20 | I73: ='GASTOS VEHICULOS'!E25*'%DIST'!F20 | L73: ='GASTOS VEHICULOS'!F25*'%DIST'!H20 | O73: ='GASTOS VEHICULOS'!G25*'%DIST'!J20 | R73: ='GASTOS VEHICULOS'!H25*'%DIST'!L20 | U73: ='GASTOS VEHICULOS'!I25*'%DIST'!N20 | X73: ='GASTOS VEHICULOS'!J25*'%DIST'!P20 | AA73: ='GASTOS VEHICULOS'!K25*'%DIST'!R20 | AD73: ='GASTOS VEHICULOS'!L25*'%DIST'!T20 | AG73: ='GASTOS VEHICULOS'!M25*'%DIST'!V20 | AJ73: ='GASTOS VEHICULOS'!N25*'%DIST'!X20 | AM73: =C73+F73+I73+L73+O73+R73+U73+X73+AA73+AD73+AG73+AJ73
A74: 73355001 | B74: PREPARADOS TERCEROS | C74: ='[9]Hoja 1'!$C$592+'[16]Hoja 1'!$D$129 | F74: ='[20]Hoja 1'!$C$203 | AM74: =C74+F74+I74+L74+O74+R74+U74+X74+AA74+AD74+AG74+AJ74
A75: 71100501 | B75: Material de empaque | AM75: =C75+F75+I75+L75+O75+R75+U75+X75+AA75+AD75+AG75+AJ75 | AN75: =AM75/AM12
A76: 71101501 | B76: Menaje | C76: ='[9]Hoja 1'!$C$558 | F76: ='[10]Hoja 1'!$C$521 | AM76: =C76+F76+I76+L76+O76+R76+U76+X76+AA76+AD76+AG76+AJ76 | AN76: =AM76/(AM6+AM7) | AO76: =AM76/$AM$13
A77: 73355501 | B77: Servicio de Gas | C77: ='[16]Hoja 1'!$D$131 | F77: ='[20]Hoja 1'!$C$205 | AM77: =C77+F77+I77+L77+O77+R77+U77+X77+AA77+AD77+AG77+AJ77 | AN77: =AM77/(AM6+AM7) | AO77: =AM77/$AM$13
B78: MANO DE OBRA DIRECTA | C78: =SUM(C79:C81) | E78: =C78/(C$13) | F78: =SUM(F79:F81) | H78: =F78/(F$13) | I78: =SUM(I79:I81) | K78: =I78/(I$13) | L78: =SUM(L79:L81) | N78: =L78/(L$13) | O78: =SUM(O79:O81) | Q78: =O78/(O$13) | R78: =SUM(R79:R81) | T78: =R78/(R$13) | U78: =SUM(U79:U81) | W78: =U78/(U$13) | X78: =SUM(X79:X81) | Z78: =X78/(X$13) | AA78: =SUM(AA79:AA81) | AC78: =AA78/(AA$13) | AD78: =SUM(AD79:AD81) | AF78: =AD78/(AD$13) | AG78: =SUM(AG79:AG81) | AI78: =AG78/(AG$13) | AJ78: =SUM(AJ79:AJ81) | AM78: =C78+F78+I78+L78+O78+R78+U78+X78+AA78+AD78+AG78+AJ78 | AN78: =AM78/AM$12 | AO78: =AM78/(AM$13)
B79: Manipuladoras | C79: ='[27]Hoja 1'!$E$13+'[28]Hoja 1'!$E$14 | F79: ='[35]Hoja 1'!$I$20-25458943+'[46]Hoja 1'!$C$27 | AM79: =C79+F79+I79+L79+O79+R79+U79+X79+AA79+AD79+AG79+AJ79 | AN79: =AM79/AM$12 | AO79: =AM79/AM13
B80: Personal Supervisor - Coordinadores | C80: ='[21]Hoja 1'!$D$25+'[21]Hoja 1'!$D$28+'[22]Hoja 1'!$D$24 | F80: ='[29]Hoja 1'!$D$30+'[29]Hoja 1'!$D$31+'[35]Hoja 1'!$D$19 | AM80: =C80+F80+I80+L80+O80+R80+U80+X80+AA80+AD80+AG80+AJ80 | AO80: =AM80/AM13
B81: Temporales MOD | AM81: =C81+F81+I81+L81+O81+R81+U81+X81+AA81+AD81+AG81+AJ81
R82: 2.723525e+08 | U82: 250
B83: OTROS COSTOS Y GASTOS INDIRECTOS | C83: =+C84+C89+C92+C96+C99+C109+C114+C120+C123+C127 | E83: =C83/(C$13) | F83: =+F84+F89+F92+F96+F99+F109+F114+F120+F123+F127 | H83: =F83/(F$13) | I83: =+I84+I89+I92+I96+I99+I109+I114+I120+I123+I127 | K83: =I83/(I$13) | L83: =+L84+L89+L92+L96+L99+L109+L114+L120+L123+L127 | N83: =L83/(L$13) | O83: =+O84+O89+O92+O96+O99+O109+O114+O120+O123+O127 | Q83: =O83/(O$13) | R83: =+R84+R89+R92+R96+R99+R109+R114+R120+R123+R127 | T83: =R83/(R$13) | U83: =+U84+U89+U92+U96+U99+U109+U114+U120+U123+U127 | W83: =U83/(U$13) | X83: =+X84+X89+X92+X96+X99+X109+X114+X120+X123+X127 | Z83: =X83/(X$13) | AA83: =+AA84+AA89+AA92+AA96+AA99+AA109+AA114+AA120+AA123+AA127 | AC83: =AA83/(AA$13) | AD83: =+AD84+AD89+AD92+AD96+AD99+AD109+AD114+AD120+AD123+AD127 | AF83: =AD83/(AD$13) | AG83: =+AG84+AG89+AG92+AG96+AG99+AG109+AG114+AG120+AG123+AG127 | AI83: =AG83/(AG$13) | AJ83: =+AJ84+AJ89+AJ92+AJ96+AJ99+AJ109+AJ114+AJ120+AJ123+AJ127 | AM83: =C83+F83+I83+L83+O83+R83+U83+X83+AA83+AD83+AG83+AJ83 | AO83: =AM83/(AM$13)
B84: COSTOS DE PERSONAL | C84: =SUM(C85:C88) | E84: =C84/C13 | F84: =SUM(F85:F88) | H84: =F84/(F$13) | I84: =SUM(I85:I88) | K84: =I84/(I$13) | L84: =SUM(L85:L88) | N84: =L84/(L$13) | O84: =SUM(O85:O88) | Q84: =O84/(O$13) | R84: =SUM(R85:R88) | T84: =R84/(R$13) | U84: =SUM(U85:U88) | W84: =U84/(U$13) | X84: =SUM(X85:X88) | Z84: =X84/(X$13) | AA84: =SUM(AA85:AA88) | AC84: =AA84/(AA$13) | AD84: =SUM(AD85:AD88) | AF84: =AD84/(AD$13) | AG84: =SUM(AG85:AG88) | AI84: =AG84/(AG$13) | AJ84: =SUM(AJ85:AJ88) | AM84: =C84+F84+I84+L84+O84+R84+U84+X84+AA84+AD84+AG84+AJ84 | AO84: =AM84/(AM$13)
B85: Costos Indirectos de Personal | C85: ='GASTOS OPERATIVOS'!C17*'%DIST'!C4 | F85: ='GASTOS OPERATIVOS'!D17*'%DIST'!E4 | AM85: =C85+F85+I85+L85+O85+R85+U85+X85+AA85+AD85+AG85+AJ85 | AO85: =AM85/(AM$13)
A86: 72055101 | B86: Dotación y Suministros | F86: ='[20]Hoja 1'!$C$179 | AM86: =C86+F86+I86+L86+O86+R86+U86+X86+AA86+AD86+AG86+AJ86 | AO86: =AM86/(AM$13)
A87: 72058401 | B87: Gastos Medicos | C87: ='[16]Hoja 1'!$D$118 | F87: ='[10]Hoja 1'!$C$553 | AM87: =C87+F87+I87+L87+O87+R87+U87+X87+AA87+AD87+AG87+AJ87 | AO87: =AM87/(AM$13)
A88: 53954002 | B88: Incapacidades | F88: ='[20]Hoja 1'!$C$153 | AM88: =C88+F88+I88+L88+O88+R88+U88+X88+AA88+AD88+AG88+AJ88
B89: HONORARIOS | C89: =SUM(C90:C91) | F89: =SUM(F90:F91) | H89: =F89/(F$13) | I89: =SUM(I90:I91) | K89: =I89/(I$13) | L89: =SUM(L90:L91) | N89: =L89/(L$13) | O89: =SUM(O90:O91) | R89: =SUM(R90:R91) | T89: =R89/(R$13) | U89: =SUM(U90:U91) | W89: =U89/(U$13) | X89: =SUM(X90:X91) | Z89: =X89/(X$13) | AA89: =SUM(AA90:AA91) | AC89: =AA89/(AA$13) | AD89: =SUM(AD90:AD91) | AG89: =SUM(AG90:AG91) | AI89: =AG89/(AG$13) | AJ89: =SUM(AJ90:AJ91) | AM89: =C89+F89+I89+L89+O89+R89+U89+X89+AA89+AD89+AG89+AJ89 | AO89: =AM89/(AM$13)
B90: Asesoría Juridica | C90: ='[47]Hoja 1'!$C$646 | AM90: =C90+F90+I90+L90+O90+R90+U90+X90+AA90+AD90+AG90+AJ90
B91: Asesoría Tecnica/ Capacitaciones | AM91: =C91+F91+I91+L91+O91+R91+U91+X91+AA91+AD91+AG91+AJ91
B92: ARRENDAMIENTOS | C92: =SUM(C93:C95) | F92: =SUM(F93:F95) | H92: =F92/(F$13) | I92: =SUM(I93:I95) | K92: =I92/(I$13) | L92: =SUM(L93:L95) | N92: =L92/(L$13) | O92: =SUM(O93:O95) | R92: =SUM(R93:R95) | T92: =R92/(R$13) | U92: =SUM(U93:U95) | W92: =U92/(U$13) | X92: =SUM(X93:X95) | Z92: =X92/(X$13) | AA92: =SUM(AA93:AA95) | AC92: =AA92/(AA$13) | AD92: =SUM(AD93:AD95) | AG92: =SUM(AG93:AG95) | AI92: =AG92/(AG$13) | AJ92: =SUM(AJ93:AJ95) | AM92: =C92+F92+I92+L92+O92+R92+U92+X92+AA92+AD92+AG92+AJ92 | AO92: =AM92/(AM$13)
B93: Construcciones y Edificaciones | AM93: =C93+F93+I93+L93+O93+R93+U93+X93+AA93+AD93+AG93+AJ93
B94: Maquinaria y Equipo | AM94: =C94+F94+I94+L94+O94+R94+U94+X94+AA94+AD94+AG94+AJ94
B95: Equipo de Oficina | AM95: =C95+F95+I95+L95+O95+R95+U95+X95+AA95+AD95+AG95+AJ95
B96: SEGUROS | C96: =SUM(C97:C98) | E96: =C96/(AM$13) | F96: =SUM(F97:F98) | H96: =F96/(F$13) | I96: =SUM(I97:I98) | K96: =I96/(I$13) | L96: =SUM(L97:L98) | N96: =L96/(L$13) | O96: =SUM(O97:O98) | R96: =SUM(R97:R98) | T96: =R96/(R$13) | U96: =SUM(U97:U98) | W96: =U96/(U$13) | X96: =SUM(X97:X98) | Z96: =X96/(X$13) | AA96: =SUM(AA97:AA98) | AC96: =AA96/(AA$13) | AD96: =SUM(AD97:AD98) | AG96: =SUM(AG97:AG98) | AI96: =AG96/(AG$13) | AJ96: =SUM(AJ97:AJ98) | AM96: =C96+F96+I96+L96+O96+R96+U96+X96+AA96+AD96+AG96+AJ96 | AN96: =AM96/AM12 | AO96: =AM96/(AM$13)
B97: Cumplimiento | C97: ='[47]Hoja 1'!$C$649+'[16]Hoja 1'!$D$122 | F97: ='[20]Hoja 1'!$C$195 | AM97: =C97+F97+I97+L97+O97+R97+U97+X97+AA97+AD97+AG97+AJ97
B98: Responsabilidad Civil Y Extracontractual | C98: ='[16]Hoja 1'!$D$124 | F98: ='[20]Hoja 1'!$C$197 | AM98: =C98+F98+I98+L98+O98+R98+U98+X98+AA98+AD98+AG98+AJ98
B99: SERVICIOS | C99: =SUM(C100:C108) | E99: =C99/(C$13) | F99: =SUM(F100:F108) | H99: =F99/(F$13) | I99: =SUM(I100:I108) | K99: =I99/(I$13) | L99: =SUM(L100:L108) | N99: =L99/(L$13) | O99: =SUM(O100:O108) | Q99: =O99/(O$13) | R99: =SUM(R100:R108) | T99: =R99/(R$13) | U99: =SUM(U100:U108) | W99: =U99/(U$13) | X99: =SUM(X100:X108) | Z99: =X99/(X$13) | AA99: =SUM(AA100:AA108) | AC99: =AA99/(AA$13) | AD99: =SUM(AD100:AD108) | AG99: =SUM(AG100:AG108) | AI99: =AG99/(AG$13) | AJ99: =SUM(AJ100:AJ108) | AM99: =C99+F99+I99+L99+O99+R99+U99+X99+AA99+AD99+AG99+AJ99 | AN99: =AM99/AM12 | AO99: =AM99/(AM$13)
B100: Aseo y Vigilancia | AM100: =C100+F100+I100+L100+O100+R100+U100+X100+AA100+AD100+AG100+AJ100
B101: Temporales Serv | AM101: =C101+F101+I101+L101+O101+R101+U101+X101+AA101+AD101+AG101+AJ101
B102: Mensajeria | AM102: =C102+F102+I102+L102+O102+R102+U102+X102+AA102+AD102+AG102+AJ102
A103: 73351502 | B103: Laboratorio | F103: ='[20]Hoja 1'!C200 | AM103: =C103+F103+I103+L103+O103+R103+U103+X103+AA103+AD103+AG103+AJ103
A104: 73351503 | B104: Fumigacion | C104: ='[16]Hoja 1'!$D$127 | F104: ='[20]Hoja 1'!C201 | AM104: =C104+F104+I104+L104+O104+R104+U104+X104+AA104+AD104+AG104+AJ104
A105: 73352501 | B105: Acueducto y Alcantarillado | AM105: =C105+F105+I105+L105+O105+R105+U105+X105+AA105+AD105+AG105+AJ105
B106: Energia | AM106: =C106+F106+I106+L106+O106+R106+U106+X106+AA106+AD106+AG106+AJ106
B107: Telefono e Internet | AM107: =C107+F107+I107+L107+O107+R107+U107+X107+AA107+AD107+AG107+AJ107
B108: Correo, porte y telegramas | AM108: =C108+F108+I108+L108+O108+R108+U108+X108+AA108+AD108+AG108+AJ108
B109: GASTOS LEGALES | C109: =SUM(C110:C113) | E109: =C109/(C$13) | F109: =SUM(F110:F113) | H109: =F109/(F$13) | I109: =SUM(I110:I113) | K109: =I109/(I$13) | L109: =SUM(L110:L113) | N109: =L109/(L$13) | O109: =SUM(O110:O113) | Q109: =O109/(O$13) | R109: =SUM(R110:R113) | T109: =R109/(R$13) | U109: =SUM(U110:U113) | W109: =U109/(U$13) | X109: =SUM(X110:X113) | Z109: =X109/(X$13) | AA109: =SUM(AA110:AA113) | AC109: =AA109/(AA$13) | AD109: =SUM(AD110:AD113) | AG109: =SUM(AG110:AG113) | AI109: =AG109/(AG$13) | AJ109: =SUM(AJ110:AJ113) | AM109: =C109+F109+I109+L109+O109+R109+U109+X109+AA109+AD109+AG109+AJ109 | AO109: =AM109/(AM$13)
...

Sheet YUMBO
B2: CORPORACIÓN HACIA UN VALLE SOLIDARIO | C2: PYG YUMBO 2026
B3: DIAS DE ATENCIÓN | C3: 5 | F3: 20 | I3: 19 | L3: 19 | O3: 19 | R3: 13 | U3: 14 | X3: 19 | AA3: 22 | AD3: 16 | AG3: 19 | AJ3: 4 | AM3: =SUM(C3:AL3)
C4: ENE | D4: x racion | E4: % | F4: FEB | G4: x racion | H4: % | I4: MAR | J4: x racion | K4: % | L4: ABR | M4: x racion | N4: % | O4: MAY | P4: x racion | Q4: % | R4: JUN | S4: x racion | T4: % | U4: JUL | V4: x racion | W4: % | X4: AGO | Y4: x racion | Z4: % | AA4: SEP | AB4: x racion | AC4: % | AD4: OCT | AE4: x racion | AF4: % | AG4: NOV | AH4: x racion | AI4: % | AJ4: DIC | AK4: x racion | AL4: % | AM4: ACUMULADO | AN4: x racion | AO4: %
B5: COMPLEMENTO AM/PM (Rac) | AM5: =C5+F5+I5+L5+O5+R5+U5+X5+AA5+AD5+AG5+AJ5 | AO5: =AM5/AM12
B6: REFUERZO COMPLEMENTO AM/PM (Rac) | AM6: =C6+F6+I6+L6+O6+R6+U6+X6+AA6+AD6+AG6+AJ6 | AO6: =AM6/AM12
B7: ALMUERZO JORNADA UNICA (Rac) | AM7: =C7+F7+I7+L7+O7+R7+U7+X7+AA7+AD7+AG7+AJ7 | AO7: =AM7/AM12
AM8: =C8+F8+I8+L8+O8+R8+U8+X8+AA8+AD8+AG8+AJ8
B9: NOVEDADES (Rac) | AM9: =C9+F9+I9+L9+O9+R9+U9+X9+AA9+AD9+AG9+AJ9
AM10: =C10+F10+I10+L10+O10+R10+U10+X10+AA10+AD10+AG10+AJ10
AM11: =C11+F11+I11+L11+O11+R11+U11+X11+AA11+AD11+AG11+AJ11
B12: TOTAL RACIONES | C12: =SUM(C5:C11) | F12: =SUM(F5:F11) | I12: =SUM(I5:I11) | L12: =SUM(L5:L11) | O12: =SUM(O5:O11) | R12: =SUM(R5:R11) | U12: =SUM(U5:U11) | X12: =SUM(X5:X11) | AA12: =SUM(AA5:AA11) | AD12: =SUM(AD5:AD11) | AG12: =SUM(AG5:AG11) | AJ12: =SUM(AJ5:AJ11) | AM12: =C12+F12+I12+L12+O12+R12+U12+X12+AA12+AD12+AG12+AJ12
B13: INGRESOS BRUTOS | C13: =C14+C23 | F13: =F14+F23 | I13: =I14+I23 | L13: =L14+L23 | O13: =O14+O23 | R13: =R14+R23 | U13: =U14+U23 | X13: =X14+X23 | AA13: =AA14+AA23 | AD13: =AD14+AD23 | AG13: =AG14+AG23 | AJ13: =AJ14+AJ23 | AM13: =C13+F13+I13+L13+O13+R13+U13+X13+AA13+AD13+AG13+AJ13
B14: OPERACIONALES | C14: =C15 | F14: =F15 | I14: =I15 | L14: =L15 | O14: =O15 | R14: =R15 | U14: =U15 | X14: =X15 | AA14: =AA15 | AD14: =AD15 | AG14: =AG15 | AJ14: =AJ15 | AM14: =C14+F14+I14+L14+O14+R14+U14+X14+AA14+AD14+AG14+AJ14
B15: INDUSTRIAS MANUFACTURERAS | C15: =SUM(C16:C22) | F15: =SUM(F16:F22) | I15: =SUM(I16:I22) | L15: =SUM(L16:L22) | O15: =SUM(O16:O22) | R15: =SUM(R16:R22) | U15: =SUM(U16:U22) | X15: =SUM(X16:X22) | AA15: =SUM(AA16:AA22) | AD15: =SUM(AD16:AD22) | AG15: =SUM(AG16:AG22) | AJ15: =SUM(AJ16:AJ22) | AM15: =C15+F15+I15+L15+O15+R15+U15+X15+AA15+AD15+AG15+AJ15 | AO15: =AM15/AM15
B16: COMPLEMENTO AM/PM (Fac) | D16: =C16/C5 | G16: =F16/F5 | AM16: =C16+F16+I16+L16+O16+R16+U16+X16+AA16+AD16+AG16+AJ16
B17: REFUERZO COMPLEMENTO AM/PM (Fac) | D17: =C17/C6 | G17: =F17/F6 | AM17: =C17+F17+I17+L17+O17+R17+U17+X17+AA17+AD17+AG17+AJ17
B18: ALMUERZO JORNADA UNICA (Fac) | D18: =C18/C7 | G18: =F18/F7 | AM18: =C18+F18+I18+L18+O18+R18+U18+X18+AA18+AD18+AG18+AJ18
AM19: =C19+F19+I19+L19+O19+R19+U19+X19+AA19+AD19+AG19+AJ19
B20: NOVEDADES (Fac) | AM20: =C20+F20+I20+L20+O20+R20+U20+X20+AA20+AD20+AG20+AJ20
AM21: =C21+F21+I21+L21+O21+R21+U21+X21+AA21+AD21+AG21+AJ21
AM22: =C22+F22+I22+L22+O22+R22+U22+X22+AA22+AD22+AG22+AJ22
B23: NO OPERACIONALES | C23: =C24 | F23: =F24 | I23: =I24 | L23: =L24 | O23: =O24 | R23: =R24 | U23: =U24 | X23: =X24 | AA23: =AA24 | AM23: =C23+F23+I23+L23+O23+R23+U23+X23+AA23+AD23+AG23+AJ23
B24: FINANCIEROS | C24: =SUM(C25:C27) | F24: =SUM(F25:F27) | I24: =SUM(I25:I27) | L24: =SUM(L25:L27) | O24: =SUM(O25:O27) | R24: =SUM(R25:R27) | U24: =SUM(U25:U27) | X24: =SUM(X25:X27) | AA24: =SUM(AA25:AA27) | AD24: =SUM(AD25:AD27) | AG24: =SUM(AG25:AG27) | AJ24: =SUM(AJ25:AJ27) | AM24: =C24+F24+I24+L24+O24+R24+U24+X24+AA24+AD24+AG24+AJ24
B25: Intereses | AM25: =C25+F25+I25+L25+O25+R25+U25+X25+AA25+AD25+AG25+AJ25
B26: Descuentos Comerciales | AM26: =C26+F26+I26+L26+O26+R26+U26+X26+AA26+AD26+AG26+AJ26
B27: otros Fin | AM27: =C27+F27+I27+L27+O27+R27+U27+X27+AA27+AD27+AG27+AJ27
B28: DESCUENTOS - GASTO OPERACIONAL | C28: =+C29 | F28: =+F29 | I28: =+I29 | L28: =+L29 | O28: =+O29 | R28: =+R29 | U28: =+U29 | X28: =+X29 | AA28: =+AA29 | AD28: =+AD29 | AG28: =+AG29 | AJ28: =+AJ29 | AM28: =C28+F28+I28+L28+O28+R28+U28+X28+AA28+AD28+AG28+AJ28
B29: OTROS | C29: =SUM(C30:C37) | E29: =C29/C13 | F29: =SUM(F30:F37) | H29: =F29/F13 | I29: =SUM(I30:I37) | K29: =I29/I13 | L29: =SUM(L30:L37) | N29: =L29/L13 | O29: =SUM(O30:O37) | Q29: =O29/O13 | R29: =SUM(R30:R37) | T29: =R29/R13 | U29: =SUM(U30:U37) | W29: =U29/U13 | X29: =SUM(X30:X38) | Z29: =X29/X13 | AA29: =SUM(AA30:AA38) | AC29: =AA29/AA13 | AD29: =SUM(AD30:AD38) | AF29: =AD29/AD13 | AG29: =SUM(AG30:AG38) | AI29: =AG29/AG13 | AJ29: =SUM(AJ30:AJ41) | AM29: =C29+F29+I29+L29+O29+R29+U29+X29+AA29+AD29+AG29+AJ29 | AO29: =AM29/AM13
B30: Procultura 0,5% | C30: =C$13*0.5% | F30: =F$13*0.5% | I30: =I$13*0.5% | L30: =L$13*0.5% | O30: =O$13*0.5% | R30: =R$13*0.5% | U30: =U$13*0.5% | X30: =X$13*0.5% | AA30: =AA$13*0.5% | AD30: =AD$13*0.5% | AG30: =AG$13*0.5% | AJ30: =AJ$13*0.5% | AM30: =C30+F30+I30+L30+O30+R30+U30+X30+AA30+AD30+AG30+AJ30
B31: Prohospitales 1% | C31: =C$13*1% | F31: =F$13*1% | I31: =I$13*1% | L31: =L$13*1% | O31: =O$13*1% | R31: =R$13*1% | U31: =U$13*1% | X31: =X$13*1% | AA31: =AA$13*1% | AD31: =AD$13*1% | AG31: =AG$13*1% | AJ31: =AJ$13*1% | AM31: =C31+F31+I31+L31+O31+R31+U31+X31+AA31+AD31+AG31+AJ31
B32: Rete Ica 0,6% | C32: =(C13*80%)*0.6% | F32: =(F13*80%)*0.6% | I32: =(I13*1%)*0.6% | L32: =(L13*1%)*0.6% | O32: =(O13*1%)*0.6% | R32: =(R13*1%)*0.6% | U32: =(U13*1%)*0.6% | X32: =(X13*1%)*0.6% | AA32: =(AA13*1%)*0.6% | AD32: =(AD13*1%)*0.6% | AG32: =(AG13*1%)*0.6% | AJ32: =(AJ13*1%)*0.6% | AM32: =C32+F32+I32+L32+O32+R32+U32+X32+AA32+AD32+AG32+AJ32
B33: Adulto Mayor 2% | C33: =C13*2% | F33: =F13*2% | I33: =I13*2% | L33: =L13*2% | O33: =O13*2% | R33: =R13*2% | U33: =U13*2% | X33: =X13*2% | AA33: =AA13*2% | AD33: =AD13*2% | AG33: =AG13*2% | AJ33: =AJ13*2% | AM33: =C33+F33+I33+L33+O33+R33+U33+X33+AA33+AD33+AG33+AJ33
B34: Retefuente | I34: =(I13*1%)*3.5% | L34: =(L13*1%)*3.5% | O34: =(O13*1%)*3.5% | R34: =(R13*1%)*3.5% | U34: =(U13*1%)*3.5% | X34: =(X13*1%)*3.5% | AA34: =(AA13*1%)*3.5% | AD34: =(AD13*1%)*3.5% | AG34: =(AG13*1%)*3.5% | AJ34: =(AJ13*1%)*3.5% | AM34: =C34+F34+I34+L34+O34+R34+U34+X34+AA34+AD34+AG34+AJ34
B35: Prodeporte 2,5% | C35: =C$13*2.5% | F35: =F$13*2.5% | I35: =I$13*2.5% | L35: =L$13*2.5% | O35: =O$13*2.5% | R35: =R$13*2.5% | U35: =U$13*2.5% | X35: =X$13*2.5% | AA35: =AA$13*2.5% | AD35: =AD$13*2.5% | AG35: =AG$13*2.5% | AJ35: =AJ$13*2.5% | AM35: =C35+F35+I35+L35+O35+R35+U35+X35+AA35+AD35+AG35+AJ35
B36: 2% Juzgado de Familia | C36: =C13*2% | F36: =F13*2% | I36: =I13*2% | L36: =L13*2% | O36: =O13*2% | R36: =R13*2% | U36: =U13*2% | X36: =X13*2% | AA36: =AA13*2% | AD36: =AD13*2% | AG36: =AG13*2% | AJ36: =AJ13*2% | AM36: =C36+F36+I36+L36+O36+R36+U36+X36+AA36+AD36+AG36+AJ36
B37: 0,5% Propacifico | C37: =C$13*0.5% | F37: =F$13*0.5% | I37: =I$13*0.5% | L37: =L$13*0.5% | O37: =O$13*0.5% | R37: =R$13*0.5% | U37: =U$13*0.5% | X37: =X$13*0.5% | AA37: =AA$13*0.5% | AD37: =AD$13*0.5% | AG37: =AG$13*0.5% | AJ37: =AJ$13*0.5% | AM37: =C37+F37+I37+L37+O37+R37+U37+X37+AA37+AD37+AG37+AJ37
AM38: =C38+F38+I38+L38+O38+R38+U38+X38+AA38+AD38+AG38+AJ38
B42: TOTAL INGRESOS NETOS | C42: =+C14+C23-C28 | F42: =+F14+F23-F28 | I42: =+I14+I23-I28 | L42: =+L14+L23-L28 | O42: =+O14+O23-O28 | R42: =+R14+R23-R28 | U42: =+U14+U23-U28 | X42: =+X14+X23-X28 | AA42: =+AA14+AA23-AA28 | AD42: =+AD14+AD23-AD28 | AG42: =+AG14+AG23-AG28 | AJ42: =+AJ14+AJ23-AJ28 | AM42: =C42+F42+I42+L42+O42+R42+U42+X42+AA42+AD42+AG42+AJ42
AG43: =161491188.56-AG29
B44: COSTOS DE PRODUCCION | C44: =+C45+C60+C78 | F44: =+F45+F60+F78 | H44: =F44/F$13 | I44: =+I45+I60+I78 | K44: =I44/I$13 | L44: =+L45+L60+L78 | N44: =L44/L$13 | O44: =+O45+O60+O78 | Q44: =O44/O$13 | R44: =+R45+R60+R78 | T44: =R44/R$13 | U44: =+U45+U60+U78 | W44: =U44/U$13 | X44: =+X45+X60+X78 | Z44: =X44/X$13 | AA44: =+AA45+AA60+AA78 | AC44: =AA44/AA$13 | AD44: =+AD45+AD60+AD78 | AF44: =AD44/AD$13 | AG44: =+AG45+AG60+AG78 | AI44: =AG44/AG$13 | AJ44: =+AJ45+AJ60+AJ78 | AM44: =C44+F44+I44+L44+O44+R44+U44+X44+AA44+AD44+AG44+AJ44 | AO44: =AM44/AM$13
B45: COSTOS INDUSTRIALIZADOS | F45: =+F46+F57 | I45: =+I46+I57 | L45: =+L46+L57 | O45: =+O46+O57 | R45: =+R46+R57 | U45: =+U46+U57 | X45: =+X46+X57 | AA45: =+AA46+AA57 | AD45: =+AD46+AD57 | AG45: =+AG46+AG57 | AJ45: =+AJ46+AJ57 | AM45: =C45+F45+I45+L45+O45+R45+U45+X45+AA45+AD45+AG45+AJ45
B46: INSUMOS CI | C46: =SUM(C47:C56)+C57 | F46: =SUM(F47:F56) | I46: =SUM(I47:I56) | L46: =SUM(L47:L56) | O46: =SUM(O47:O56) | R46: =SUM(R47:R56) | U46: =SUM(U47:U56) | X46: =SUM(X47:X56) | AA46: =SUM(AA47:AA56) | AD46: =SUM(AD47:AD56) | AG46: =SUM(AG47:AG56) | AI46: =AG46/AG13 | AJ46: =SUM(AJ47:AJ56) | AM46: =C46+F46+I46+L46+O46+R46+U46+X46+AA46+AD46+AG46+AJ46
B47: RACION PARA PREPARAR EN CASA (Ins) | G47: =F47/F5 | H47: =F47/F13 | J47: =I47/I5 | K47: =I47/I13 | M47: =L47/L5 | N47: =L47/L13 | S47: =R47/R5 | T47: =R47/R13 | V47: =U47/U5 | W47: =U47/U13 | Y47: =X47/X5 | Z47: =X47/X13 | AC47: =AA47/AA13 | AF47: =AD47/AD13 | AM47: =C47+F47+I47+L47+O47+R47+U47+X47+AA47+AD47+AG47+AJ47 | AN47: =AM47/AM5 | AO47: =AM47/AM13
AB48: =AA48/AA6 | AC48: =AA48/AA17 | AE48: =AD48/AD6 | AF48: =AD48/AD17 | AH48: =AG48/AG6 | AI48: =AG48/AG17 | AM48: =C48+F48+I48+L48+O48+R48+U48+X48+AA48+AD48+AG48+AJ48
AB49: =AA49/AA7 | AC49: =AA49/AA18 | AE49: =AD49/AD7 | AF49: =AD49/AD18 | AH49: =AG49/AG7 | AI49: =AG49/AG18 | AM49: =C49+F49+I49+L49+O49+R49+U49+X49+AA49+AD49+AG49+AJ49
AM50: =C50+F50+I50+L50+O50+R50+U50+X50+AA50+AD50+AG50+AJ50
AM51: =C51+F51+I51+L51+O51+R51+U51+X51+AA51+AD51+AG51+AJ51
B52: REFRIGERIOS (Ins) | AM52: =C52+F52+I52+L52+O52+R52+U52+X52+AA52+AD52+AG52+AJ52
AM53: =C53+F53+I53+L53+O53+R53+U53+X53+AA53+AD53+AG53+AJ53
B57: FLETES CI | F57: =SUM(F58:F59) | G57: =F57/F12 | H57: =F57/F13 | I57: =SUM(I58:I59) | J57: =I57/I12 | K57: =I57/I13 | L57: =SUM(L58:L59) | M57: =L57/L12 | N57: =L57/L13 | O57: =SUM(O58:O59) | R57: =SUM(R58:R59) | S57: =R57/R12 | T57: =R57/R13 | U57: =SUM(U58:U59) | V57: =U57/U12 | W57: =U57/U13 | X57: =SUM(X58:X59) | Y57: =X57/X12 | Z57: =X57/X13 | AA57: =SUM(AA58:AA59) | AB57: =AA57/AA12 | AC57: =AA57/AA13 | AD57: =SUM(AD58:AD59) | AE57: =AD57/AD12 | AF57: =AD57/AD13 | AG57: =SUM(AG58:AG59) | AH57: =AG57/AG12 | AI57: =AG57/AG13 | AJ57: =SUM(AJ58:AJ59) | AM57: =C57+F57+I57+L57+O57+R57+U57+X57+AA57+AD57+AG57+AJ57
B58: INDUSTRIALIZADOS PROPIOS | G58: =F58/F5 | H58: =F58/F13 | J58: =I58/I5 | K58: =I58/I13 | M58: =L58/L5 | N58: =L58/L13 | S58: =R58/R5 | T58: =R58/R13 | V58: =U58/U5 | W58: =U58/U13 | Y58: =X58/X5 | Z58: =X58/X13 | AB58: =AA58/AA12 | AC58: =AA58/AA13 | AE58: =AD58/AD12 | AF58: =AD58/AD13 | AH58: =AG58/AG12 | AI58: =AG58/AG13 | AM58: =C58+F58+I58+L58+O58+R58+U58+X58+AA58+AD58+AG58+AJ58 | AO58: =AM58/AM$16
B59: INDUSTRIALIZADOS TERCEROS | G59: =F59/F5 | H59: =F59/F13 | J59: =I59/I5 | K59: =I59/I13 | M59: =L59/L5 | N59: =L59/L13 | S59: =R59/R5 | T59: =R59/R13 | V59: =U59/U5 | W59: =U59/U13 | Y59: =X59/X5 | Z59: =X59/X13 | AB59: =AA59/AA12 | AC59: =AA59/AA13 | AE59: =AD59/AD12 | AF59: =AD59/AD13 | AH59: =AG59/AG12 | AI59: =AG59/AG13 | AM59: =C59+F59+I59+L59+O59+R59+U59+X59+AA59+AD59+AG59+AJ59 | AO59: =AM59/(AM16)
B60: COSTOS PREPARADOS | C60: =+C61+C72+C75+C76+C77 | F60: =+F61+F72+F75+F76+F77 | I60: =+I61+I72+I75+I76+I77 | L60: =+L61+L72+L75+L76+L77 | O60: =+O61+O72+O75+O76+O77 | R60: =+R61+R72+R75+R76+R77 | U60: =+U61+U72+U75+U76+U77 | X60: =+X61+X72+X75+X76+X77 | AA60: =+AA61+AA72+AA75+AA76+AA77 | AD60: =+AD61+AD72+AD75+AD76+AD77 | AG60: =+AG61+AG72+AG75+AG76+AG77 | AJ60: =+AJ61+AJ72+AJ75+AJ76+AJ77 | AM60: =C60+F60+I60+L60+O60+R60+U60+X60+AA60+AD60+AG60+AJ60
B61: INSUMOS CP | C61: =SUM(C62:C71) | E61: =C61/(C$13-C$19-C$20) | F61: =SUM(F62:F71) | H61: =F61/(F$13-F$19-F$20) | I61: =SUM(I62:I71) | K61: =I61/(I$13-I$19-I$20) | L61: =SUM(L62:L71) | N61: =L61/L13 | O61: =SUM(O62:O71) | Q61: =O61/(O13-O20) | R61: =SUM(R62:R71) | T61: =R61/R13 | U61: =SUM(U62:U71) | W61: =U61/U13 | X61: =SUM(X62:X71) | Z61: =X61/X13 | AA61: =SUM(AA62:AA71) | AC61: =AA61/(AA13-AA19-AA20) | AD61: =SUM(AD62:AD71) | AF61: =AD61/(AD13-AD19-AD20) | AG61: =SUM(AG62:AG71) | AI61: =AG61/(AG13-AG19) | AJ61: =SUM(AJ62:AJ71) | AL61: =AJ61/(AJ13-AJ19) | AM61: =C61+F61+I61+L61+O61+R61+U61+X61+AA61+AD61+AG61+AJ61 | AO61: =AM61/(AM$13-AM$19-AM$20)
A62: 7105 | B62: COMPLEMENTO AM/PM (Ins) | C62: ='[44]Hoja 1'!$I$47 | D62: =C62/C5 | E62: =C62/C16 | F62: ='[45]Hoja 1'!$I$56 | G62: =F62/F5 | H62: =F62/F16 | J62: =I62/I5 | K62: =I62/I16 | M62: =L62/L5 | N62: =L62/L16 | P62: =O62/O5 | Q62: =O62/O16 | S62: =R62/R5 | T62: =R62/R16 | V62: =U62/U5 | W62: =U62/U16 | Y62: =X62/X5 | Z62: =X62/X16 | AB62: =AA62/AA5 | AC62: =AA62/AA16 | AE62: =AD62/AD5 | AF62: =AD62/AD16 | AH62: =AG62/AG5 | AI62: =AG62/AG16 | AK62: =AJ62/AJ5 | AL62: =AJ62/AJ16 | AM62: =C62+F62+I62+L62+O62+R62+U62+X62+AA62+AD62+AG62+AJ62 | AN62: =AM62/AM5 | AO62: =AM62/AM16
A63: 7105 | B63: REFUERZO COMPLEMENTO AM/PM (Ins) | C63: ='[44]Hoja 1'!$I$49 | D63: =C63/C6 | E63: =C63/C17 | F63: ='[45]Hoja 1'!$I$58 | G63: =F63/F6 | H63: =F63/F17 | J63: =I63/I6 | K63: =I63/I17 | M63: =L63/L6 | N63: =L63/L17 | P63: =O63/O6 | Q63: =O63/O17 | S63: =R63/R6 | T63: =R63/R17 | V63: =U63/U6 | W63: =U63/U17 | Y63: =X63/X6 | Z63: =X63/X17 | AB63: =AA63/AA6 | AC63: =AA63/AA17 | AE63: =AD63/AD6 | AF63: =AD63/AD17 | AH63: =AG63/AG6 | AI63: =AG63/AG17 | AK63: =AJ63/AJ6 | AL63: =AJ63/AJ17 | AM63: =C63+F63+I63+L63+O63+R63+U63+X63+AA63+AD63+AG63+AJ63 | AN63: =AM63/AM6 | AO63: =AM63/AM17
A64: 7105 | B64: ALMUERZO JORNADA UNICA | C64: ='[44]Hoja 1'!$I$51 | D64: =C64/C7 | E64: =C64/C18 | F64: ='[45]Hoja 1'!$I$60 | G64: =F64/F7 | H64: =F64/F18 | J64: =I64/I7 | K64: =I64/I18 | M64: =L64/L7 | N64: =L64/L18 | P64: =O64/O7 | Q64: =O64/O18 | S64: =R64/R7 | T64: =R64/R18 | V64: =U64/U7 | W64: =U64/U18 | Y64: =X64/X7 | Z64: =X64/X18 | AB64: =AA64/AA7 | AC64: =AA64/AA18 | AE64: =AD64/AD7 | AF64: =AD64/AD18 | AH64: =AG64/AG7 | AI64: =AG64/AG18 | AK64: =AJ64/AJ7 | AL64: =AJ64/AJ18 | AM64: =C64+F64+I64+L64+O64+R64+U64+X64+AA64+AD64+AG64+AJ64 | AN64: =AM64/AM7 | AO64: =AM64/AM18
AM65: =C65+F65+I65+L65+O65+R65+U65+X65+AA65+AD65+AG65+AJ65
B66: MENU ESPECIAL | AM66: =C66+F66+I66+L66+O66+R66+U66+X66+AA66+AD66+AG66+AJ66
B67: REFRIGERIOS | AM67: =C67+F67+I67+L67+O67+R67+U67+X67+AA67+AD67+AG67+AJ67
AM68: =C68+F68+I68+L68+O68+R68+U68+X68+AA68+AD68+AG68+AJ68
AM69: =C69+F69+I69+L69+O69+R69+U69+X69+AA69+AD69+AG69+AJ69
AM70: =C70+F70+I70+L70+O70+R70+U70+X70+AA70+AD70+AG70+AJ70
AM71: =C71+F71+I71+L71+O71+R71+U71+X71+AA71+AD71+AG71+AJ71
B72: FLETES CP | C72: =SUM(C73:C74) | D72: =C72/C12 | E72: =C72/C13 | F72: =SUM(F73:F74) | G72: =F72/F12 | H72: =F72/F13 | I72: =SUM(I73:I74) | J72: =I72/I12 | K72: =I72/I13 | L72: =SUM(L73:L74) | M72: =L72/L12 | N72: =L72/L13 | O72: =SUM(O73:O74) | P72: =O72/O12 | Q72: =O72/O13 | R72: =SUM(R73:R74) | S72: =R72/R12 | T72: =R72/R13 | U72: =SUM(U73:U74) | V72: =U72/U12 | W72: =U72/U13 | X72: =SUM(X73:X74) | Y72: =X72/X12 | Z72: =X72/X13 | AA72: =SUM(AA73:AA74) | AB72: =AA72/AA12 | AC72: =AA72/AA13 | AD72: =SUM(AD73:AD74) | AE72: =AD72/AD12 | AF72: =AD72/AD13 | AG72: =SUM(AG73:AG74) | AH72: =AG72/AG12 | AI72: =AG72/AG13 | AJ72: =SUM(AJ73:AJ74) | AM72: =C72+F72+I72+L72+O72+R72+U72+X72+AA72+AD72+AG72+AJ72 | AN72: =AM72/AM12 | AO72: =AM72/AM13
B73: PREPARADOS PROPIOS | C73: ='GASTOS VEHICULOS'!C25*'%DIST'!B21 | F73: ='GASTOS VEHICULOS'!D25*'%DIST'!D21 | I73: ='GASTOS VEHICULOS'!E25*'%DIST'!F21 | L73: ='GASTOS VEHICULOS'!F25*'%DIST'!H21 | O73: ='GASTOS VEHICULOS'!G25*'%DIST'!J21 | R73: ='GASTOS VEHICULOS'!H25*'%DIST'!L21 | U73: ='GASTOS VEHICULOS'!I25*'%DIST'!N21 | X73: ='GASTOS VEHICULOS'!J25*'%DIST'!P21 | AA73: ='GASTOS VEHICULOS'!K25*'%DIST'!R21 | AD73: ='GASTOS VEHICULOS'!L25*'%DIST'!T21 | AG73: ='GASTOS VEHICULOS'!M25*'%DIST'!V21 | AJ73: ='GASTOS VEHICULOS'!N25*'%DIST'!X21 | AM73: =C73+F73+I73+L73+O73+R73+U73+X73+AA73+AD73+AG73+AJ73
A74: 73355001 | B74: PREPARADOS TERCEROS | C74: ='[14]Hoja 1'!$C$66 | F74: ='[10]Hoja 1'!$C$627+'[18]Hoja 1'!$C$193 | AM74: =C74+F74+I74+L74+O74+R74+U74+X74+AA74+AD74+AG74+AJ74 | AN74: =AM74/AM12 | AO74: =AM74/AM13
B75: Material de empaque | AM75: =C75+F75+I75+L75+O75+R75+U75+X75+AA75+AD75+AG75+AJ75
A76: 71101501 | B76: Menaje | F76: ='[10]Hoja 1'!$C$593 | AM76: =C76+F76+I76+L76+O76+R76+U76+X76+AA76+AD76+AG76+AJ76 | AO76: =AM76/$AM$13
A77: 73355501 | B77: Servicio de Gas | C77: ='[9]Hoja 1'!$C$692+'[14]Hoja 1'!$C$68 | F77: ='[10]Hoja 1'!$C$629+'[18]Hoja 1'!$C$195 | AM77: =C77+F77+I77+L77+O77+R77+U77+X77+AA77+AD77+AG77+AJ77 | AN77: =AM77/AM12 | AO77: =AM77/$AM$13
B78: MANO DE OBRA DIRECTA | C78: =SUM(C79:C81) | D78: =C78/C12 | E78: =C78/C13 | F78: =SUM(F79:F81) | G78: =F78/F12 | H78: =F78/F13 | I78: =SUM(I79:I81) | J78: =I78/I12 | K78: =I78/I13 | L78: =SUM(L79:L81) | M78: =L78/L12 | N78: =L78/L13 | O78: =SUM(O79:O81) | P78: =O78/O12 | Q78: =O78/O13 | R78: =SUM(R79:R81) | S78: =R78/R12 | T78: =R78/R13 | U78: =SUM(U79:U81) | V78: =U78/U12 | W78: =U78/U13 | X78: =SUM(X79:X81) | Y78: =X78/X12 | Z78: =X78/X13 | AA78: =SUM(AA79:AA81) | AB78: =AA78/AA12 | AC78: =AA78/AA13 | AD78: =SUM(AD79:AD81) | AE78: =AD78/AD12 | AF78: =AD78/AD13 | AG78: =SUM(AG79:AG81) | AI78: =AG78/AG13 | AJ78: =SUM(AJ79:AJ81) | AM78: =C78+F78+I78+L78+O78+R78+U78+X78+AA78+AD78+AG78+AJ78 | AN78: =AM78/AM12 | AO78: =AM78/AM13
A79: 7205 | B79: Manipuladoras | C79: ='[48]Hoja 1'!$D$9+'[22]Hoja 1'!$D$28+'[49]Hoja 1'!$D$9 | F79: ='[30]Hoja 1'!$D$19-23031718+'[31]Hoja 1'!$D$33+'[50]Hoja 1'!$D$9 | AM79: =C79+F79+I79+L79+O79+R79+U79+X79+AA79+AD79+AG79+AJ79 | AN79: =AM79/$AM$12 | AO79: =AM79/AM13
A80: 7205 | B80: Personal Supervisor - Coordinadores | C80: ='[21]Hoja 1'!$D$34+'[21]Hoja 1'!$D$38+'[22]Hoja 1'!$D$32 | F80: ='[29]Hoja 1'!$D$39+'[30]Hoja 1'!$D$18 | AM80: =C80+F80+I80+L80+O80+R80+U80+X80+AA80+AD80+AG80+AJ80 | AN80: =AM80/$AM$12 | AO80: =AM80/AM13
B81: Temporales MOD | AM81: =C81+F81+I81+L81+O81+R81+U81+X81+AA81+AD81+AG81+AJ81
B83: OTROS COSTOS Y GASTOS INDIRECTOS | C83: =+C84+C89+C92+C96+C99+C109+C114+C120+C123+C127 | E83: =C83/(C$13) | F83: =+F84+F89+F92+F96+F99+F109+F114+F120+F123+F127 | H83: =F83/(F$13) | I83: =+I84+I89+I92+I96+I99+I109+I114+I120+I123+I127 | K83: =I83/(I$13) | L83: =+L84+L89+L92+L96+L99+L109+L114+L120+L123+L127 | N83: =L83/(L$13) | O83: =+O84+O89+O92+O96+O99+O109+O114+O120+O123+O127 | Q83: =O83/(O$13) | R83: =+R84+R89+R92+R96+R99+R109+R114+R120+R123+R127 | T83: =R83/(R$13) | U83: =+U84+U89+U92+U96+U99+U109+U114+U120+U123+U127 | W83: =U83/(U$13) | X83: =+X84+X89+X92+X96+X99+X109+X114+X120+X123+X127 | Z83: =X83/(X$13) | AA83: =+AA84+AA89+AA92+AA96+AA99+AA109+AA114+AA120+AA123+AA127 | AC83: =AA83/(AA$13) | AD83: =+AD84+AD89+AD92+AD96+AD99+AD109+AD114+AD120+AD123+AD127 | AF83: =AD83/(AD$13) | AG83: =+AG84+AG89+AG92+AG96+AG99+AG109+AG114+AG120+AG123+AG127 | AI83: =AG83/(AG$13) | AJ83: =+AJ84+AJ89+AJ92+AJ96+AJ99+AJ109+AJ114+AJ120+AJ123+AJ127 | AM83: =C83+F83+I83+L83+O83+R83+U83+X83+AA83+AD83+AG83+AJ83 | AO83: =AM83/(AM$13)
B84: COSTOS DE PERSONAL | C84: =SUM(C85:C88) | E84: =C84/(C$13) | F84: =SUM(F85:F88) | H84: =F84/(F$13) | I84: =SUM(I85:I88) | K84: =I84/(I$13) | L84: =SUM(L85:L88) | N84: =L84/(L$13) | O84: =SUM(O85:O88) | Q84: =O84/(O$13) | R84: =SUM(R85:R88) | T84: =R84/(R$13) | U84: =SUM(U85:U88) | X84: =SUM(X85:X88) | AA84: =SUM(AA85:AA88) | AD84: =SUM(AD85:AD88) | AG84: =SUM(AG85:AG88) | AI84: =AG84/(AG$13) | AJ84: =SUM(AJ85:AJ88) | AM84: =C84+F84+I84+L84+O84+R84+U84+X84+AA84+AD84+AG84+AJ84 | AN84: =AM84/AM12 | AO84: =AM84/(AM$13)
B85: Costos Indirectos de Personal | C85: ='GASTOS OPERATIVOS'!C17*'%DIST'!C5 | F85: ='GASTOS OPERATIVOS'!D17*'%DIST'!E5 | AM85: =C85+F85+I85+L85+O85+R85+U85+X85+AA85+AD85+AG85+AJ85 | AO85: =AM85/(AM$13)
B86: Dotación y Suministros | F86: ='[18]Hoja 1'!$C$174 | AM86: =C86+F86+I86+L86+O86+R86+U86+X86+AA86+AD86+AG86+AJ86 | AO86: =AM86/(AM$13)
A87: 72058401 | B87: Gastos Medicos | F87: ='[10]Hoja 1'!$C$623 | AM87: =C87+F87+I87+L87+O87+R87+U87+X87+AA87+AD87+AG87+AJ87 | AO87: =AM87/(AM$13)
A88: 53954002 | B88: Incapacidades | C88: ='[14]Hoja 1'!$C$21+'[37]Hoja 1'!$C$64 | F88: ='[18]Hoja 1'!$C$148+'[11]Hoja 1'!$C$70 | AM88: =C88+F88+I88+L88+O88+R88+U88+X88+AA88+AD88+AG88+AJ88
B89: HONORARIOS | C89: =SUM(C90:C91) | E89: =C89/(C$13) | F89: =SUM(F90:F91) | I89: =SUM(I90:I91) | K89: =I89/(I$13) | L89: =SUM(L90:L91) | N89: =L89/(L$13) | O89: =SUM(O90:O91) | R89: =SUM(R90:R91) | U89: =SUM(U90:U91) | X89: =SUM(X90:X91) | AA89: =SUM(AA90:AA91) | AD89: =SUM(AD90:AD91) | AG89: =SUM(AG90:AG91) | AI89: =AG89/(AG$13) | AJ89: =SUM(AJ90:AJ91) | AM89: =C89+F89+I89+L89+O89+R89+U89+X89+AA89+AD89+AG89+AJ89 | AO89: =AM89/(AM$13)
B90: Asesoría Juridica | AM90: =C90+F90+I90+L90+O90+R90+U90+X90+AA90+AD90+AG90+AJ90
B91: Asesoría Tecnica | AM91: =C91+F91+I91+L91+O91+R91+U91+X91+AA91+AD91+AG91+AJ91
B92: ARRENDAMIENTOS | C92: =SUM(C93:C95) | E92: =C92/(C$13) | F92: =SUM(F93:F95) | I92: =SUM(I93:I95) | K92: =I92/(I$13) | L92: =SUM(L93:L95) | N92: =L92/(L$13) | O92: =SUM(O93:O95) | R92: =SUM(R93:R95) | U92: =SUM(U93:U95) | X92: =SUM(X93:X95) | AA92: =SUM(AA93:AA95) | AD92: =SUM(AD93:AD95) | AG92: =SUM(AG93:AG95) | AI92: =AG92/(AG$13) | AJ92: =SUM(AJ93:AJ95) | AM92: =C92+F92+I92+L92+O92+R92+U92+X92+AA92+AD92+AG92+AJ92 | AO92: =AM92/(AM$13)
B93: Construcciones y Edificaciones | AM93: =C93+F93+I93+L93+O93+R93+U93+X93+AA93+AD93+AG93+AJ93
B94: Maquinaria y Equipo | AM94: =C94+F94+I94+L94+O94+R94+U94+X94+AA94+AD94+AG94+AJ94
B95: Equipo de Oficina | AM95: =C95+F95+I95+L95+O95+R95+U95+X95+AA95+AD95+AG95+AJ95
B96: SEGUROS | C96: =SUM(C97:C98) | F96: =SUM(F97:F98) | I96: =SUM(I97:I98) | K96: =I96/(I$13) | L96: =SUM(L97:L98) | N96: =L96/(L$13) | O96: =SUM(O97:O98) | Q96: =O96/(O$13) | R96: =SUM(R97:R98) | U96: =SUM(U97:U98) | X96: =SUM(X97:X98) | AA96: =SUM(AA97:AA98) | AD96: =SUM(AD97:AD98) | AG96: =SUM(AG97:AG98) | AI96: =AG96/(AG$13) | AJ96: =SUM(AJ97:AJ98) | AM96: =C96+F96+I96+L96+O96+R96+U96+X96+AA96+AD96+AG96+AJ96 | AN96: =AM96/AM12 | AO96: =AM96/(AM$13)
B97: Cumplimiento | C97: ='[9]Hoja 1'!$C$687+'[14]Hoja 1'!$C$59 | AM97: =C97+F97+I97+L97+O97+R97+U97+X97+AA97+AD97+AG97+AJ97
B98: Responsabilidad Civil Y Extracontractual | C98: ='[14]Hoja 1'!$C$61 | AM98: =C98+F98+I98+L98+O98+R98+U98+X98+AA98+AD98+AG98+AJ98
B99: SERVICIOS | C99: =SUM(C100:C108) | E99: =C99/(C$13) | F99: =SUM(F100:F108) | I99: =SUM(I100:I108) | K99: =I99/(I$13) | L99: =SUM(L100:L108) | N99: =L99/(L$13) | O99: =SUM(O100:O108) | Q99: =O99/(O$13) | R99: =SUM(R100:R108) | U99: =SUM(U100:U108) | X99: =SUM(X100:X108) | AA99: =SUM(AA100:AA108) | AD99: =SUM(AD100:AD108) | AG99: =SUM(AG100:AG108) | AI99: =AG99/(AG$13) | AJ99: =SUM(AJ100:AJ108) | AM99: =C99+F99+I99+L99+O99+R99+U99+X99+AA99+AD99+AG99+AJ99 | AN99: =AM99/AM12 | AO99: =AM99/(AM$13)
B100: Aseo y Vigilancia | AM100: =C100+F100+I100+L100+O100+R100+U100+X100+AA100+AD100+AG100+AJ100
A101: 73351001 | B101: Temporales Serv | C101: ='[9]Hoja 1'!$C$690 | AM101: =C101+F101+I101+L101+O101+R101+U101+X101+AA101+AD101+AG101+AJ101
B102: Mensajeria | AM102: =C102+F102+I102+L102+O102+R102+U102+X102+AA102+AD102+AG102+AJ102
A103: 73351502 | B103: Laboratorio | F103: ='[18]Hoja 1'!C190 | AM103: =C103+F103+I103+L103+O103+R103+U103+X103+AA103+AD103+AG103+AJ103
A104: 73351503 | B104: Fumigacion | C104: ='[14]Hoja 1'!$C$64 | F104: ='[18]Hoja 1'!C191 | AM104: =C104+F104+I104+L104+O104+R104+U104+X104+AA104+AD104+AG104+AJ104
B105: Acueducto y Alcantarillado | AM105: =C105+F105+I105+L105+O105+R105+U105+X105+AA105+AD105+AG105+AJ105
B106: Energia | AM106: =C106+F106+I106+L106+O106+R106+U106+X106+AA106+AD106+AG106+AJ106
B107: Telefono e Internet | AM107: =C107+F107+I107+L107+O107+R107+U107+X107+AA107+AD107+AG107+AJ107
B108: Correo, porte y telegramas | AM108: =C108+F108+I108+L108+O108+R108+U108+X108+AA108+AD108+AG108+AJ108
...

Sheet BUGA
B2: CORPORACIÓN HACIA UN VALLE SOLIDARIO | C2: PYG BUGA 2026
B3: DIAS DE ATENCIÓN | C3: 10 | F3: 20 | I3: 19 | L3: 19 | O3: 19 | R3: 18 | U3: 9 | X3: 19 | AA3: 22 | AD3: 16 | AG3: 18 | AM3: =SUM(C3:AL3)
C4: ENE | D4: x racion | E4: % | F4: FEB | G4: x racion | H4: % | I4: MAR | J4: x racion | K4: % | L4: ABR | M4: x racion | N4: % | O4: MAY | P4: x racion | Q4: % | R4: JUN | S4: x racion | T4: % | U4: JUL | V4: x racion | W4: % | X4: AGO | Y4: x racion | Z4: % | AA4: SEP | AB4: x racion | AC4: % | AD4: OCT | AE4: x racion | AF4: % | AG4: NOV | AI4: % | AJ4: DIC | AK4: x racion | AL4: % | AM4: ACUMULADO | AN4: x racion | AO4: %
B5: COMPLEMENTO INDUSTRIALIZADO (Rac) | AM5: =C5+F5+I5+L5+O5+R5+U5+X5+AA5+AD5+AG5+AJ5 | AO5: =AM5/AM12
B6: COMPLEMENTO PREPARADO (Rac) | AM6: =C6+F6+I6+L6+O6+R6+U6+X6+AA6+AD6+AG6+AJ6 | AO6: =AM6/AM12
B7: ALMUERZO JORNADA UNICA (Rac) | AM7: =C7+F7+I7+L7+O7+R7+U7+X7+AA7+AD7+AG7+AJ7 | AO7: =AM7/AM12
B8: NOVEDADES (Rac) | AM8: =C8+F8+I8+L8+O8+R8+U8+X8+AA8+AD8+AG8+AJ8
AM9: =C9+F9+I9+L9+O9+R9+U9+X9+AA9+AD9+AG9+AJ9
AM10: =C10+F10+I10+L10+O10+R10+U10+X10+AA10+AD10+AG10+AJ10
AM11: =C11+F11+I11+L11+O11+R11+U11+X11+AA11+AD11+AG11+AJ11
B12: TOTAL RACIONES | C12: =SUM(C5:C11) | F12: =SUM(F5:F11) | I12: =SUM(I5:I11) | L12: =SUM(L5:L11) | O12: =SUM(O5:O11) | R12: =SUM(R5:R11) | U12: =SUM(U5:U11) | X12: =SUM(X5:X11) | AA12: =SUM(AA5:AA11) | AD12: =SUM(AD5:AD11) | AG12: =SUM(AG5:AG11) | AJ12: =SUM(AJ5:AJ11) | AM12: =C12+F12+I12+L12+O12+R12+U12+X12+AA12+AD12+AG12+AJ12
B13: INGRESOS BRUTOS | C13: =C14+C23 | F13: =F14+F23 | I13: =I14+I23 | L13: =L14+L23 | O13: =O14+O23 | R13: =R14+R23 | U13: =U14+U23 | X13: =X14+X23 | AA13: =AA14+AA23 | AD13: =AD14+AD23 | AG13: =AG14+AG23 | AJ13: =AJ14+AJ23 | AM13: =C13+F13+I13+L13+O13+R13+U13+X13+AA13+AD13+AG13+AJ13
B14: OPERACIONALES | C14: =C15 | F14: =F15 | I14: =I15 | L14: =L15 | O14: =O15 | R14: =R15 | U14: =U15 | X14: =X15 | AA14: =AA15 | AD14: =AD15 | AG14: =AG15 | AJ14: =AJ15 | AM14: =C14+F14+I14+L14+O14+R14+U14+X14+AA14+AD14+AG14+AJ14
B15: INDUSTRIAS MANUFACTURERAS | C15: =SUM(C16:C22) | F15: =SUM(F16:F22) | I15: =SUM(I16:I22) | L15: =SUM(L16:L22) | O15: =SUM(O16:O22) | R15: =SUM(R16:R22) | U15: =SUM(U16:U22) | X15: =SUM(X16:X22) | AA15: =SUM(AA16:AA22) | AD15: =SUM(AD16:AD22) | AG15: =SUM(AG16:AG22) | AJ15: =SUM(AJ16:AJ22) | AM15: =C15+F15+I15+L15+O15+R15+U15+X15+AA15+AD15+AG15+AJ15 | AO15: =AM15/AM15
B16: COMPLEMENTO INDUSTRIALIZADO (Fac) | D16: =C16/C5 | G16: =F16/F5 | AM16: =C16+F16+I16+L16+O16+R16+U16+X16+AA16+AD16+AG16+AJ16
B17: COMPLEMENTO PREPARADO (Fac) | D17: =C17/C6 | G17: =F17/F6 | AM17: =C17+F17+I17+L17+O17+R17+U17+X17+AA17+AD17+AG17+AJ17 | AN17: =AM17/AM6 | AO17: =AM17/AM$13
B18: ALMUERZO JORNADA UNICA (Fac) | D18: =C18/C7 | G18: =F18/F7 | AM18: =C18+F18+I18+L18+O18+R18+U18+X18+AA18+AD18+AG18+AJ18 | AN18: =AM18/AM7 | AO18: =AM18/AM$13
AM19: =C19+F19+I19+L19+O19+R19+U19+X19+AA19+AD19+AG19+AJ19
B20: NOVEDADES (Fac) | AM20: =C20+F20+I20+L20+O20+R20+U20+X20+AA20+AD20+AG20+AJ20
AM21: =C21+F21+I21+L21+O21+R21+U21+X21+AA21+AD21+AG21+AJ21
AM22: =C22+F22+I22+L22+O22+R22+U22+X22+AA22+AD22+AG22+AJ22
B23: NO OPERACIONALES | C23: =C24 | F23: =F24 | I23: =I24 | L23: =L24 | O23: =O24 | R23: =R24 | U23: =U24 | X23: =X24 | AA23: =AA24 | AM23: =C23+F23+I23+L23+O23+R23+U23+X23+AA23+AD23+AG23+AJ23
B24: FINANCIEROS | C24: =SUM(C25:C27) | F24: =SUM(F25:F27) | I24: =SUM(I25:I27) | L24: =SUM(L25:L27) | O24: =SUM(O25:O27) | R24: =SUM(R25:R27) | U24: =SUM(U25:U27) | X24: =SUM(X25:X27) | AA24: =SUM(AA25:AA27) | AD24: =SUM(AD25:AD27) | AG24: =SUM(AG25:AG27) | AJ24: =SUM(AJ25:AJ27) | AM24: =C24+F24+I24+L24+O24+R24+U24+X24+AA24+AD24+AG24+AJ24
B25: Intereses | AM25: =C25+F25+I25+L25+O25+R25+U25+X25+AA25+AD25+AG25+AJ25
B26: Descuentos Comerciales | AM26: =C26+F26+I26+L26+O26+R26+U26+X26+AA26+AD26+AG26+AJ26
B27: otros Fin | AM27: =C27+F27+I27+L27+O27+R27+U27+X27+AA27+AD27+AG27+AJ27
B28: DESCUENTOS - GASTO OPERACIONAL | C28: =+C29 | F28: =+F29 | I28: =+I29 | L28: =+L29 | O28: =+O29 | R28: =+R29 | U28: =+U29 | X28: =+X29 | AA28: =+AA29 | AD28: =+AD29 | AG28: =+AG29 | AJ28: =+AJ29 | AM28: =C28+F28+I28+L28+O28+R28+U28+X28+AA28+AD28+AG28+AJ28
B29: OTROS | C29: =SUM(C30:C41) | E29: =C29/C13 | F29: =SUM(F30:F37) | H29: =F29/F13 | I29: =SUM(I30:I37) | K29: =I29/I13 | L29: =SUM(L30:L37) | N29: =L29/L13 | O29: =SUM(O30:O37) | R29: =SUM(R30:R37) | T29: =R29/R13 | U29: =SUM(U30:U37) | W29: =U29/U13 | X29: =SUM(X30:X37) | Z29: =X29/X13 | AA29: =SUM(AA30:AA37) | AC29: =AA29/AA13 | AD29: =SUM(AD30:AD37) | AF29: =AD29/AD13 | AG29: =SUM(AG30:AG39) | AI29: =AG29/AG13 | AJ29: =SUM(AJ30:AJ38) | AM29: =C29+F29+I29+L29+O29+R29+U29+X29+AA29+AD29+AG29+AJ29 | AO29: =AM29/AM13
B30: 1% Estampilla Prohospital | C30: =C13*1% | F30: =F13*1% | I30: =I13*1% | L30: =L13*1% | O30: =O13*1% | R30: =R13*1% | U30: =U13*1% | X30: =X13*1% | AA30: =AA13*1% | AD30: =AD13*1% | AG30: =AG13*1% | AJ30: =AJ13*1% | AM30: =C30+F30+I30+L30+O30+R30+U30+X30+AA30+AD30+AG30+AJ30
B31: 2,5% Estampilla Pro Deporte | C31: =C$13*2.5% | F31: =F$13*2.5% | I31: =I$13*2.5% | L31: =L$13*2.5% | O31: =O$13*2.5% | R31: =R$13*2.5% | U31: =U$13*2.5% | X31: =X$13*2.5% | AA31: =AA$13*2.5% | AD31: =AD$13*2.5% | AG31: =AG$13*2.5% | AJ31: =AJ$13*2.5% | AM31: =C31+F31+I31+L31+O31+R31+U31+X31+AA31+AD31+AG31+AJ31
B32: 1% Estampilla Pro Univalle | C32: =C$13*1% | F32: =F$13*1% | I32: =I$13*1% | L32: =L$13*1% | O32: =O$13*1% | R32: =R$13*1% | U32: =U$13*1% | X32: =X$13*1% | AA32: =AA$13*1% | AD32: =AD$13*1% | AG32: =AG$13*1% | AJ32: =AJ$13*1% | AM32: =C32+F32+I32+L32+O32+R32+U32+X32+AA32+AD32+AG32+AJ32
B33: 3% Estampilla Adulto Mayor | C33: =C13*3% | F33: =F13*3% | I33: =I13*3% | L33: =L13*3% | O33: =O13*3% | R33: =R13*3% | U33: =U13*3% | X33: =X13*3% | AA33: =AA13*3% | AD33: =AD13*3% | AG33: =AG13*3% | AJ33: =AJ13*3% | AM33: =C33+F33+I33+L33+O33+R33+U33+X33+AA33+AD33+AG33+AJ33
B34: 0,5% Estampilla Universidad del Pacifico | C34: =C$13*0.5% | F34: =F$13*0.5% | I34: =I$13*0.5% | L34: =L$13*0.5% | O34: =O$13*0.5% | R34: =R$13*0.5% | U34: =U$13*0.5% | X34: =X$13*0.5% | AA34: =AA$13*0.5% | AD34: =AD$13*0.5% | AG34: =AG$13*0.5% | AJ34: =AJ$13*0.5% | AM34: =C34+F34+I34+L34+O34+R34+U34+X34+AA34+AD34+AG34+AJ34
B35: 0,66% Rete Ica | C35: =C$13*0.66% | F35: =F$13*0.66% | I35: =I$13*0.66% | L35: =L$13*0.66% | O35: =O$13*0.66% | R35: =R$13*0.66% | U35: =U$13*0.66% | X35: =X$13*0.66% | AA35: =AA$13*0.66% | AD35: =AD$13*0.66% | AG35: =AG$13*0.66% | AJ35: =AJ$13*0.66% | AM35: =C35+F35+I35+L35+O35+R35+U35+X35+AA35+AD35+AG35+AJ35
B36: Retefuente | C36: =(C$13*1%)*3.5% | F36: =(F$13*1%)*3.5% | I36: =(I$13*1%)*3.5% | L36: =(L$13*1%)*3.5% | O36: =(O$13*1%)*3.5% | R36: =(R$13*1%)*3.5% | U36: =(U$13*1%)*3.5% | X36: =(X$13*1%)*3.5% | AA36: =(AA$13*1%)*3.5% | AD36: =(AD$13*1%)*3.5% | AG36: =(AG$13*1%)*3.5% | AJ36: =(AJ$13*1%)*3.5% | AM36: =C36+F36+I36+L36+O36+R36+U36+X36+AA36+AD36+AG36+AJ36
B37: 2% Juzgado de Familia | C37: =C$13*2% | F37: =F$13*2% | I37: =I$13*2% | L37: =L$13*2% | O37: =O$13*2% | R37: =R$13*2% | U37: =U$13*2% | X37: =X$13*2% | AA37: =AA$13*2% | AD37: =AD$13*2% | AG37: =AG$13*2% | AJ37: =AJ$13*2% | AM37: =C37+F37+I37+L37+O37+R37+U37+X37+AA37+AD37+AG37+AJ37
B38: 0,5% Impuesto de Timbre | AM38: =C38+F38+I38+L38+O38+R38+U38+X38+AA38+AD38+AG38+AJ38
B42: TOTAL INGRESOS NETOS | C42: =+C14+C23-C28 | F42: =+F14+F23-F28 | I42: =+I14+I23-I28 | L42: =+L14+L23-L28 | O42: =+O14+O23-O28 | R42: =+R14+R23-R28 | U42: =+U14+U23-U28 | X42: =+X14+X23-X28 | AA42: =+AA14+AA23-AA28 | AD42: =+AD14+AD23-AD28 | AG42: =+AG14+AG23-AG28 | AJ42: =+AJ14+AJ23-AJ28 | AM42: =C42+F42+I42+L42+O42+R42+U42+X42+AA42+AD42+AG42+AJ42
E43: =(C46+C61)/C13 | H43: =(F46+F61)/F13 | K43: =(I46+I61)/I13 | N43: =(L46+L61)/L13 | Q43: =(O46+O61)/O13 | T43: =(R46+R61)/R13 | W43: =(U46+U61)/U13 | Z43: =(X46+X61)/X13 | AC43: =(AA46+AA61)/AA13 | AF43: =(AD46+AD61)/AD13 | AI43: =(AG46+AG61)/AG13 | AO43: =(AM46+AM61)/AM13
B44: COSTOS DE PRODUCCION | C44: =+C45+C60+C78 | E44: =C44/C$13 | F44: =+F45+F60+F78 | H44: =F44/F$13 | I44: =+I45+I60+I78 | K44: =I44/I$13 | L44: =+L45+L60+L78 | N44: =L44/L$13 | O44: =+O45+O60+O78 | R44: =+R45+R60+R78 | T44: =R44/R$13 | U44: =+U45+U60+U78 | W44: =U44/U$13 | X44: =+X45+X60+X78 | Z44: =X44/X$13 | AA44: =+AA45+AA60+AA78 | AC44: =AA44/AA$13 | AD44: =+AD45+AD60+AD78 | AF44: =AD44/AD$13 | AG44: =+AG45+AG60+AG78 | AI44: =AG44/AG$13 | AJ44: =+AJ45+AJ60+AJ78 | AM44: =C44+F44+I44+L44+O44+R44+U44+X44+AA44+AD44+AG44+AJ44 | AO44: =AM44/AM$13
B45: COSTOS INDUSTRIALIZADOS | C45: =+C46+C58+C59 | F45: =+F46+F57 | H45: =F45/F13 | I45: =+I46+I57 | K45: =I45/I13 | L45: =+L46+L57 | N45: =L45/L13 | O45: =+O46+O57 | R45: =+R46+R57 | T45: =R45/R13 | U45: =+U46+U57 | W45: =U45/U13 | X45: =+X46+X57 | Z45: =X45/X13 | AA45: =+AA46+AA57 | AC45: =AA45/AA13 | AD45: =+AD46+AD57 | AF45: =AD45/AD13 | AG45: =+AG46+AG57 | AI45: =AG45/AG13 | AJ45: =+AJ46+AJ57 | AM45: =C45+F45+I45+L45+O45+R45+U45+X45+AA45+AD45+AG45+AJ45 | AO45: =AM45/AM$13
B46: INSUMOS CI | C46: =SUM(C47:C56)+C57 | F46: =SUM(F47:F56) | I46: =SUM(I47:I56) | L46: =SUM(L47:L56) | O46: =SUM(O47:O56) | R46: =SUM(R47:R56) | U46: =SUM(U47:U56) | X46: =SUM(X47:X56) | AA46: =SUM(AA47:AA56) | AC46: =AA46/AA13 | AD46: =SUM(AD47:AD56) | AF46: =AD46/AD13 | AG46: =SUM(AG47:AG56) | AI46: =AG46/AG13 | AJ46: =SUM(AJ47:AJ56) | AM46: =C46+F46+I46+L46+O46+R46+U46+X46+AA46+AD46+AG46+AJ46 | AO46: =AM46/AM13
B47: COMPLEMENTO INDUSTRIALIZADO (Ins) | C47: ='[44]Hoja 1'!$D$35 | F47: ='[45]Hoja 1'!$D$40 | AM47: =C47+F47+I47+L47+O47+R47+U47+X47+AA47+AD47+AG47+AJ47
AM48: =C48+F48+I48+L48+O48+R48+U48+X48+AA48+AD48+AG48+AJ48
B49: NOVEDADES | AM49: =C49+F49+I49+L49+O49+R49+U49+X49+AA49+AD49+AG49+AJ49
AM50: =C50+F50+I50+L50+O50+R50+U50+X50+AA50+AD50+AG50+AJ50
AM51: =C51+F51+I51+L51+O51+R51+U51+X51+AA51+AD51+AG51+AJ51
B52: REFRIGERIOS | AM52: =C52+F52+I52+L52+O52+R52+U52+X52+AA52+AD52+AG52+AJ52
B53: PAQUETES MANIPULADORAS | AM53: =C53+F53+I53+L53+O53+R53+U53+X53+AA53+AD53+AG53+AJ53
AM54: =C54+F54+I54+L54+O54+R54+U54+X54+AA54+AD54+AG54+AJ54
AM55: =C55+F55+I55+L55+O55+R55+U55+X55+AA55+AD55+AG55+AJ55
B57: FLETES CI | F57: =SUM(F58:F59) | G57: =F57/F12 | H57: =F57/F13 | I57: =SUM(I58:I59) | J57: =I57/I12 | K57: =I57/I13 | L57: =SUM(L58:L59) | M57: =L57/L12 | N57: =L57/L13 | O57: =SUM(O58:O59) | P57: =O57/O12 | Q57: =O57/O13 | R57: =SUM(R58:R59) | S57: =R57/R12 | T57: =R57/R13 | U57: =SUM(U58:U59) | V57: =U57/U12 | W57: =U57/U13 | X57: =SUM(X58:X59) | Y57: =X57/X12 | Z57: =X57/X13 | AA57: =SUM(AA58:AA59) | AB57: =AA57/AA12 | AC57: =AA57/AA13 | AD57: =SUM(AD58:AD59) | AE57: =AD57/AD12 | AF57: =AD57/AD13 | AG57: =SUM(AG58:AG59) | AH57: =AG57/AG12 | AI57: =AG57/AG13 | AJ57: =SUM(AJ58:AJ59) | AM57: =C57+F57+I57+L57+O57+R57+U57+X57+AA57+AD57+AG57+AJ57 | AN57: =AM57/AM12 | AO57: =AM57/AM13
B58: INDUSTRIALIZADOS PROPIOS | AM58: =C58+F58+I58+L58+O58+R58+U58+X58+AA58+AD58+AG58+AJ58
B59: INDUSTRIALIZADOS TERCEROS | G59: =F59/F12 | H59: =F59/F13 | J59: =I59/I12 | K59: =I59/I13 | M59: =L59/L12 | N59: =L59/L13 | P59: =O59/O12 | Q59: =O59/O13 | S59: =R59/R12 | T59: =R59/R13 | V59: =U59/U12 | W59: =U59/U13 | Y59: =X59/X12 | Z59: =X59/X13 | AB59: =AA59/AA12 | AC59: =AA59/AA13 | AE59: =AD59/AD12 | AF59: =AD59/AD13 | AH59: =AG59/AG12 | AI59: =AG59/AG13 | AM59: =C59+F59+I59+L59+O59+R59+U59+X59+AA59+AD59+AG59+AJ59
B60: COSTOS PREPARADOS | C60: =+C61+C72+C75+C76+C77 | F60: =+F61+F72+F75+F76+F77 | H60: =F60/F13 | I60: =+I61+I72+I75+I76+I77 | K60: =I60/I13 | L60: =+L61+L72+L75+L76+L77 | N60: =L60/L13 | O60: =+O61+O72+O75+O76+O77 | Q60: =O60/O13 | R60: =+R61+R72+R75+R76+R77 | T60: =R60/R13 | U60: =+U61+U72+U75+U76+U77 | W60: =U60/U13 | X60: =+X61+X72+X75+X76+X77 | AA60: =+AA61+AA72+AA75+AA76+AA77 | AC60: =AA60/AA13 | AD60: =+AD61+AD72+AD75+AD76+AD77 | AF60: =AD60/AD13 | AG60: =+AG61+AG72+AG75+AG76+AG77 | AJ60: =+AJ61+AJ72+AJ75+AJ76+AJ77 | AM60: =C60+F60+I60+L60+O60+R60+U60+X60+AA60+AD60+AG60+AJ60
B61: INSUMOS CP | C61: =SUM(C62:C71) | F61: =SUM(F62:F71) | I61: =SUM(I62:I71) | L61: =SUM(L62:L71) | O61: =SUM(O62:O71) | R61: =SUM(R62:R71) | U61: =SUM(U62:U71) | X61: =SUM(X62:X71) | AA61: =SUM(AA62:AA71) | AC61: =AA61/AA13 | AD61: =SUM(AD62:AD71) | AG61: =SUM(AG62:AG71) | AJ61: =SUM(AJ62:AJ71) | AM61: =C61+F61+I61+L61+O61+R61+U61+X61+AA61+AD61+AG61+AJ61
B62: COMPLEMENTO PREPARADO (Ins) | C62: ='[44]Hoja 1'!$D$26+'[44]Hoja 1'!$D$34 | D62: =C62/C6 | E62: =C62/C17 | F62: ='[45]Hoja 1'!$D$39 | G62: =F62/F6 | H62: =F62/F17 | J62: =I62/I6 | K62: =I62/I17 | M62: =L62/L6 | N62: =L62/L17 | P62: =O62/O6 | Q62: =O62/O17 | S62: =R62/R6 | T62: =R62/R17 | V62: =U62/U6 | W62: =U62/U17 | Y62: =X62/X6 | Z62: =X62/X17 | AB62: =AA62/AA6 | AC62: =AA62/AA17 | AE62: =AD62/AD6 | AF62: =AD62/AD17 | AH62: =AG62/AG6 | AI62: =AG62/AG17 | AM62: =C62+F62+I62+L62+O62+R62+U62+X62+AA62+AD62+AG62+AJ62 | AN62: =AM62/AM6 | AO62: =AM62/AM17
B63: ALMUERZO JORNADA UNICA (Ins) | C63: ='[44]Hoja 1'!$D$30+'[44]Hoja 1'!$D$36 | D63: =C63/C7 | E63: =C63/C18 | F63: ='[45]Hoja 1'!$D$41 | G63: =F63/F7 | H63: =F63/F18 | J63: =I63/I7 | K63: =I63/I18 | M63: =L63/L7 | N63: =L63/L18 | P63: =O63/O7 | Q63: =O63/O18 | S63: =R63/R7 | T63: =R63/R18 | V63: =U63/U7 | W63: =U63/U18 | Y63: =X63/X7 | Z63: =X63/X18 | AB63: =AA63/AA7 | AC63: =AA63/AA18 | AE63: =AD63/AD7 | AF63: =AD63/AD18 | AH63: =AG63/AG7 | AI63: =AG63/AG18 | AM63: =C63+F63+I63+L63+O63+R63+U63+X63+AA63+AD63+AG63+AJ63 | AN63: =AM63/AM7 | AO63: =AM63/AM18
AM64: =C64+F64+I64+L64+O64+R64+U64+X64+AA64+AD64+AG64+AJ64
AM65: =C65+F65+I65+L65+O65+R65+U65+X65+AA65+AD65+AG65+AJ65
B66: MENU ESPECIAL | AM66: =C66+F66+I66+L66+O66+R66+U66+X66+AA66+AD66+AG66+AJ66
AM71: =C71+F71+I71+L71+O71+R71+U71+X71+AA71+AD71+AG71+AJ71
B72: FLETES CP | C72: =SUM(C73:C74) | D72: =C72/C12 | E72: =C72/C13 | F72: =SUM(F73:F74) | G72: =F72/F12 | H72: =F72/F13 | I72: =SUM(I73:I74) | J72: =I72/I12 | K72: =I72/I13 | L72: =SUM(L73:L74) | M72: =L72/L12 | N72: =L72/L13 | O72: =SUM(O73:O74) | P72: =O72/O12 | Q72: =O72/O13 | R72: =SUM(R73:R74) | S72: =R72/R12 | T72: =R72/R13 | U72: =SUM(U73:U74) | V72: =U72/U12 | W72: =U72/U13 | X72: =SUM(X73:X74) | Y72: =X72/X12 | Z72: =X72/X13 | AA72: =SUM(AA73:AA74) | AB72: =AA72/AA12 | AC72: =AA72/AA13 | AD72: =SUM(AD73:AD74) | AE72: =AD72/AD12 | AF72: =AD72/AD13 | AG72: =SUM(AG73:AG74) | AH72: =AG72/AG12 | AI72: =AG72/AG13 | AJ72: =SUM(AJ73:AJ74) | AM72: =C72+F72+I72+L72+O72+R72+U72+X72+AA72+AD72+AG72+AJ72 | AN72: =AM72/AM12 | AO72: =AM72/AM13
B73: PREPARADOS PROPIOS | C73: ='GASTOS VEHICULOS'!C25*'%DIST'!B23 | F73: ='GASTOS VEHICULOS'!D25*'%DIST'!D23 | I73: ='GASTOS VEHICULOS'!E25*'%DIST'!F23 | L73: ='GASTOS VEHICULOS'!F25*'%DIST'!H23 | O73: ='GASTOS VEHICULOS'!G25*'%DIST'!J23 | R73: ='GASTOS VEHICULOS'!H25*'%DIST'!L23 | U73: ='GASTOS VEHICULOS'!I25*'%DIST'!N23 | X73: ='GASTOS VEHICULOS'!J25*'%DIST'!P23 | AA73: ='GASTOS VEHICULOS'!K25*'%DIST'!R23 | AD73: ='GASTOS VEHICULOS'!L25*'%DIST'!T23 | AG73: ='GASTOS VEHICULOS'!M25*'%DIST'!V23 | AM73: =C73+F73+I73+L73+O73+R73+U73+X73+AA73+AD73+AG73+AJ73
A74: 73355001 | B74: PREPARADOS TERCEROS | C74: ='[15]Hoja 1'!$C$105 | F74: ='[10]Hoja 1'!$C$471+'[19]Hoja 1'!$C$218 | AM74: =C74+F74+I74+L74+O74+R74+U74+X74+AA74+AD74+AG74+AJ74
B75: Material de empaque | AM75: =C75+F75+I75+L75+O75+R75+U75+X75+AA75+AD75+AG75+AJ75
A76: 71101501 | B76: Menaje | C76: ='[9]Hoja 1'!$C$453+'[15]Hoja 1'!$C$54 | F76: ='[10]Hoja 1'!$C$428 | AM76: =C76+F76+I76+L76+O76+R76+U76+X76+AA76+AD76+AG76+AJ76 | AO76: =AM76/$AM$13
A77: 73355501 | B77: Servicio de Gas | C77: ='[9]Hoja 1'!$C$498+'[15]Hoja 1'!$C$107 | F77: ='[19]Hoja 1'!$C$220 | AM77: =C77+F77+I77+L77+O77+R77+U77+X77+AA77+AD77+AG77+AJ77 | AN77: =AM77/(AM6+AM7) | AO77: =AM77/$AM$13
B78: MANO DE OBRA DIRECTA | C78: =SUM(C79:C81) | D78: =C78/$C$12 | E78: =C78/$C$13 | F78: =SUM(F79:F81) | G78: =F78/F$12 | H78: =F78/F13 | I78: =SUM(I79:I81) | J78: =I78/I$12 | K78: =I78/(I$13) | L78: =SUM(L79:L81) | M78: =L78/L$12 | N78: =L78/(L$13) | O78: =SUM(O79:O81) | P78: =O78/O$12 | Q78: =O78/(O$13) | R78: =SUM(R79:R81) | S78: =R78/R$12 | T78: =R78/(R$13) | U78: =SUM(U79:U81) | V78: =U78/U$12 | W78: =U78/(U$13) | X78: =SUM(X79:X81) | Y78: =X78/X$12 | Z78: =X78/(X$13) | AA78: =SUM(AA79:AA81) | AB78: =AA78/AA$12 | AC78: =AA78/(AA$13) | AD78: =SUM(AD79:AD81) | AE78: =AD78/AD$12 | AF78: =AD78/(AD$13) | AG78: =SUM(AG79:AG81) | AI78: =AG78/(AG$13) | AJ78: =SUM(AJ79:AJ81) | AM78: =C78+F78+I78+L78+O78+R78+U78+X78+AA78+AD78+AG78+AJ78 | AN78: =AM78/AM$12 | AO78: =AM78/(AM$13)
B79: Manipuladoras | C79: ='[53]Hoja 1'!$I$12+'[24]Hoja 1'!$I$26 | F79: ='[33]Hoja 1'!$I$20-16825149+'[34]Hoja 1'!$D$21+'[54]Hoja 1'!$C$23 | AM79: =C79+F79+I79+L79+O79+R79+U79+X79+AA79+AD79+AG79+AJ79 | AN79: =AM79/AM12 | AO79: =AM79/(AM$13) | AP79: 267.36689
B80: Personal Supervisor - Coordinadores | C80: ='[21]Hoja 1'!$D$21+'[53]Hoja 1'!$I$11+'[24]Hoja 1'!$I$24 | F80: ='[29]Hoja 1'!$D$22+'[33]Hoja 1'!$I$19 | AM80: =C80+F80+I80+L80+O80+R80+U80+X80+AA80+AD80+AG80+AJ80 | AN80: =AM80/AM12 | AO80: =AM80/(AM$13)
A81: 72959501 | B81: Cuota de Apoyo y Sostenimiento (SENA) | C81: ='[9]Hoja 1'!$C$436+'[1]Hoja 1'!$D$27 | F81: ='[10]Hoja 1'!$C$403+'[10]Hoja 1'!$C$410 | AM81: =C81+F81+I81+L81+O81+R81+U81+X81+AA81+AD81+AG81+AJ81
B83: OTROS COSTOS Y GASTOS INDIRECTOS | C83: =+C84+C89+C92+C96+C99+C109+C114+C120+C123+C127 | E83: =C83/(C$13) | F83: =+F84+F89+F92+F96+F99+F109+F114+F120+F123+F127 | H83: =F83/(F$13) | I83: =+I84+I89+I92+I96+I99+I109+I114+I120+I123+I127 | K83: =I83/(I$13) | L83: =+L84+L89+L92+L96+L99+L109+L114+L120+L123+L127 | N83: =L83/(L$13) | O83: =+O84+O89+O92+O96+O99+O109+O114+O120+O123+O127 | Q83: =O83/(O$13) | R83: =+R84+R89+R92+R96+R99+R109+R114+R120+R123+R127 | T83: =R83/(R$13) | U83: =+U84+U89+U92+U96+U99+U109+U114+U120+U123+U127 | W83: =U83/(U$13) | X83: =+X84+X89+X92+X96+X99+X109+X114+X120+X123+X127 | Z83: =X83/(X$13) | AA83: =+AA84+AA89+AA92+AA96+AA99+AA109+AA114+AA120+AA123+AA127 | AC83: =AA83/(AA$13) | AD83: =+AD84+AD89+AD92+AD96+AD99+AD109+AD114+AD120+AD123+AD127 | AF83: =AD83/(AD$13) | AG83: =+AG84+AG89+AG92+AG96+AG99+AG109+AG114+AG120+AG123+AG127 | AI83: =AG83/(AG$13) | AJ83: =+AJ84+AJ89+AJ92+AJ96+AJ99+AJ109+AJ114+AJ120+AJ123+AJ127 | AM83: =C83+F83+I83+L83+O83+R83+U83+X83+AA83+AD83+AG83+AJ83 | AO83: =AM83/(AM$13)
B84: COSTOS DE PERSONAL | C84: =SUM(C85:C88) | E84: =C84/(C$13) | F84: =SUM(F85:F88) | H84: =F84/(F$13) | I84: =SUM(I85:I88) | K84: =I84/(I$13) | L84: =SUM(L85:L88) | N84: =L84/(L$13) | O84: =SUM(O85:O88) | Q84: =O84/(O$13) | R84: =SUM(R85:R88) | T84: =R84/(R$13) | U84: =SUM(U85:U88) | W84: =U84/(U$13) | X84: =SUM(X85:X88) | Z84: =X84/(X$13) | AA84: =SUM(AA85:AA88) | AC84: =AA84/(AA$13) | AD84: =SUM(AD85:AD88) | AF84: =AD84/(AD$13) | AG84: =SUM(AG85:AG88) | AJ84: =SUM(AJ85:AJ88) | AM84: =C84+F84+I84+L84+O84+R84+U84+X84+AA84+AD84+AG84+AJ84 | AO84: =AM84/(AM$13)
B85: Costos Indirectos de Personal | C85: ='[21]Hoja 1'!$D$20+'[55]Hoja 1'!$D$9+'[53]Hoja 1'!$I$9+'[3]Hoja 1'!$D$15+'[24]Hoja 1'!$D$16+'[24]Hoja 1'!$I$22 | F85: ='[29]Hoja 1'!$D$21+'[6]Hoja 1'!$D$18-228123+'[33]Hoja 1'!$I$17-1342558 | AM85: =C85+F85+I85+L85+O85+R85+U85+X85+AA85+AD85+AG85+AJ85 | AO85: =AM85/(AM$13)
A86: 51055101 | B86: Dotación y Suministros | F86: ='[19]Hoja 1'!$C$151+'[19]Hoja 1'!$C$193 | AM86: =C86+F86+I86+L86+O86+R86+U86+X86+AA86+AD86+AG86+AJ86 | AO86: =AM86/AM13
B87: Gastos Medicos | C87: ='[9]Hoja 1'!$C$485+'[15]Hoja 1'!$C$88 | F87: ='[10]Hoja 1'!$C$458 | AM87: =C87+F87+I87+L87+O87+R87+U87+X87+AA87+AD87+AG87+AJ87 | AO87: =AM87/(AM$13)
A88: 53954002 | B88: Incapacidades | F88: ='[19]Hoja 1'!$C$167 | AM88: =C88+F88+I88+L88+O88+R88+U88+X88+AA88+AD88+AG88+AJ88
B89: HONORARIOS | C89: =SUM(C90:C91) | E89: =C89/(C$13) | F89: =SUM(F90:F91) | H89: =F89/(F$13) | I89: =SUM(I90:I91) | K89: =I89/(I$13) | L89: =SUM(L90:L91) | N89: =L89/(L$13) | O89: =SUM(O90:O91) | Q89: =O89/(O$13) | R89: =SUM(R90:R91) | T89: =R89/(R$13) | U89: =SUM(U90:U91) | W89: =U89/(U$13) | X89: =SUM(X90:X91) | Z89: =X89/(X$13) | AA89: =SUM(AA90:AA91) | AC89: =AA89/(AA$13) | AD89: =SUM(AD90:AD91) | AF89: =AD89/(AD$13) | AG89: =SUM(AG90:AG91) | AJ89: =SUM(AJ90:AJ91) | AM89: =C89+F89+I89+L89+O89+R89+U89+X89+AA89+AD89+AG89+AJ89 | AO89: =AM89/(AM$13)
B90: Asesoría Juridica | AM90: =C90+F90+I90+L90+O90+R90+U90+X90+AA90+AD90+AG90+AJ90
B91: Asesoría Tecnica/Capacitacion | AM91: =C91+F91+I91+L91+O91+R91+U91+X91+AA91+AD91+AG91+AJ91
B92: ARRENDAMIENTOS | C92: =SUM(C93:C95) | E92: =C92/(C$13) | F92: =SUM(F93:F95) | H92: =F92/(F$13) | I92: =SUM(I93:I95) | K92: =I92/(I$13) | L92: =SUM(L93:L95) | N92: =L92/(L$13) | O92: =SUM(O93:O95) | Q92: =O92/(O$13) | R92: =SUM(R93:R95) | T92: =R92/(R$13) | U92: =SUM(U93:U95) | W92: =U92/(U$13) | X92: =SUM(X93:X95) | Z92: =X92/(X$13) | AA92: =SUM(AA93:AA95) | AC92: =AA92/(AA$13) | AD92: =SUM(AD93:AD95) | AF92: =AD92/(AD$13) | AG92: =SUM(AG93:AG95) | AJ92: =SUM(AJ93:AJ95) | AM92: =C92+F92+I92+L92+O92+R92+U92+X92+AA92+AD92+AG92+AJ92 | AO92: =AM92/(AM$13)
B93: Construcciones y Edificaciones | C93: ='[9]Hoja 1'!$C$489 | F93: ='[10]Hoja 1'!$C$462 | AM93: =C93+F93+I93+L93+O93+R93+U93+X93+AA93+AD93+AG93+AJ93
B94: Maquinaria y Equipo | AM94: =C94+F94+I94+L94+O94+R94+U94+X94+AA94+AD94+AG94+AJ94
B95: Equipo de Oficina | AM95: =C95+F95+I95+L95+O95+R95+U95+X95+AA95+AD95+AG95+AJ95
B96: SEGUROS | C96: =SUM(C97:C98) | E96: =C96/(C$13) | F96: =SUM(F97:F98) | H96: =F96/(F$13) | I96: =SUM(I97:I98) | K96: =I96/(I$13) | L96: =SUM(L97:L98) | N96: =L96/(L$13) | O96: =SUM(O97:O98) | Q96: =O96/(O$13) | R96: =SUM(R97:R98) | T96: =R96/(R$13) | U96: =SUM(U97:U98) | W96: =U96/(U$13) | X96: =SUM(X97:X98) | Z96: =X96/(X$13) | AA96: =SUM(AA97:AA98) | AC96: =AA96/(AA$13) | AD96: =SUM(AD97:AD98) | AF96: =AD96/(AD$13) | AG96: =SUM(AG97:AG98) | AI96: =AG96/(AG$13) | AJ96: =SUM(AJ97:AJ98) | AM96: =C96+F96+I96+L96+O96+R96+U96+X96+AA96+AD96+AG96+AJ96 | AO96: =AM96/(AM$13)
A97: 73301001 | B97: Cumplimiento | C97: ='[47]Hoja 1'!$C$535+'[15]Hoja 1'!$C$92 | AM97: =C97+F97+I97+L97+O97+R97+U97+X97+AA97+AD97+AG97+AJ97
A98: 73306001 | B98: Responsabilidad Civil Y Extracontractual | C98: ='[15]Hoja 1'!$C$94 | AM98: =C98+F98+I98+L98+O98+R98+U98+X98+AA98+AD98+AG98+AJ98
B99: SERVICIOS | C99: =SUM(C100:C108) | E99: =C99/(C$13) | F99: =SUM(F100:F108) | H99: =F99/(F$13) | I99: =SUM(I100:I108) | K99: =I99/(I$13) | L99: =SUM(L100:L108) | N99: =L99/(L$13) | O99: =SUM(O100:O108) | Q99: =O99/(O$13) | R99: =SUM(R100:R108) | T99: =R99/(R$13) | U99: =SUM(U100:U108) | W99: =U99/(U$13) | X99: =SUM(X100:X108) | Z99: =X99/(X$13) | AA99: =SUM(AA100:AA108) | AC99: =AA99/(AA$13) | AD99: =SUM(AD100:AD108) | AF99: =AD99/(AD$13) | AG99: =SUM(AG100:AG108) | AI99: =AG99/(AG$13) | AJ99: =SUM(AJ100:AJ108) | AM99: =C99+F99+I99+L99+O99+R99+U99+X99+AA99+AD99+AG99+AJ99 | AO99: =AM99/(AM$13) | AP99: 1.051
B100: Aseo y Vigilancia | AM100: =C100+F100+I100+L100+O100+R100+U100+X100+AA100+AD100+AG100+AJ100
B101: Temporales Serv | AM101: =C101+F101+I101+L101+O101+R101+U101+X101+AA101+AD101+AG101+AJ101
B102: Mensajeria | AM102: =C102+F102+I102+L102+O102+R102+U102+X102+AA102+AD102+AG102+AJ102
A103: 73351502 | B103: Laboratorio | F103: ='[19]Hoja 1'!C209 | AM103: =C103+F103+I103+L103+O103+R103+U103+X103+AA103+AD103+AG103+AJ103
A104: 73351503 | B104: Fumigacion | C104: ='[15]Hoja 1'!$C$97 | F104: ='[19]Hoja 1'!C210 | AM104: =C104+F104+I104+L104+O104+R104+U104+X104+AA104+AD104+AG104+AJ104
A105: 73352501 | B105: Acueducto y Alcantarillado | C105: ='[9]Hoja 1'!$C$492+'[15]Hoja 1'!$C$99 | F105: ='[10]Hoja 1'!$C$465+'[19]Hoja 1'!$C$212 | AM105: =C105+F105+I105+L105+O105+R105+U105+X105+AA105+AD105+AG105+AJ105
A106: 73353001 | B106: Energia | C106: ='[9]Hoja 1'!$C$494+'[15]Hoja 1'!$C$101 | F106: ='[10]Hoja 1'!$C$467+'[19]Hoja 1'!$C$214 | AM106: =C106+F106+I106+L106+O106+R106+U106+X106+AA106+AD106+AG106+AJ106
A107: 73353501 | B107: Telefono e Internet | C107: ='[9]Hoja 1'!$C$496 | F107: ='[10]Hoja 1'!$C$469 | AM107: =C107+F107+I107+L107+O107+R107+U107+X107+AA107+AD107+AG107+AJ107
A108: 73354001 | B108: Correo, porte y telegramas | C108: ='[15]Hoja 1'!$C$103 | F108: ='[19]Hoja 1'!$C$216 | AM108: =C108+F108+I108+L108+O108+R108+U108+X108+AA108+AD108+AG108+AJ108
B109: GASTOS LEGALES | C109: =SUM(C110:C113) | E109: =C109/(C$13) | F109: =SUM(F110:F113) | H109: =F109/(F$13) | I109: =SUM(I110:I113) | K109: =I109/(I$13) | L109: =SUM(L110:L113) | N109: =L109/(L$13) | O109: =SUM(O110:O113) | Q109: =O109/(O$13) | R109: =SUM(R110:R113) | T109: =R109/(R$13) | U109: =SUM(U110:U113) | W109: =U109/(U$13) | X109: =SUM(X110:X113) | Z109: =X109/(X$13) | AA109: =SUM(AA110:AA113) | AC109: =AA109/(AA$13) | AD109: =SUM(AD110:AD113) | AF109: =AD109/(AD$13) | AG109: =SUM(AG110:AG113) | AJ109: =SUM(AJ110:AJ113) | AM109: =C109+F109+I109+L109+O109+R109+U109+X109+AA109+AD109+AG109+AJ109 | AO109: =AM109/(AM$13)
A110: 73400501 | B110: Notariales | AM110: =C110+F110+I110+L110+O110+R110+U110+X110+AA110+AD110+AG110+AJ110
...

Sheet IMDERTY
B2: CORPORACIÓN HACIA UN VALLE SOLIDARIO | C2: PRESUPUESTO IMDERTY 2024
B3: DIAS DE ATENCIÓN | L3: 20 | O3: 20 | R3: 20 | U3: 20 | X3: 20 | AA3: 20 | AD3: 20 | AG3: 20 | AJ3: 20 | AM3: =SUM(C3:AL3)
C4: ENE | D4: x racion | E4: % | F4: FEB | G4: x racion | H4: % | I4: MAR | J4: x racion | K4: % | L4: ABR | M4: x racion | N4: % | O4: MAY | P4: x racion | Q4: % | R4: JUN | S4: x racion | T4: % | U4: JUL | V4: x racion | W4: % | X4: AGO | Y4: x racion | Z4: % | AA4: SEP | AB4: x racion | AC4: % | AD4: OCT | AE4: x racion | AF4: % | AG4: NOV | AH4: x racion | AI4: % | AJ4: DIC | AK4: x racion | AL4: % | AM4: ACUMULADO | AN4: x racion | AO4: % | AQ4: REAL 2024
B5: SUMINISTRO | AM5: =C5+F5+I5+L5+O5+R5+U5+X5+AA5+AD5+AG5+AJ5 | AO5: =AM5/AM12
AM6: =C6+F6+I6+L6+O6+R6+U6+X6+AA6+AD6+AG6+AJ6 | AO6: =AM6/AM12
AM7: =C7+F7+I7+L7+O7+R7+U7+X7+AA7+AD7+AG7+AJ7 | AO7: =AM7/AM12
AM8: =C8+F8+I8+L8+O8+R8+U8+X8+AA8+AD8+AG8+AJ8
AM9: =C9+F9+I9+L9+O9+R9+U9+X9+AA9+AD9+AG9+AJ9
AM10: =C10+F10+I10+L10+O10+R10+U10+X10+AA10+AD10+AG10+AJ10
AM11: =C11+F11+I11+L11+O11+R11+U11+X11+AA11+AD11+AG11+AJ11
B12: TOTAL RACIONES | C12: =SUM(C5:C11) | F12: =SUM(F5:F11) | I12: =SUM(I5:I11) | L12: =SUM(L5:L11) | O12: =SUM(O5:O11) | R12: =SUM(R5:R11) | U12: =SUM(U5:U11) | X12: =SUM(X5:X11) | AA12: =SUM(AA5:AA11) | AD12: =SUM(AD5:AD11) | AG12: =SUM(AG5:AG11) | AJ12: =SUM(AJ5:AJ11) | AM12: =C12+F12+I12+L12+O12+R12+U12+X12+AA12+AD12+AG12+AJ12 | AQ12: =SUM(AQ5:AQ11)
B13: INGRESOS BRUTOS | C13: =C14+C23 | F13: =F14+F23 | I13: =I14+I23 | L13: =L14+L23 | O13: =O14+O23 | R13: =R14+R23 | U13: =U14+U23 | X13: =X14+X23 | AA13: =AA14+AA23 | AD13: =AD14+AD23 | AG13: =AG14+AG23 | AJ13: =AJ14+AJ23 | AM13: =C13+F13+I13+L13+O13+R13+U13+X13+AA13+AD13+AG13+AJ13 | AQ13: =AQ14+AQ23
B14: OPERACIONALES | C14: =C15 | F14: =F15 | I14: =I15 | L14: =L15 | O14: =O15 | R14: =R15 | U14: =U15 | X14: =X15 | AA14: =AA15 | AD14: =AD15 | AG14: =AG15 | AJ14: =AJ15 | AM14: =C14+F14+I14+L14+O14+R14+U14+X14+AA14+AD14+AG14+AJ14 | AQ14: =AQ15
B15: INDUSTRIAS MANUFACTURERAS | C15: =SUM(C16:C22) | F15: =SUM(F16:F22) | I15: =SUM(I16:I22) | L15: =SUM(L16:L22) | O15: =SUM(O16:O22) | R15: =SUM(R16:R22) | U15: =SUM(U16:U22) | X15: =SUM(X16:X22) | Z15: =X15/X15 | AA15: =SUM(AA16:AA22) | AC15: =AA15/AA15 | AD15: =SUM(AD16:AD22) | AF15: =AD15/AD15 | AG15: =SUM(AG16:AG22) | AI15: =AG15/AG15 | AJ15: =SUM(AJ16:AJ22) | AM15: =C15+F15+I15+L15+O15+R15+U15+X15+AA15+AD15+AG15+AJ15 | AO15: =AM15/AM15 | AQ15: =SUM(AQ16:AQ22)
B16: SUMINISTRO | J16: =I16/I5 | P16: =O16/O5 | S16: =R16/R5 | V16: =U16/U5 | Y16: =X16/X5 | AB16: =AA16/AA5 | AE16: =AD16/AD5 | AH16: =AG16/AG5 | AK16: =AJ16/AJ5 | AM16: =C16+F16+I16+L16+O16+R16+U16+X16+AA16+AD16+AG16+AJ16 | AO16: =AM16/AM$13
AM17: =C17+F17+I17+L17+O17+R17+U17+X17+AA17+AD17+AG17+AJ17 | AO17: =AM17/AM$13
AM18: =C18+F18+I18+L18+O18+R18+U18+X18+AA18+AD18+AG18+AJ18 | AO18: =AM18/AM$13
AE19: =AD19/AD8 | AH19: =AG19/AG8 | AK19: =AJ19/AJ8 | AM19: =C19+F19+I19+L19+O19+R19+U19+X19+AA19+AD19+AG19+AJ19
AM20: =C20+F20+I20+L20+O20+R20+U20+X20+AA20+AD20+AG20+AJ20
AM21: =C21+F21+I21+L21+O21+R21+U21+X21+AA21+AD21+AG21+AJ21
AM22: =C22+F22+I22+L22+O22+R22+U22+X22+AA22+AD22+AG22+AJ22
B23: NO OPERACIONALES | C23: =C24 | F23: =F24 | I23: =I24 | L23: =L24 | O23: =O24 | R23: =R24 | U23: =U24 | X23: =X24 | AA23: =AA24 | AM23: =C23+F23+I23+L23+O23+R23+U23+X23+AA23+AD23+AG23+AJ23
B24: FINANCIEROS | C24: =SUM(C25:C27) | F24: =SUM(F25:F27) | I24: =SUM(I25:I27) | L24: =SUM(L25:L27) | O24: =SUM(O25:O27) | R24: =SUM(R25:R27) | U24: =SUM(U25:U27) | X24: =SUM(X25:X27) | AA24: =SUM(AA25:AA27) | AD24: =SUM(AD25:AD27) | AG24: =SUM(AG25:AG27) | AJ24: =SUM(AJ25:AJ27) | AM24: =C24+F24+I24+L24+O24+R24+U24+X24+AA24+AD24+AG24+AJ24
B25: Intereses | AM25: =C25+F25+I25+L25+O25+R25+U25+X25+AA25+AD25+AG25+AJ25
B26: Descuentos Comerciales | AM26: =C26+F26+I26+L26+O26+R26+U26+X26+AA26+AD26+AG26+AJ26
B27: otros | AM27: =C27+F27+I27+L27+O27+R27+U27+X27+AA27+AD27+AG27+AJ27
B28: DESCUENTOS - GASTO OPERACIONAL | C28: =+C29 | F28: =+F29 | I28: =+I29 | L28: =+L29 | O28: =+O29 | R28: =+R29 | U28: =+U29 | X28: =+X29 | AA28: =+AA29 | AD28: =+AD29 | AG28: =+AG29 | AJ28: =+AJ29 | AM28: =C28+F28+I28+L28+O28+R28+U28+X28+AA28+AD28+AG28+AJ28 | AQ28: =+AQ29
B29: OTROS | C29: =SUM(C30:C35) | F29: =SUM(F30:F35) | H29: =F29/F13 | I29: =SUM(I30:I35) | K29: =I29/I13 | L29: =SUM(L30:L35) | O29: =SUM(O30:O35) | R29: =SUM(R30:R35) | T29: =R29/R13 | U29: =SUM(U30:U35) | W29: =U29/U13 | X29: =SUM(X30:X35) | Z29: =X29/X13 | AA29: =SUM(AA30:AA35) | AC29: =AA29/AA13 | AD29: =SUM(AD30:AD35) | AF29: =AD29/AD13 | AG29: =SUM(AG30:AG35) | AI29: =AG29/AG13 | AJ29: =SUM(AJ30:AJ35) | AM29: =C29+F29+I29+L29+O29+R29+U29+X29+AA29+AD29+AG29+AJ29 | AO29: =AM29/AM13 | AQ29: =SUM(AQ30:AQ35)
B30: 1,35% Estampillas | I30: =I13*1% | U30: =U13*1.35% | X30: =X13*1.35% | AA30: =AA13*1.35% | AD30: =AD13*1.35% | AG30: =AG13*1.35% | AJ30: =AJ13*1.35% | AM30: =C30+F30+I30+L30+O30+R30+U30+X30+AA30+AD30+AG30+AJ30
I31: =I13*0.6% | AM31: =C31+F31+I31+L31+O31+R31+U31+X31+AA31+AD31+AG31+AJ31
AM32: =C32+F32+I32+L32+O32+R32+U32+X32+AA32+AD32+AG32+AJ32
AM33: =C33+F33+I33+L33+O33+R33+U33+X33+AA33+AD33+AG33+AJ33
C34: =(C$13*10%)*3.5% | I34: =I13*2.5% | AM34: =C34+F34+I34+L34+O34+R34+U34+X34+AA34+AD34+AG34+AJ34
AM35: =C35+F35+I35+L35+O35+R35+U35+X35+AA35+AD35+AG35+AJ35
B42: TOTAL INGRESOS NETOS | C42: =+C14+C23-C28 | F42: =+F14+F23-F28 | I42: =+I14+I23-I28 | L42: =+L14+L23-L28 | O42: =+O14+O23-O28 | R42: =+R14+R23-R28 | U42: =+U14+U23-U28 | X42: =+X14+X23-X28 | AA42: =+AA14+AA23-AA28 | AD42: =+AD14+AD23-AD28 | AG42: =+AG14+AG23-AG28 | AJ42: =+AJ14+AJ23-AJ28 | AM42: =C42+F42+I42+L42+O42+R42+U42+X42+AA42+AD42+AG42+AJ42 | AQ42: =+AQ14+AQ23-AQ28
B44: COSTOS DE PRODUCCION | C44: =+C45+C60+C78 | F44: =+F45+F60+F78 | H44: =F44/F$13 | I44: =+I45+I60+I78 | K44: =I44/I$13 | L44: =+L45+L60+L78 | O44: =+O45+O60+O78 | Q44: =O44/O$13 | R44: =+R45+R60+R78 | T44: =R44/R$13 | U44: =+U45+U60+U78 | W44: =U44/U$13 | X44: =+X45+X60+X78 | Z44: =X44/X$13 | AA44: =+AA45+AA60+AA78 | AC44: =AA44/AA$13 | AD44: =+AD45+AD60+AD78 | AF44: =AD44/AD$13 | AG44: =+AG45+AG60+AG78 | AI44: =AG44/AG$13 | AJ44: =+AJ45+AJ60+AJ78 | AL44: =AJ44/AJ$13 | AM44: =C44+F44+I44+L44+O44+R44+U44+X44+AA44+AD44+AG44+AJ44 | AO44: =AM44/AM$13 | AQ44: =+AQ45+AQ60+AQ78
B45: COSTOS INDUSTRIALIZADOS | C45: =+C46+C58+C59 | F45: =+F46+F57 | H45: =F45/F13 | I45: =+I46+I57 | K45: =I45/I13 | L45: =+L46+L57 | O45: =+O46+O57 | R45: =+R46+R57 | T45: =R45/R13 | U45: =+U46+U57 | W45: =U45/U13 | X45: =+X46+X57 | AA45: =+AA46+AA57 | AD45: =+AD46+AD57 | AG45: =+AG46+AG57 | AJ45: =+AJ46+AJ57 | AM45: =C45+F45+I45+L45+O45+R45+U45+X45+AA45+AD45+AG45+AJ45 | AQ45: =+AQ46+AQ57
B46: INSUMOS | C46: =SUM(C47:C56)+C57 | F46: =SUM(F47:F56) | I46: =SUM(I47:I56) | L46: =SUM(L47:L56) | O46: =SUM(O47:O56) | R46: =SUM(R47:R56) | U46: =SUM(U47:U56) | X46: =SUM(X47:X56) | AA46: =SUM(AA47:AA56) | AD46: =SUM(AD47:AD56) | AG46: =SUM(AG47:AG56) | AJ46: =SUM(AJ47:AJ56) | AM46: =C46+F46+I46+L46+O46+R46+U46+X46+AA46+AD46+AG46+AJ46 | AQ46: =SUM(AQ47:AQ56)
B47: SUMINISTRO | J47: =I47/I5 | K47: =I47/I16 | P47: =O47/O5 | Q47: =O47/O16 | S47: =R47/R5 | T47: =R47/R16 | V47: =U47/U5 | W47: =U47/U16 | Y47: =X47/X5 | Z47: =X47/X16 | AB47: =AA47/AA5 | AC47: =AA47/AA16 | AE47: =AD47/AD5 | AF47: =AD47/AD16 | AH47: =AG47/AG5 | AI47: =AG47/AG16 | AK47: =AJ47/AJ5 | AL47: =AJ47/AJ16 | AM47: =C47+F47+I47+L47+O47+R47+U47+X47+AA47+AD47+AG47+AJ47 | AN47: =AM47/$AM$5 | AO47: =AM47/AM13
AM48: =C48+F48+I48+L48+O48+R48+U48+X48+AA48+AD48+AG48+AJ48 | AN48: =AM48/AM12
AM49: =C49+F49+I49+L49+O49+R49+U49+X49+AA49+AD49+AG49+AJ49
AM50: =C50+F50+I50+L50+O50+R50+U50+X50+AA50+AD50+AG50+AJ50
AM51: =C51+F51+I51+L51+O51+R51+U51+X51+AA51+AD51+AG51+AJ51
AM52: =C52+F52+I52+L52+O52+R52+U52+X52+AA52+AD52+AG52+AJ52
AM53: =C53+F53+I53+L53+O53+R53+U53+X53+AA53+AD53+AG53+AJ53
B57: FLETES | F57: =SUM(F58:F59) | G57: =F57/F12 | H57: =F57/F13 | I57: =SUM(I58:I59) | J57: =I57/I12 | K57: =I57/I13 | L57: =SUM(L58:L59) | O57: =SUM(O58:O59) | R57: =SUM(R58:R59) | U57: =SUM(U58:U59) | X57: =SUM(X58:X59) | AA57: =SUM(AA58:AA59) | AD57: =SUM(AD58:AD59) | AG57: =SUM(AG58:AG59) | AJ57: =SUM(AJ58:AJ59) | AM57: =C57+F57+I57+L57+O57+R57+U57+X57+AA57+AD57+AG57+AJ57 | AN57: =AM57/AM12 | AO57: =AM57/AM13
B58: INDUSTRIALIZADOS PROPIOS | AM58: =C58+F58+I58+L58+O58+R58+U58+X58+AA58+AD58+AG58+AJ58 | AO58: =AM58/AM$13
B59: INDUSTRIALIZADOS TERCEROS | AM59: =C59+F59+I59+L59+O59+R59+U59+X59+AA59+AD59+AG59+AJ59 | AO59: =AM59/AM$13
B60: COSTOS PREPARADOS | C60: =+C61+C73+C74+C75+C76+C77 | F60: =+F61+F72+F75+F76+F77 | H60: =F60/F13 | I60: =+I61+I72+I75+I76+I77 | K60: =I60/I13 | L60: =+L61+L72+L75+L76+L77 | O60: =+O61+O72+O75+O76+O77 | R60: =+R61+R72+R75+R76+R77 | U60: =+U61+U72+U75+U76+U77 | X60: =+X61+X72+X75+X76+X77 | AA60: =+AA61+AA72+AA75+AA76+AA77 | AD60: =+AD61+AD72+AD75+AD76+AD77 | AG60: =+AG61+AG72+AG75+AG76+AG77 | AJ60: =+AJ61+AJ72+AJ75+AJ76+AJ77 | AM60: =C60+F60+I60+L60+O60+R60+U60+X60+AA60+AD60+AG60+AJ60 | AQ60: =+AQ61+AQ72+AQ75+AQ76+AQ77
B61: INSUMOS | C61: =SUM(C62:C71)+C72 | F61: =SUM(F62:F71) | I61: =SUM(I62:I71) | L61: =SUM(L62:L71) | O61: =SUM(O62:O71) | P61: =O61/$O$5 | R61: =SUM(R62:R71) | S61: =R61/$O$5 | T61: =R61/$O$13 | U61: =SUM(U62:U71) | V61: =U61/$O$5 | W61: =U61/$O$13 | X61: =SUM(X62:X71) | AA61: =SUM(AA62:AA71) | AD61: =SUM(AD62:AD71) | AG61: =SUM(AG62:AG71) | AJ61: =SUM(AJ62:AJ71) | AM61: =C61+F61+I61+L61+O61+R61+U61+X61+AA61+AD61+AG61+AJ61 | AN61: =AM61/$O$5 | AO61: =AM61/$O$13 | AQ61: =SUM(AQ62:AQ71)
AM62: =C62+F62+I62+L62+O62+R62+U62+X62+AA62+AD62+AG62+AJ62 | AN62: =AM62/$O$5 | AO62: =AM62/$O$13
AM63: =C63+F63+I63+L63+O63+R63+U63+X63+AA63+AD63+AG63+AJ63 | AN63: =AM63/$O$5 | AO63: =AM63/$O$13
AM64: =C64+F64+I64+L64+O64+R64+U64+X64+AA64+AD64+AG64+AJ64 | AN64: =AM64/$O$5 | AO64: =AM64/$O$13
AM65: =C65+F65+I65+L65+O65+R65+U65+X65+AA65+AD65+AG65+AJ65 | AN65: =AM65/$O$5 | AO65: =AM65/$O$13
AM66: =C66+F66+I66+L66+O66+R66+U66+X66+AA66+AD66+AG66+AJ66 | AN66: =AM66/$O$5 | AO66: =AM66/$O$13
AN67: =AM67/$O$5 | AO67: =AM67/$O$13
AN68: =AM68/$O$5 | AO68: =AM68/$O$13
AN69: =AM69/$O$5 | AO69: =AM69/$O$13
AN70: =AM70/$O$5 | AO70: =AM70/$O$13
AM71: =C71+F71+I71+L71+O71+R71+U71+X71+AA71+AD71+AG71+AJ71 | AN71: =AM71/$O$5 | AO71: =AM71/$O$13
B72: FLETES | F72: =SUM(F73:F74) | G72: =F72/F12 | H72: =F72/F13 | I72: =SUM(I73:I74) | J72: =I72/I12 | K72: =I72/I13 | L72: =SUM(L73:L74) | O72: =SUM(O73:O74) | P72: =O72/O12 | Q72: =O72/O13 | R72: =SUM(R73:R74) | S72: =R72/R12 | T72: =R72/R13 | U72: =SUM(U73:U74) | V72: =U72/U12 | W72: =U72/U13 | X72: =SUM(X73:X74) | Y72: =X72/X12 | Z72: =X72/X13 | AA72: =SUM(AA73:AA74) | AB72: =AA72/AA12 | AC72: =AA72/AA13 | AD72: =SUM(AD73:AD74) | AE72: =AD72/AD12 | AF72: =AD72/AD13 | AG72: =SUM(AG73:AG74) | AH72: =AG72/AG12 | AI72: =AG72/AG13 | AJ72: =SUM(AJ73:AJ74) | AM72: =C72+F72+I72+L72+O72+R72+U72+X72+AA72+AD72+AG72+AJ72 | AN72: =AM72/AM12 | AO72: =AM72/AM13 | AQ72: =SUM(AQ73:AQ74)
B73: PREPARADOS PROPIOS | AM73: =C73+F73+I73+L73+O73+R73+U73+X73+AA73+AD73+AG73+AJ73
B74: PREPARADOS TERCEROS | AM74: =C74+F74+I74+L74+O74+R74+U74+X74+AA74+AD74+AG74+AJ74
B75: Material de empaque | AM75: =C75+F75+I75+L75+O75+R75+U75+X75+AA75+AD75+AG75+AJ75 | AO75: =AM75/AM$13
B76: Menaje | AM76: =C76+F76+I76+L76+O76+R76+U76+X76+AA76+AD76+AG76+AJ76
B77: Servicio de Gas | AM77: =C77+F77+I77+L77+O77+R77+U77+X77+AA77+AD77+AG77+AJ77
B78: MANO DE OBRA DIRECTA | C78: =SUM(C79:C81) | F78: =SUM(F79:F81) | H78: =F78/(F$13) | I78: =SUM(I79:I81) | K78: =I78/(I$13) | L78: =SUM(L79:L81) | O78: =SUM(O79:O81) | R78: =SUM(R79:R81) | T78: =R78/(R$13) | U78: =SUM(U79:U81) | W78: =U78/(U$13) | X78: =SUM(X79:X81) | Z78: =X78/(X$13) | AA78: =SUM(AA79:AA81) | AC78: =AA78/(AA$13) | AD78: =SUM(AD79:AD81) | AF78: =AD78/(AD$13) | AG78: =SUM(AG79:AG81) | AI78: =AG78/(AG$13) | AJ78: =SUM(AJ79:AJ81) | AM78: =C78+F78+I78+L78+O78+R78+U78+X78+AA78+AD78+AG78+AJ78 | AO78: =AM78/(AM$13) | AQ78: =SUM(AQ79:AQ81)
B79: Manipuladoras | AM79: =C79+F79+I79+L79+O79+R79+U79+X79+AA79+AD79+AG79+AJ79 | AN79: =AM79/AM12
B80: Personal Supervisor - Coordinadores | AM80: =C80+F80+I80+L80+O80+R80+U80+X80+AA80+AD80+AG80+AJ80
B81: Temporales | AM81: =C81+F81+I81+L81+O81+R81+U81+X81+AA81+AD81+AG81+AJ81
B83: OTROS COSTOS Y GASTOS INDIRECTOS | C83: =+C84+C89+C92+C96+C99+C109+C114+C120+C123+C127 | F83: =+F84+F89+F92+F96+F99+F109+F114+F120+F123+F127 | H83: =F83/(F$13) | I83: =+I84+I89+I92+I96+I99+I109+I114+I120+I123+I127 | K83: =I83/(I$13) | L83: =+L84+L89+L92+L96+L99+L109+L114+L120+L123+L127 | O83: =+O84+O89+O92+O96+O99+O109+O114+O120+O123+O127 | Q83: =O83/(O$13) | R83: =+R84+R89+R92+R96+R99+R109+R114+R120+R123+R127 | T83: =R83/(R$13) | U83: =+U84+U89+U92+U96+U99+U109+U114+U120+U123+U127 | W83: =U83/(U$13) | X83: =+X84+X89+X92+X96+X99+X109+X114+X120+X123+X127 | Z83: =X83/(X$13) | AA83: =+AA84+AA89+AA92+AA96+AA99+AA109+AA114+AA120+AA123+AA127 | AC83: =AA83/(AA$13) | AD83: =+AD84+AD89+AD92+AD96+AD99+AD109+AD114+AD120+AD123+AD127 | AF83: =AD83/(AD$13) | AG83: =+AG84+AG89+AG92+AG96+AG99+AG109+AG114+AG120+AG123+AG127 | AI83: =AG83/(AG$13) | AJ83: =+AJ84+AJ89+AJ92+AJ96+AJ99+AJ109+AJ114+AJ120+AJ123+AJ127 | AL83: =AJ83/(AJ$13) | AM83: =C83+F83+I83+L83+O83+R83+U83+X83+AA83+AD83+AG83+AJ83 | AO83: =AM83/(AM$13) | AQ83: =+AQ84+AQ89+AQ92+AQ96+AQ99+AQ109+AQ114+AQ120+AQ123+AQ127
B84: COSTOS DE PERSONAL | C84: =SUM(C85:C88) | F84: =SUM(F85:F88) | H84: =F84/(F$13) | I84: =SUM(I85:I88) | K84: =I84/(I$13) | L84: =SUM(L85:L88) | O84: =SUM(O85:O88) | R84: =SUM(R85:R88) | T84: =R84/(R$13) | U84: =SUM(U85:U88) | W84: =U84/(U$13) | X84: =SUM(X85:X88) | Z84: =X84/(X$13) | AA84: =SUM(AA85:AA88) | AC84: =AA84/(AA$13) | AD84: =SUM(AD85:AD88) | AF84: =AD84/(AD$13) | AG84: =SUM(AG85:AG88) | AI84: =AG84/(AG$13) | AJ84: =SUM(AJ85:AJ88) | AL84: =AJ84/(AJ$13) | AM84: =C84+F84+I84+L84+O84+R84+U84+X84+AA84+AD84+AG84+AJ84 | AO84: =AM84/(AM$13) | AQ84: =SUM(AQ85:AQ88)
B85: Costos Indirectos de Personal | AM85: =C85+F85+I85+L85+O85+R85+U85+X85+AA85+AD85+AG85+AJ85 | AO85: =AM85/(AM$13)
B86: Dotación y Suministros | AM86: =C86+F86+I86+L86+O86+R86+U86+X86+AA86+AD86+AG86+AJ86
B87: Gastos Medicos | AM87: =C87+F87+I87+L87+O87+R87+U87+X87+AA87+AD87+AG87+AJ87
B88: Inacapacidades | AM88: =C88+F88+I88+L88+O88+R88+U88+X88+AA88+AD88+AG88+AJ88
B89: HONORARIOS | C89: =SUM(C90:C91) | F89: =SUM(F90:F91) | H89: =F89/(F$13) | I89: =SUM(I90:I91) | K89: =I89/(I$13) | L89: =SUM(L90:L91) | O89: =SUM(O90:O91) | R89: =SUM(R90:R91) | T89: =R89/(R$13) | U89: =SUM(U90:U91) | W89: =U89/(U$13) | X89: =SUM(X90:X91) | Z89: =X89/(X$13) | AA89: =SUM(AA90:AA91) | AC89: =AA89/(AA$13) | AD89: =SUM(AD90:AD91) | AF89: =AD89/(AD$13) | AG89: =SUM(AG90:AG91) | AI89: =AG89/(AG$13) | AJ89: =SUM(AJ90:AJ91) | AM89: =C89+F89+I89+L89+O89+R89+U89+X89+AA89+AD89+AG89+AJ89 | AO89: =AM89/(AM$13)
B90: Asesoría Juridica | AM90: =C90+F90+I90+L90+O90+R90+U90+X90+AA90+AD90+AG90+AJ90
B91: Asesoría Tecnica | AM91: =C91+F91+I91+L91+O91+R91+U91+X91+AA91+AD91+AG91+AJ91
B92: ARRENDAMIENTOS | C92: =SUM(C93:C95) | F92: =SUM(F93:F95) | H92: =F92/(F$13) | I92: =SUM(I93:I95) | K92: =I92/(I$13) | L92: =SUM(L93:L95) | O92: =SUM(O93:O95) | R92: =SUM(R93:R95) | T92: =R92/(R$13) | U92: =SUM(U93:U95) | W92: =U92/(U$13) | X92: =SUM(X93:X95) | Z92: =X92/(X$13) | AA92: =SUM(AA93:AA95) | AC92: =AA92/(AA$13) | AD92: =SUM(AD93:AD95) | AF92: =AD92/(AD$13) | AG92: =SUM(AG93:AG95) | AI92: =AG92/(AG$13) | AJ92: =SUM(AJ93:AJ95) | AM92: =C92+F92+I92+L92+O92+R92+U92+X92+AA92+AD92+AG92+AJ92 | AO92: =AM92/(AM$13)
B93: Construcciones y Edificaciones | AM93: =C93+F93+I93+L93+O93+R93+U93+X93+AA93+AD93+AG93+AJ93
B94: Maquinaria y Equipo | AM94: =C94+F94+I94+L94+O94+R94+U94+X94+AA94+AD94+AG94+AJ94
B95: Equipo de Oficina | AM95: =C95+F95+I95+L95+O95+R95+U95+X95+AA95+AD95+AG95+AJ95
B96: SEGUROS | C96: =SUM(C97:C98) | F96: =SUM(F97:F98) | H96: =F96/(F$13) | I96: =SUM(I97:I98) | K96: =I96/(I$13) | L96: =SUM(L97:L98) | O96: =SUM(O97:O98) | R96: =SUM(R97:R98) | T96: =R96/(R$13) | U96: =SUM(U97:U98) | W96: =U96/(U$13) | X96: =SUM(X97:X98) | Z96: =X96/(X$13) | AA96: =SUM(AA97:AA98) | AC96: =AA96/(AA$13) | AD96: =SUM(AD97:AD98) | AF96: =AD96/(AD$13) | AG96: =SUM(AG97:AG98) | AI96: =AG96/(AG$13) | AJ96: =SUM(AJ97:AJ98) | AM96: =C96+F96+I96+L96+O96+R96+U96+X96+AA96+AD96+AG96+AJ96 | AO96: =AM96/(AM$13) | AQ96: =SUM(AQ97:AQ98)
A97: 73301001 | B97: Cumplimiento | AM97: =C97+F97+I97+L97+O97+R97+U97+X97+AA97+AD97+AG97+AJ97
A98: 73306001 | B98: Respomsabilidad Civil Y Extracontractual | AM98: =C98+F98+I98+L98+O98+R98+U98+X98+AA98+AD98+AG98+AJ98
B99: SERVICIOS | C99: =SUM(C100:C108) | F99: =SUM(F100:F108) | H99: =F99/(F$13) | I99: =SUM(I100:I106) | K99: =I99/(I$13) | L99: =SUM(L100:L108) | O99: =SUM(O100:O108) | R99: =SUM(R100:R108) | T99: =R99/(R$13) | U99: =SUM(U100:U108) | W99: =U99/(U$13) | X99: =SUM(X100:X108) | Z99: =X99/(X$13) | AA99: =SUM(AA100:AA108) | AC99: =AA99/(AA$13) | AD99: =SUM(AD100:AD108) | AF99: =AD99/(AD$13) | AG99: =SUM(AG100:AG108) | AI99: =AG99/(AG$13) | AJ99: =SUM(AJ100:AJ108) | AM99: =C99+F99+I99+L99+O99+R99+U99+X99+AA99+AD99+AG99+AJ99 | AO99: =AM99/(AM$13)
B100: Aseo y Vigilancia | AM100: =C100+F100+I100+L100+O100+R100+U100+X100+AA100+AD100+AG100+AJ100
B101: Temporales | AM101: =C101+F101+I101+L101+O101+R101+U101+X101+AA101+AD101+AG101+AJ101
B102: Mensajeria | AM102: =C102+F102+I102+L102+O102+R102+U102+X102+AA102+AD102+AG102+AJ102
B103: Laboratorio | AM103: =C103+F103+I103+L103+O103+R103+U103+X103+AA103+AD103+AG103+AJ103
B104: Fumigacion | AM104: =C104+F104+I104+L104+O104+R104+U104+X104+AA104+AD104+AG104+AJ104
B105: Acueducto y Alcantarillado | AM105: =C105+F105+I105+L105+O105+R105+U105+X105+AA105+AD105+AG105+AJ105
B106: Energia | AM106: =C106+F106+I106+L106+O106+R106+U106+X106+AA106+AD106+AG106+AJ106
B107: Telefono e Internet | AM107: =C107+F107+I107+L107+O107+R107+U107+X107+AA107+AD107+AG107+AJ107
B108: Correo, porte y telegramas | AM108: =C108+F108+I108+L108+O108+R108+U108+X108+AA108+AD108+AG108+AJ108
B109: GASTOS LEGALES | C109: =SUM(C110:C113) | F109: =SUM(F110:F113) | H109: =F109/(F$13) | I109: =SUM(I110:I113) | K109: =I109/(I$13) | L109: =SUM(L110:L113) | O109: =SUM(O110:O113) | R109: =SUM(R110:R113) | T109: =R109/(R$13) | U109: =SUM(U110:U113) | W109: =U109/(U$13) | X109: =SUM(X110:X113) | Z109: =X109/(X$13) | AA109: =SUM(AA110:AA113) | AC109: =AA109/(AA$13) | AD109: =SUM(AD110:AD113) | AF109: =AD109/(AD$13) | AG109: =SUM(AG110:AG113) | AI109: =AG109/(AG$13) | AJ109: =SUM(AJ110:AJ113) | AM109: =C109+F109+I109+L109+O109+R109+U109+X109+AA109+AD109+AG109+AJ109 | AO109: =AM109/(AM$13) | AQ109: =SUM(AQ110:AQ113)
A110: 73400501 | B110: Notariales | AM110: =C110+F110+I110+L110+O110+R110+U110+X110+AA110+AD110+AG110+AJ110
A111: 73401001 | B111: Registro Mercantil | AM111: =C111+F111+I111+L111+O111+R111+U111+X111+AA111+AD111+AG111+AJ111
A112: 73401501 | B112: Trámites y Licencias | AM112: =C112+F112+I112+L112+O112+R112+U112+X112+AA112+AD112+AG112+AJ112
...

Sheet COMEDORES CALI
B2: CORPORACIÓN HACIA UN VALLE SOLIDARIO | C2: PYG COMEDORES CALI 2026
B3: DIAS DE ATENCIÓN | C3: 16 | F3: 20 | I3: 21 | L3: 20 | O3: 19 | R3: 19 | U3: 22 | X3: 19 | AA3: 22 | AD3: 21 | AG3: 19 | AJ3: 21 | AM3: =SUM(C3:AL3)
C4: ENE | D4: x racion | E4: % | F4: FEB | G4: x racion | H4: % | I4: MAR | J4: x racion | K4: % | L4: ABR | M4: x racion | N4: % | O4: MAY | P4: x racion | Q4: % | R4: JUN | S4: x racion | T4: % | U4: JUL | V4: x racion | W4: % | X4: AGO | Y4: x racion | Z4: % | AA4: SEP | AB4: x racion | AC4: % | AD4: OCT | AE4: x racion | AF4: % | AG4: NOV | AH4: x racion | AI4: % | AJ4: DIC | AK4: x racion | AL4: % | AM4: ACUMULADO | AN4: x racion | AO4: %
B5: SUMINISTRO lunes a viernes | AM5: =C5+F5+I5+L5+O5+R5+U5+X5+AA5+AD5+AG5+AJ5 | AO5: =AM5/AM12
B6: SUMINISTRO lunes a viernes OP | AM6: =C6+F6+I6+L6+O6+R6+U6+X6+AA6+AD6+AG6+AJ6 | AO6: =AM6/AM12
B7: SUMINISTRO Fines de Semana | AM7: =C7+F7+I7+L7+O7+R7+U7+X7+AA7+AD7+AG7+AJ7 | AO7: =AM7/AM12
B8: Contingencia | AM8: =C8+F8+I8+L8+O8+R8+U8+X8+AA8+AD8+AG8+AJ8
AM9: =C9+F9+I9+L9+O9+R9+U9+X9+AA9+AD9+AG9+AJ9
AM10: =C10+F10+I10+L10+O10+R10+U10+X10+AA10+AD10+AG10+AJ10
AM11: =C11+F11+I11+L11+O11+R11+U11+X11+AA11+AD11+AG11+AJ11
B12: TOTAL RACIONES | C12: =SUM(C5:C11) | F12: =SUM(F5:F11) | I12: =SUM(I5:I11) | L12: =SUM(L5:L11) | O12: =SUM(O5:O11) | R12: =SUM(R5:R11) | U12: =SUM(U5:U11) | X12: =SUM(X5:X11) | AA12: =SUM(AA5:AA11) | AD12: =SUM(AD5:AD11) | AG12: =SUM(AG5:AG11) | AJ12: =SUM(AJ5:AJ11) | AM12: =C12+F12+I12+L12+O12+R12+U12+X12+AA12+AD12+AG12+AJ12
B13: INGRESOS BRUTOS | C13: =C14+C23 | F13: =F14+F23 | I13: =I14+I23 | L13: =L14+L23 | O13: =O14+O23 | R13: =R14+R23 | U13: =U14+U23 | X13: =X14+X23 | AA13: =AA14+AA23 | AD13: =AD14+AD23 | AG13: =AG14+AG23 | AJ13: =AJ14+AJ23 | AM13: =C13+F13+I13+L13+O13+R13+U13+X13+AA13+AD13+AG13+AJ13
B14: OPERACIONALES | C14: =C15 | F14: =F15 | I14: =I15 | L14: =L15 | O14: =O15 | R14: =R15 | U14: =U15 | X14: =X15 | AA14: =AA15 | AD14: =AD15 | AG14: =AG15 | AJ14: =AJ15 | AM14: =C14+F14+I14+L14+O14+R14+U14+X14+AA14+AD14+AG14+AJ14
B15: INDUSTRIAS MANUFACTURERAS | C15: =SUM(C16:C22) | F15: =SUM(F16:F22) | I15: =SUM(I16:I22) | L15: =SUM(L16:L22) | O15: =SUM(O16:O22) | R15: =SUM(R16:R22) | U15: =SUM(U16:U22) | X15: =SUM(X16:X22) | Z15: =X15/X15 | AA15: =SUM(AA16:AA22) | AC15: =AA15/AA15 | AD15: =SUM(AD16:AD22) | AF15: =AD15/AD15 | AG15: =SUM(AG16:AG22) | AI15: =AG15/AG15 | AJ15: =SUM(AJ16:AJ22) | AM15: =C15+F15+I15+L15+O15+R15+U15+X15+AA15+AD15+AG15+AJ15 | AO15: =AM15/AM15
B16: SUMINISTRO lunes a viernes | J16: =I16/I5 | M16: =L16/L5 | P16: =O16/O5 | S16: =R16/R5 | V16: =U16/U5 | Y16: =X16/X5 | AB16: =AA16/AA5 | AE16: =AD16/AD5 | AH16: =AG16/AG5 | AK16: =AJ16/AJ5 | AM16: =C16+F16+I16+L16+O16+R16+U16+X16+AA16+AD16+AG16+AJ16 | AN16: =AM16/(AM5) | AO16: =AM16/AM$13
B17: SUMINISTRO lunes a viernes OP | AM17: =C17+F17+I17+L17+O17+R17+U17+X17+AA17+AD17+AG17+AJ17 | AO17: =AM17/AM$13
B18: SUMINISTRO Fines de Semana | J18: =I18/I7 | M18: =L18/L7 | P18: =O18/O7 | S18: =R18/R7 | V18: =U18/U7 | Y18: =X18/X7 | AB18: =AA18/AA7 | AE18: =AD18/AD7 | AH18: =AG18/AG7 | AK18: =AJ18/AJ7 | AM18: =C18+F18+I18+L18+O18+R18+U18+X18+AA18+AD18+AG18+AJ18 | AN18: =AM18/AM7 | AO18: =AM18/AM$13
B19: Contingencia | AM19: =C19+F19+I19+L19+O19+R19+U19+X19+AA19+AD19+AG19+AJ19
AM20: =C20+F20+I20+L20+O20+R20+U20+X20+AA20+AD20+AG20+AJ20
B21: TRANSPORTE Lunes a viernes | AM21: =C21+F21+I21+L21+O21+R21+U21+X21+AA21+AD21+AG21+AJ21
B22: TRANSPORTE Fines de Semana | AM22: =C22+F22+I22+L22+O22+R22+U22+X22+AA22+AD22+AG22+AJ22
B23: NO OPERACIONALES | C23: =C24 | F23: =F24 | I23: =I24 | L23: =L24 | O23: =O24 | R23: =R24 | U23: =U24 | X23: =X24 | AA23: =AA24 | AM23: =C23+F23+I23+L23+O23+R23+U23+X23+AA23+AD23+AG23+AJ23
B24: FINANCIEROS | C24: =SUM(C25:C27) | F24: =SUM(F25:F27) | I24: =SUM(I25:I27) | L24: =SUM(L25:L27) | O24: =SUM(O25:O27) | R24: =SUM(R25:R27) | U24: =SUM(U25:U27) | X24: =SUM(X25:X27) | AA24: =SUM(AA25:AA27) | AD24: =SUM(AD25:AD27) | AG24: =SUM(AG25:AG27) | AJ24: =SUM(AJ25:AJ27) | AM24: =C24+F24+I24+L24+O24+R24+U24+X24+AA24+AD24+AG24+AJ24
B25: Intereses | AM25: =C25+F25+I25+L25+O25+R25+U25+X25+AA25+AD25+AG25+AJ25
B26: Descuentos Comerciales | AM26: =C26+F26+I26+L26+O26+R26+U26+X26+AA26+AD26+AG26+AJ26
B27: otros Fin | AM27: =C27+F27+I27+L27+O27+R27+U27+X27+AA27+AD27+AG27+AJ27
B28: DESCUENTOS - GASTO OPERACIONAL | C28: =+C29 | F28: =+F29 | I28: =+I29 | L28: =+L29 | O28: =+O29 | R28: =+R29 | U28: =+U29 | X28: =+X29 | AA28: =+AA29 | AD28: =+AD29 | AG28: =+AG29 | AJ28: =+AJ29 | AM28: =C28+F28+I28+L28+O28+R28+U28+X28+AA28+AD28+AG28+AJ28
B29: OTROS | C29: =SUM(C30:C35) | F29: =SUM(F30:F35) | H29: =F29/F13 | I29: =SUM(I30:I35) | K29: =I29/I13 | L29: =SUM(L30:L35) | N29: =L29/L13 | O29: =SUM(O30:O35) | Q29: =O29/O13 | R29: =SUM(R30:R35) | T29: =R29/R13 | U29: =SUM(U30:U35) | W29: =U29/U13 | X29: =SUM(X30:X35) | Z29: =X29/X13 | AA29: =SUM(AA30:AA35) | AC29: =AA29/AA13 | AD29: =SUM(AD30:AD35) | AF29: =AD29/AD13 | AG29: =SUM(AG30:AG35) | AI29: =AG29/AG13 | AJ29: =SUM(AJ30:AJ35) | AM29: =C29+F29+I29+L29+O29+R29+U29+X29+AA29+AD29+AG29+AJ29 | AN29: =AM29/$AM$5 | AO29: =AM29/AM13
AM30: =C30+F30+I30+L30+O30+R30+U30+X30+AA30+AD30+AG30+AJ30
AM31: =C31+F31+I31+L31+O31+R31+U31+X31+AA31+AD31+AG31+AJ31
AM32: =C32+F32+I32+L32+O32+R32+U32+X32+AA32+AD32+AG32+AJ32
AM33: =C33+F33+I33+L33+O33+R33+U33+X33+AA33+AD33+AG33+AJ33
AM34: =C34+F34+I34+L34+O34+R34+U34+X34+AA34+AD34+AG34+AJ34
AM35: =C35+F35+I35+L35+O35+R35+U35+X35+AA35+AD35+AG35+AJ35
B42: TOTAL INGRESOS NETOS | C42: =+C14+C23-C28 | F42: =+F14+F23-F28 | I42: =+I14+I23-I28 | L42: =+L14+L23-L28 | O42: =+O14+O23-O28 | R42: =+R14+R23-R28 | U42: =+U14+U23-U28 | X42: =+X14+X23-X28 | AA42: =+AA14+AA23-AA28 | AD42: =+AD14+AD23-AD28 | AG42: =+AG14+AG23-AG28 | AJ42: =+AJ14+AJ23-AJ28 | AM42: =C42+F42+I42+L42+O42+R42+U42+X42+AA42+AD42+AG42+AJ42
B44: COSTOS DE PRODUCCION | C44: =+C45+C60+C78 | E44: =C44/C$13 | F44: =+F45+F60+F78 | H44: =F44/F$13 | I44: =+I45+I60+I78 | K44: =I44/I$13 | L44: =+L45+L60+L78 | N44: =L44/L$13 | O44: =+O45+O60+O78 | Q44: =O44/O$13 | R44: =+R45+R60+R78 | T44: =R44/R$13 | U44: =+U45+U60+U78 | W44: =U44/U$13 | X44: =+X45+X60+X78 | Z44: =X44/X$13 | AA44: =+AA45+AA60+AA78 | AC44: =AA44/AA$13 | AD44: =+AD45+AD60+AD78 | AF44: =AD44/AD$13 | AG44: =+AG45+AG60+AG78 | AI44: =AG44/AG$13 | AJ44: =+AJ45+AJ60+AJ78 | AL44: =AJ44/AJ$13 | AM44: =C44+F44+I44+L44+O44+R44+U44+X44+AA44+AD44+AG44+AJ44 | AO44: =AM44/AM$13
B45: COSTOS INDUSTRIALIZADOS | C45: =+C46+C58+C59 | F45: =+F46+F57 | H45: =F45/F13 | I45: =+I46+I57 | K45: =I45/I13 | L45: =+L46+L57 | O45: =+O46+O57 | R45: =+R46+R57 | T45: =R45/R13 | U45: =+U46+U57 | W45: =U45/U13 | X45: =+X46+X57 | AA45: =+AA46+AA57 | AD45: =+AD46+AD57 | AG45: =+AG46+AG57 | AJ45: =+AJ46+AJ57 | AM45: =C45+F45+I45+L45+O45+R45+U45+X45+AA45+AD45+AG45+AJ45 | AO45: =AM45/AM13
B46: INSUMOS CI | C46: =SUM(C47:C56)+C57 | F46: =SUM(F47:F56) | I46: =SUM(I47:I56) | L46: =SUM(L47:L56) | O46: =SUM(O47:O56) | R46: =SUM(R47:R56) | U46: =SUM(U47:U56) | X46: =SUM(X47:X56) | AA46: =SUM(AA47:AA56) | AD46: =SUM(AD47:AD56) | AG46: =SUM(AG47:AG56) | AJ46: =SUM(AJ47:AJ56) | AM46: =C46+F46+I46+L46+O46+R46+U46+X46+AA46+AD46+AG46+AJ46 | AO46: =AM46/(AM16+AM18+AM19)
A47: 7105 | B47: SUMINISTRO lunes a viernes | C47: 1.8485226e+09 | D47: =C47/C12 | E47: =C47/(C16+C18) | F47: 2.1903026e+09 | G47: =F47/F12 | H47: =F47/(F16+F18) | J47: =I47/I12 | K47: =I47/(I16+I18) | M47: =L47/L12 | N47: =L47/(L16+L18) | P47: =O47/O12 | Q47: =O47/(O16+O18) | S47: =R47/R12 | T47: =R47/(R16+R18) | V47: =U47/U12 | W47: =U47/(U16+U18) | Y47: =X47/X12 | Z47: =X47/(X16+X18) | AB47: =AA47/AA12 | AC47: =AA47/(AA16+AA18) | AE47: =AD47/AD12 | AF47: =AD47/(AD16+AD18) | AH47: =AG47/AG12 | AI47: =AG47/(AG16+AG18) | AK47: =AJ47/AJ12 | AL47: =AJ47/(AJ16+AJ18) | AM47: =C47+F47+I47+L47+O47+R47+U47+X47+AA47+AD47+AG47+AJ47 | AN47: =AM47/(AM5+AM7+AM8) | AO47: =AM47/(AM16+AM18+AM19)
B48: SUMINISTRO lunes a viernes OP | AM48: =C48+F48+I48+L48+O48+R48+U48+X48+AA48+AD48+AG48+AJ48
B49: SUMINISTRO Fines de Semana | AM49: =C49+F49+I49+L49+O49+R49+U49+X49+AA49+AD49+AG49+AJ49 | AN49: =AM49/AM7 | AO49: =AM49/AM18
AM50: =C50+F50+I50+L50+O50+R50+U50+X50+AA50+AD50+AG50+AJ50
AM51: =C51+F51+I51+L51+O51+R51+U51+X51+AA51+AD51+AG51+AJ51
B52: REFRIGERIOS | AM52: =C52+F52+I52+L52+O52+R52+U52+X52+AA52+AD52+AG52+AJ52
B53: PAQUETES MANIPULADORAS | AM53: =C53+F53+I53+L53+O53+R53+U53+X53+AA53+AD53+AG53+AJ53
B57: FLETES OPERADORES | F57: =SUM(F58:F59) | G57: =F57/F12 | H57: =F57/F13 | I57: =SUM(I58:I59) | J57: =I57/I12 | K57: =I57/I13 | L57: =SUM(L58:L59) | O57: =SUM(O58:O59) | R57: =SUM(R58:R59) | U57: =SUM(U58:U59) | X57: =SUM(X58:X59) | AA57: =SUM(AA58:AA59) | AD57: =SUM(AD58:AD59) | AG57: =SUM(AG58:AG59) | AJ57: =SUM(AJ58:AJ59) | AM57: =C57+F57+I57+L57+O57+R57+U57+X57+AA57+AD57+AG57+AJ57 | AN57: =AM57/AM12 | AO57: =AM57/AM13
B58: ENTREGA TERCEROS | AM58: =C58+F58+I58+L58+O58+R58+U58+X58+AA58+AD58+AG58+AJ58 | AO58: =AM58/AM$13
B59: ENTREGA MATERIA PRIMA TERCEROS | AM59: =C59+F59+I59+L59+O59+R59+U59+X59+AA59+AD59+AG59+AJ59 | AO59: =AM59/AM$13
B60: COSTOS PREPARADOS | C60: =+C61+C72+C75+C76+C77 | F60: =+F61+F72+F75+F76+F77 | I60: =+I61+I72+I75+I76+I77 | L60: =+L61+L72+L75+L76+L77 | O60: =+O61+O72+O75+O76+O77 | R60: =+R61+R72+R75+R76+R77 | U60: =+U61+U72+U75+U76+U77 | X60: =+X61+X72+X75+X76+X77 | AA60: =+AA61+AA72+AA75+AA76+AA77 | AD60: =+AD61+AD72+AD75+AD76+AD77 | AG60: =+AG61+AG72+AG75+AG76+AG77 | AJ60: =+AJ61+AJ72+AJ75+AJ76+AJ77 | AM60: =C60+F60+I60+L60+O60+R60+U60+X60+AA60+AD60+AG60+AJ60 | AN60: =AM60/$AM$5 | AO60: =AM60/AM$13
B61: INSUMOS CP | C61: =SUM(C62:C71) | F61: =SUM(F62:F71) | I61: =SUM(I62:I71) | L61: =SUM(L62:L71) | O61: =SUM(O62:O71) | P61: =O61/$O$5 | Q61: =O61/$O$13 | R61: =SUM(R62:R71) | S61: =R61/$O$5 | T61: =R61/$O$13 | U61: =SUM(U62:U71) | V61: =U61/$O$5 | W61: =U61/$O$13 | X61: =SUM(X62:X71) | AA61: =SUM(AA62:AA71) | AD61: =SUM(AD62:AD71) | AG61: =SUM(AG62:AG71) | AJ61: =SUM(AJ62:AJ71) | AM61: =C61+F61+I61+L61+O61+R61+U61+X61+AA61+AD61+AG61+AJ61 | AN61: =AM61/$O$5 | AO61: =AM61/$O$13
B62: COMPLEMENTO PREPARADO (Ins) | AM62: =C62+F62+I62+L62+O62+R62+U62+X62+AA62+AD62+AG62+AJ62 | AN62: =AM62/$O$5 | AO62: =AM62/$O$13
B63: ALMUERZO JORNADA UNICA (Ins) | AM63: =C63+F63+I63+L63+O63+R63+U63+X63+AA63+AD63+AG63+AJ63 | AN63: =AM63/$O$5 | AO63: =AM63/$O$13
AM64: =C64+F64+I64+L64+O64+R64+U64+X64+AA64+AD64+AG64+AJ64 | AN64: =AM64/$O$5 | AO64: =AM64/$O$13
B65: RACION MANIPULADORAS | AM65: =C65+F65+I65+L65+O65+R65+U65+X65+AA65+AD65+AG65+AJ65 | AN65: =AM65/$O$5 | AO65: =AM65/$O$13
B66: MENU ESPECIAL | AM66: =C66+F66+I66+L66+O66+R66+U66+X66+AA66+AD66+AG66+AJ66 | AN66: =AM66/$O$5 | AO66: =AM66/$O$13
AN67: =AM67/$O$5 | AO67: =AM67/$O$13
AN68: =AM68/$O$5 | AO68: =AM68/$O$13
AN69: =AM69/$O$5 | AO69: =AM69/$O$13
AN70: =AM70/$O$5 | AO70: =AM70/$O$13
AM71: =C71+F71+I71+L71+O71+R71+U71+X71+AA71+AD71+AG71+AJ71 | AN71: =AM71/$O$5 | AO71: =AM71/$O$13
B72: FLETES | C72: =SUM(C73:C74) | D72: =C72/C12 | E72: =C72/C13 | F72: =SUM(F73:F74) | G72: =F72/F12 | H72: =F72/F13 | I72: =SUM(I73:I74) | J72: =I72/I12 | K72: =I72/I13 | L72: =SUM(L73:L74) | M72: =L72/L12 | N72: =L72/L13 | O72: =SUM(O73:O74) | P72: =O72/O12 | Q72: =O72/O13 | R72: =SUM(R73:R74) | S72: =R72/R12 | T72: =R72/R13 | U72: =SUM(U73:U74) | V72: =U72/U12 | W72: =U72/U13 | X72: =SUM(X73:X74) | Y72: =X72/X12 | Z72: =X72/X13 | AA72: =SUM(AA73:AA74) | AB72: =AA72/AA12 | AC72: =AA72/AA13 | AD72: =SUM(AD73:AD74) | AE72: =AD72/AD12 | AF72: =AD72/AD13 | AG72: =SUM(AG73:AG74) | AH72: =AG72/AG12 | AI72: =AG72/AG13 | AJ72: =SUM(AJ73:AJ74) | AK72: =AJ72/AJ12 | AL72: =AJ72/AJ13 | AM72: =C72+F72+I72+L72+O72+R72+U72+X72+AA72+AD72+AG72+AJ72 | AN72: =AM72/AM12 | AO72: =AM72/AM13
B73: PREPARADOS PROPIOS | C73: ='GASTOS VEHICULOS'!C25*'%DIST'!B25 | F73: ='GASTOS VEHICULOS'!D25*'%DIST'!D25 | I73: ='GASTOS VEHICULOS'!E25*'%DIST'!F25 | L73: ='GASTOS VEHICULOS'!F25*'%DIST'!H25 | O73: ='GASTOS VEHICULOS'!G25*'%DIST'!J25 | R73: ='GASTOS VEHICULOS'!H25*'%DIST'!L25 | U73: ='GASTOS VEHICULOS'!I25*'%DIST'!N25 | X73: ='GASTOS VEHICULOS'!J25*'%DIST'!P25 | AA73: ='GASTOS VEHICULOS'!K25*'%DIST'!R25 | AD73: ='GASTOS VEHICULOS'!L25*'%DIST'!T25 | AG73: ='GASTOS VEHICULOS'!M25*'%DIST'!V25 | AJ73: ='GASTOS VEHICULOS'!N25*'%DIST'!X25 | AM73: =C73+F73+I73+L73+O73+R73+U73+X73+AA73+AD73+AG73+AJ73
A74: 73355001 | B74: PREPARADOS TERCEROS | C74: ='[9]Hoja 1'!$C$315 | F74: ='[10]Hoja 1'!$C$310 | AM74: =C74+F74+I74+L74+O74+R74+U74+X74+AA74+AD74+AG74+AJ74 | AO74: =AM72/AM13
A75: 71100501 | B75: Material de empaque | C75: ='[9]Hoja 1'!$C$309-9947928.12 | F75: ='[10]Hoja 1'!$C$304-10303069.4 | AM75: =C75+F75+I75+L75+O75+R75+U75+X75+AA75+AD75+AG75+AJ75 | AO75: =AM75/AM$13
B76: Menaje | AM76: =C76+F76+I76+L76+O76+R76+U76+X76+AA76+AD76+AG76+AJ76
B77: Servicio de Gas | AM77: =C77+F77+I77+L77+O77+R77+U77+X77+AA77+AD77+AG77+AJ77
B78: MANO DE OBRA DIRECTA | C78: =SUM(C79:C81) | F78: =SUM(F79:F81) | H78: =F78/(F$13) | I78: =SUM(I79:I81) | K78: =I78/(I$13) | L78: =SUM(L79:L81) | N78: =L78/(L$13) | O78: =SUM(O79:O81) | Q78: =O78/(O$13) | R78: =SUM(R79:R81) | T78: =R78/(R$13) | U78: =SUM(U79:U81) | W78: =U78/(U$13) | X78: =SUM(X79:X81) | Z78: =X78/(X$13) | AA78: =SUM(AA79:AA81) | AC78: =AA78/(AA$13) | AD78: =SUM(AD79:AD81) | AF78: =AD78/(AD$13) | AG78: =SUM(AG79:AG81) | AI78: =AG78/(AG$13) | AJ78: =SUM(AJ79:AJ81) | AM78: =C78+F78+I78+L78+O78+R78+U78+X78+AA78+AD78+AG78+AJ78 | AO78: =AM78/(AM$13)
B79: Manipuladoras | AM79: =C79+F79+I79+L79+O79+R79+U79+X79+AA79+AD79+AG79+AJ79 | AN79: =AM79/AM12
B80: Personal Supervisor - Coordinadores | C80: ='[21]Hoja 1'!$D$16+'[22]Hoja 1'!$D$16 | F80: ='[29]Hoja 1'!$D$17+'[33]Hoja 1'!$D$13 | AM80: =C80+F80+I80+L80+O80+R80+U80+X80+AA80+AD80+AG80+AJ80
B81: Personal Otros OP | AM81: =C81+F81+I81+L81+O81+R81+U81+X81+AA81+AD81+AG81+AJ81
B83: OTROS COSTOS Y GASTOS INDIRECTOS | C83: =+C84+C89+C92+C96+C99+C109+C114+C120+C123+C127 | E83: =C83/(C$13) | F83: =+F84+F89+F92+F96+F99+F109+F114+F120+F123+F127 | H83: =F83/(F$13) | I83: =+I84+I89+I92+I96+I99+I109+I114+I120+I123+I127 | K83: =I83/(I$13) | L83: =+L84+L89+L92+L96+L99+L109+L114+L120+L123+L127 | N83: =L83/(L$13) | O83: =+O84+O89+O92+O96+O99+O109+O114+O120+O123+O127 | Q83: =O83/(O$13) | R83: =+R84+R89+R92+R96+R99+R109+R114+R120+R123+R127 | T83: =R83/(R$13) | U83: =+U84+U89+U92+U96+U99+U109+U114+U120+U123+U127 | W83: =U83/(U$13) | X83: =+X84+X89+X92+X96+X99+X109+X114+X120+X123+X127 | Z83: =X83/(X$13) | AA83: =+AA84+AA89+AA92+AA96+AA99+AA109+AA114+AA120+AA123+AA127 | AC83: =AA83/(AA$13) | AD83: =+AD84+AD89+AD92+AD96+AD99+AD109+AD114+AD120+AD123+AD127 | AF83: =AD83/(AD$13) | AG83: =+AG84+AG89+AG92+AG96+AG99+AG109+AG114+AG120+AG123+AG127 | AI83: =AG83/(AG$13) | AJ83: =+AJ84+AJ89+AJ92+AJ96+AJ99+AJ109+AJ114+AJ120+AJ123+AJ127 | AM83: =C83+F83+I83+L83+O83+R83+U83+X83+AA83+AD83+AG83+AJ83 | AO83: =AM83/(AM$13)
B84: COSTOS DE PERSONAL | C84: =SUM(C85:C88) | E84: =C84/(C$13) | F84: =SUM(F85:F88) | H84: =F84/(F$13) | I84: =SUM(I85:I88) | K84: =I84/(I$13) | L84: =SUM(L85:L88) | N84: =L84/(L$13) | O84: =SUM(O85:O88) | Q84: =O84/(O$13) | R84: =SUM(R85:R88) | T84: =R84/(R$13) | U84: =SUM(U85:U88) | W84: =U84/(U$13) | X84: =SUM(X85:X88) | Z84: =X84/(X$13) | AA84: =SUM(AA85:AA88) | AC84: =AA84/(AA$13) | AD84: =SUM(AD85:AD88) | AF84: =AD84/(AD$13) | AG84: =SUM(AG85:AG88) | AI84: =AG84/(AG$13) | AJ84: =SUM(AJ85:AJ88) | AM84: =C84+F84+I84+L84+O84+R84+U84+X84+AA84+AD84+AG84+AJ84 | AO84: =AM84/(AM$13)
B85: Costos Indirectos de Personal | C85: ='GASTOS OPERATIVOS'!C17*'%DIST'!C9 | F85: ='GASTOS OPERATIVOS'!D17*'%DIST'!E9 | AM85: =C85+F85+I85+L85+O85+R85+U85+X85+AA85+AD85+AG85+AJ85 | AO85: =AM85/(AM$13) | AP85: 1.095
B86: Dotación y Suministros | AM86: =C86+F86+I86+L86+O86+R86+U86+X86+AA86+AD86+AG86+AJ86 | AO86: =AN86/AM13
B87: Gastos Medicos | AM87: =C87+F87+I87+L87+O87+R87+U87+X87+AA87+AD87+AG87+AJ87
B88: Incapacidades
B89: HONORARIOS | C89: =SUM(C90:C91) | E89: =C89/(C$13) | F89: =SUM(F90:F91) | H89: =F89/(F$13) | I89: =SUM(I90:I91) | K89: =I89/(I$13) | L89: =SUM(L90:L91) | N89: =L89/(L$13) | O89: =SUM(O90:O91) | Q89: =O89/(O$13) | R89: =SUM(R90:R91) | T89: =R89/(R$13) | U89: =SUM(U90:U91) | W89: =U89/(U$13) | X89: =SUM(X90:X91) | Z89: =X89/(X$13) | AA89: =SUM(AA90:AA91) | AC89: =AA89/(AA$13) | AD89: =SUM(AD90:AD91) | AF89: =AD89/(AD$13) | AG89: =SUM(AG90:AG91) | AI89: =AG89/(AG$13) | AJ89: =SUM(AJ90:AJ91) | AM89: =C89+F89+I89+L89+O89+R89+U89+X89+AA89+AD89+AG89+AJ89 | AO89: =AM89/(AM$13)
B90: Asesoría Juridica | AM90: =C90+F90+I90+L90+O90+R90+U90+X90+AA90+AD90+AG90+AJ90
B91: Asesoría Tecnica | AM91: =C91+F91+I91+L91+O91+R91+U91+X91+AA91+AD91+AG91+AJ91
B92: ARRENDAMIENTOS | C92: =SUM(C93:C95) | E92: =C92/(C$13) | F92: =SUM(F93:F95) | H92: =F92/(F$13) | I92: =SUM(I93:I95) | K92: =I92/(I$13) | L92: =SUM(L93:L95) | N92: =L92/(L$13) | O92: =SUM(O93:O95) | Q92: =O92/(O$13) | R92: =SUM(R93:R95) | T92: =R92/(R$13) | U92: =SUM(U93:U95) | W92: =U92/(U$13) | X92: =SUM(X93:X95) | Z92: =X92/(X$13) | AA92: =SUM(AA93:AA95) | AC92: =AA92/(AA$13) | AD92: =SUM(AD93:AD95) | AF92: =AD92/(AD$13) | AG92: =SUM(AG93:AG95) | AI92: =AG92/(AG$13) | AJ92: =SUM(AJ93:AJ95) | AM92: =C92+F92+I92+L92+O92+R92+U92+X92+AA92+AD92+AG92+AJ92 | AO92: =AM92/(AM$13)
B93: Construcciones y Edificaciones | AM93: =C93+F93+I93+L93+O93+R93+U93+X93+AA93+AD93+AG93+AJ93
B94: Maquinaria y Equipo | AM94: =C94+F94+I94+L94+O94+R94+U94+X94+AA94+AD94+AG94+AJ94
B95: Equipo de Oficina | AM95: =C95+F95+I95+L95+O95+R95+U95+X95+AA95+AD95+AG95+AJ95
B96: SEGUROS | C96: =SUM(C97:C98) | E96: =C96/(C$13) | F96: =SUM(F97:F98) | H96: =F96/(F$13) | I96: =SUM(I97:I98) | K96: =I96/(I$13) | L96: =SUM(L97:L98) | N96: =L96/(L$13) | O96: =SUM(O97:O98) | Q96: =O96/(O$13) | R96: =SUM(R97:R98) | T96: =R96/(R$13) | U96: =SUM(U97:U98) | W96: =U96/(U$13) | X96: =SUM(X97:X98) | Z96: =X96/(X$13) | AA96: =SUM(AA97:AA98) | AC96: =AA96/(AA$13) | AD96: =SUM(AD97:AD98) | AF96: =AD96/(AD$13) | AG96: =SUM(AG97:AG98) | AI96: =AG96/(AG$13) | AJ96: =SUM(AJ97:AJ98) | AM96: =C96+F96+I96+L96+O96+R96+U96+X96+AA96+AD96+AG96+AJ96 | AO96: =AM96/(AM$13)
B97: Cumplimiento | AM97: =C97+F97+I97+L97+O97+R97+U97+X97+AA97+AD97+AG97+AJ97
B98: Responsabilidad Civil Y Extracontractual | AM98: =C98+F98+I98+L98+O98+R98+U98+X98+AA98+AD98+AG98+AJ98
B99: SERVICIOS | C99: =SUM(C100:C108) | E99: =C99/(C$13) | F99: =SUM(F100:F108) | H99: =F99/(F$13) | I99: =SUM(I100:I106) | K99: =I99/(I$13) | L99: =SUM(L100:L108) | N99: =L99/(L$13) | O99: =SUM(O100:O108) | Q99: =O99/(O$13) | R99: =SUM(R100:R108) | T99: =R99/(R$13) | U99: =SUM(U100:U108) | W99: =U99/(U$13) | X99: =SUM(X100:X108) | Z99: =X99/(X$13) | AA99: =SUM(AA100:AA108) | AC99: =AA99/(AA$13) | AD99: =SUM(AD100:AD108) | AF99: =AD99/(AD$13) | AG99: =SUM(AG100:AG108) | AI99: =AG99/(AG$13) | AJ99: =SUM(AJ100:AJ108) | AM99: =C99+F99+I99+L99+O99+R99+U99+X99+AA99+AD99+AG99+AJ99 | AO99: =AM99/(AM$13)
B100: Aseo y Vigilancia | AM100: =C100+F100+I100+L100+O100+R100+U100+X100+AA100+AD100+AG100+AJ100
B101: Temporales Serv | AM101: =C101+F101+I101+L101+O101+R101+U101+X101+AA101+AD101+AG101+AJ101
B102: Mensajeria | AM102: =C102+F102+I102+L102+O102+R102+U102+X102+AA102+AD102+AG102+AJ102
B103: Laboratorio | AM103: =C103+F103+I103+L103+O103+R103+U103+X103+AA103+AD103+AG103+AJ103
B104: Fumigacion | AM104: =C104+F104+I104+L104+O104+R104+U104+X104+AA104+AD104+AG104+AJ104
B105: Acueducto y Alcantarillado | AM105: =C105+F105+I105+L105+O105+R105+U105+X105+AA105+AD105+AG105+AJ105
B106: Energia | AM106: =C106+F106+I106+L106+O106+R106+U106+X106+AA106+AD106+AG106+AJ106
B107: Telefono e Internet | AM107: =C107+F107+I107+L107+O107+R107+U107+X107+AA107+AD107+AG107+AJ107
B108: Correo, porte y telegramas | AM108: =C108+F108+I108+L108+O108+R108+U108+X108+AA108+AD108+AG108+AJ108
B109: GASTOS LEGALES | C109: =SUM(C110:C113) | E109: =C109/(C$13) | F109: =SUM(F110:F113) | H109: =F109/(F$13) | I109: =SUM(I110:I113) | K109: =I109/(I$13) | L109: =SUM(L110:L113) | N109: =L109/(L$13) | O109: =SUM(O110:O113) | Q109: =O109/(O$13) | R109: =SUM(R110:R113) | T109: =R109/(R$13) | U109: =SUM(U110:U113) | W109: =U109/(U$13) | X109: =SUM(X110:X113) | Z109: =X109/(X$13) | AA109: =SUM(AA110:AA113) | AC109: =AA109/(AA$13) | AD109: =SUM(AD110:AD113) | AF109: =AD109/(AD$13) | AG109: =SUM(AG110:AG113) | AI109: =AG109/(AG$13) | AJ109: =SUM(AJ110:AJ113) | AM109: =C109+F109+I109+L109+O109+R109+U109+X109+AA109+AD109+AG109+AJ109 | AO109: =AM109/(AM$13)
B110: Notariales | AM110: =C110+F110+I110+L110+O110+R110+U110+X110+AA110+AD110+AG110+AJ110
B111: Registro Mercantil | AM111: =C111+F111+I111+L111+O111+R111+U111+X111+AA111+AD111+AG111+AJ111
B112: Trámites y Licencias | AM112: =C112+F112+I112+L112+O112+R112+U112+X112+AA112+AD112+AG112+AJ112
...

Sheet CTAS EN PPACION
B2: CORPORACIÓN HACIA UN VALLE SOLIDARIO | C2: PYG CUENTAS EN PARTICIPACION 2026
B3: DIAS DE ATENCIÓN | C3: 20 | F3: 20 | I3: 20 | L3: 20 | O3: 20 | R3: 20 | U3: 20 | X3: 20 | AA3: 20 | AD3: 20 | AG3: 20 | AJ3: 20 | AM3: =SUM(C3:AL3)
C4: ENE | D4: x racion | E4: % | F4: FEB | G4: x racion | H4: % | I4: MAR | J4: x racion | K4: % | L4: ABR | M4: x racion | N4: % | O4: MAY | P4: x racion | Q4: % | R4: JUN | S4: x racion | T4: % | U4: JUL | V4: x racion | W4: % | X4: AGO | Y4: x racion | Z4: % | AA4: SEP | AB4: x racion | AC4: % | AD4: OCT | AE4: x racion | AF4: % | AG4: NOV | AH4: x racion | AI4: % | AJ4: DIC | AK4: x racion | AL4: % | AM4: ACUMULADO | AN4: x racion | AO4: %
AM5: =C5+F5+I5+L5+O5+R5+U5+X5+AA5+AD5+AG5+AJ5 | AO5: =AM5/AM12
B6: RACIONES | AM6: =C6+F6+I6+L6+O6+R6+U6+X6+AA6+AD6+AG6+AJ6 | AO6: =AM6/AM12
AM7: =C7+F7+I7+L7+O7+R7+U7+X7+AA7+AD7+AG7+AJ7 | AO7: =AM7/AM12
AM8: =C8+F8+I8+L8+O8+R8+U8+X8+AA8+AD8+AG8+AJ8
AM9: =C9+F9+I9+L9+O9+R9+U9+X9+AA9+AD9+AG9+AJ9
AM10: =C10+F10+I10+L10+O10+R10+U10+X10+AA10+AD10+AG10+AJ10
AM11: =C11+F11+I11+L11+O11+R11+U11+X11+AA11+AD11+AG11+AJ11
B12: TOTAL RACIONES | C12: =SUM(C5:C11) | F12: =SUM(F5:F11) | I12: =SUM(I5:I11) | L12: =SUM(L5:L11) | O12: =SUM(O5:O11) | R12: =SUM(R5:R11) | U12: =SUM(U5:U11) | X12: =SUM(X5:X11) | AA12: =SUM(AA5:AA11) | AD12: =SUM(AD5:AD11) | AG12: =SUM(AG5:AG11) | AJ12: =SUM(AJ5:AJ11) | AM12: =C12+F12+I12+L12+O12+R12+U12+X12+AA12+AD12+AG12+AJ12
B13: INGRESOS BRUTOS | C13: =C14+C23 | F13: =F14+F23 | I13: =I14+I23 | L13: =L14+L23 | O13: =O14+O23 | R13: =R14+R23 | U13: =U14+U23 | X13: =X14+X23 | AA13: =AA14+AA23 | AD13: =AD14+AD23 | AG13: =AG14+AG23 | AJ13: =AJ14+AJ23 | AM13: =C13+F13+I13+L13+O13+R13+U13+X13+AA13+AD13+AG13+AJ13
B14: OPERACIONALES | C14: =C15 | F14: =F15 | I14: =I15 | L14: =L15 | O14: =O15 | R14: =R15 | U14: =U15 | X14: =X15 | AA14: =AA15 | AD14: =AD15 | AG14: =AG15 | AJ14: =AJ15 | AM14: =C14+F14+I14+L14+O14+R14+U14+X14+AA14+AD14+AG14+AJ14
B15: INDUSTRIAS MANUFACTURERAS | C15: =SUM(C16:C22) | F15: =SUM(F16:F22) | I15: =SUM(I16:I22) | L15: =SUM(L16:L22) | O15: =SUM(O16:O22) | R15: =SUM(R16:R22) | U15: =SUM(U16:U22) | X15: =SUM(X16:X22) | Z15: =X15/X15 | AA15: =SUM(AA16:AA22) | AC15: =AA15/AA15 | AD15: =SUM(AD16:AD22) | AF15: =AD15/AD15 | AG15: =SUM(AG16:AG22) | AI15: =AG15/AG15 | AJ15: =SUM(AJ16:AJ22) | AM15: =C15+F15+I15+L15+O15+R15+U15+X15+AA15+AD15+AG15+AJ15 | AO15: =AM15/AM15
AM16: =C16+F16+I16+L16+O16+R16+U16+X16+AA16+AD16+AG16+AJ16
B17: SUMINISTRO | J17: =I17/I6 | M17: =L17/L6 | P17: =O17/O6 | S17: =R17/R6 | V17: =U17/U6 | Y17: =X17/X6 | AB17: =AA17/AA6 | AE17: =AD17/AD6 | AH17: =AG17/AG6 | AK17: =AJ17/AJ6 | AM17: =C17+F17+I17+L17+O17+R17+U17+X17+AA17+AD17+AG17+AJ17
J18: =I18/I7 | M18: =L18/L7 | P18: =O18/O7 | S18: =R18/R7 | V18: =U18/U7 | Y18: =X18/X7 | AB18: =AA18/AA7 | AE18: =AD18/AD7 | AH18: =AG18/AG7 | AM18: =C18+F18+I18+L18+O18+R18+U18+X18+AA18+AD18+AG18+AJ18
AM19: =C19+F19+I19+L19+O19+R19+U19+X19+AA19+AD19+AG19+AJ19
AM20: =C20+F20+I20+L20+O20+R20+U20+X20+AA20+AD20+AG20+AJ20
B21: TRANSPORTE | AM21: =C21+F21+I21+L21+O21+R21+U21+X21+AA21+AD21+AG21+AJ21
AM22: =C22+F22+I22+L22+O22+R22+U22+X22+AA22+AD22+AG22+AJ22
B23: NO OPERACIONALES | C23: =C24 | F23: =F24 | I23: =I24 | L23: =L24 | O23: =O24 | R23: =R24 | U23: =U24 | X23: =X24 | AA23: =AA24 | AM23: =C23+F23+I23+L23+O23+R23+U23+X23+AA23+AD23+AG23+AJ23
B24: FINANCIEROS | C24: =SUM(C25:C27) | F24: =SUM(F25:F27) | I24: =SUM(I25:I27) | L24: =SUM(L25:L27) | O24: =SUM(O25:O27) | R24: =SUM(R25:R27) | U24: =SUM(U25:U27) | X24: =SUM(X25:X27) | AA24: =SUM(AA25:AA27) | AD24: =SUM(AD25:AD27) | AG24: =SUM(AG25:AG27) | AJ24: =SUM(AJ25:AJ27) | AM24: =C24+F24+I24+L24+O24+R24+U24+X24+AA24+AD24+AG24+AJ24
B25: Intereses | AM25: =C25+F25+I25+L25+O25+R25+U25+X25+AA25+AD25+AG25+AJ25
B26: Descuentos Comerciales | AM26: =C26+F26+I26+L26+O26+R26+U26+X26+AA26+AD26+AG26+AJ26
B27: otros | AM27: =C27+F27+I27+L27+O27+R27+U27+X27+AA27+AD27+AG27+AJ27
B28: DESCUENTOS - GASTO OPERACIONAL | C28: =+C29 | F28: =+F29 | I28: =+I29 | L28: =+L29 | O28: =+O29 | R28: =+R29 | U28: =+U29 | X28: =+X29 | AA28: =+AA29 | AD28: =+AD29 | AG28: =+AG29 | AJ28: =+AJ29 | AM28: =C28+F28+I28+L28+O28+R28+U28+X28+AA28+AD28+AG28+AJ28
B29: OTROS | C29: =SUM(C30:C35) | F29: =SUM(F30:F35) | H29: =F29/F13 | I29: =SUM(I30:I35) | K29: =I29/I13 | L29: =SUM(L30:L35) | N29: =L29/L13 | O29: =SUM(O30:O35) | Q29: =O29/O13 | R29: =SUM(R30:R35) | T29: =R29/R13 | U29: =SUM(U30:U35) | W29: =U29/U13 | X29: =SUM(X30:X35) | Z29: =X29/X13 | AA29: =SUM(AA30:AA35) | AC29: =AA29/AA13 | AD29: =SUM(AD30:AD35) | AF29: =AD29/AD13 | AG29: =SUM(AG30:AG35) | AI29: =AG29/AG13 | AJ29: =SUM(AJ30:AJ35) | AM29: =C29+F29+I29+L29+O29+R29+U29+X29+AA29+AD29+AG29+AJ29 | AN29: =AM29/$AM$6 | AO29: =AM29/AM13
AM30: =C30+F30+I30+L30+O30+R30+U30+X30+AA30+AD30+AG30+AJ30
B31: Rete fuente | AM31: =C31+F31+I31+L31+O31+R31+U31+X31+AA31+AD31+AG31+AJ31
B32: Rete fuente | AM32: =C32+F32+I32+L32+O32+R32+U32+X32+AA32+AD32+AG32+AJ32
AM33: =C33+F33+I33+L33+O33+R33+U33+X33+AA33+AD33+AG33+AJ33
AM34: =C34+F34+I34+L34+O34+R34+U34+X34+AA34+AD34+AG34+AJ34
AM35: =C35+F35+I35+L35+O35+R35+U35+X35+AA35+AD35+AG35+AJ35
B42: TOTAL INGRESOS NETOS | C42: =+C14+C23-C28 | F42: =+F14+F23-F28 | I42: =+I14+I23-I28 | L42: =+L14+L23-L28 | O42: =+O14+O23-O28 | R42: =+R14+R23-R28 | U42: =+U14+U23-U28 | X42: =+X14+X23-X28 | AA42: =+AA14+AA23-AA28 | AD42: =+AD14+AD23-AD28 | AG42: =+AG14+AG23-AG28 | AJ42: =+AJ14+AJ23-AJ28 | AM42: =C42+F42+I42+L42+O42+R42+U42+X42+AA42+AD42+AG42+AJ42
B44: COSTOS DE PRODUCCION | C44: =+C45+C60+C78 | F44: =+F45+F60+F78 | H44: =F44/F$13 | I44: =+I45+I60+I78 | K44: =I44/I$13 | L44: =+L45+L60+L78 | N44: =L44/L$13 | O44: =+O45+O60+O78 | Q44: =O44/O$13 | R44: =+R45+R60+R78 | T44: =R44/R$13 | U44: =+U45+U60+U78 | W44: =U44/U$13 | X44: =+X45+X60+X78 | Z44: =X44/X$13 | AA44: =+AA45+AA60+AA78 | AC44: =AA44/AA$13 | AD44: =+AD45+AD60+AD78 | AF44: =AD44/AD$13 | AG44: =+AG45+AG60+AG78 | AI44: =AG44/AG$13 | AJ44: =+AJ45+AJ60+AJ78 | AM44: =C44+F44+I44+L44+O44+R44+U44+X44+AA44+AD44+AG44+AJ44 | AO44: =AM44/AM$13
B45: COSTOS INDUSTRIALIZADOS | C45: =+C46+C57 | F45: =+F46+F57 | H45: =F45/F13 | I45: =+I46+I57 | K45: =I45/I13 | L45: =+L46+L57 | O45: =+O46+O57 | R45: =+R46+R57 | T45: =R45/R13 | U45: =+U46+U57 | W45: =U45/U13 | X45: =+X46+X57 | AA45: =+AA46+AA57 | AD45: =+AD46+AD57 | AG45: =+AG46+AG57 | AJ45: =+AJ46+AJ57 | AM45: =C45+F45+I45+L45+O45+R45+U45+X45+AA45+AD45+AG45+AJ45
B46: INSUMOS | C46: =SUM(C47:C56) | F46: =SUM(F47:F56) | I46: =SUM(I47:I56) | L46: =SUM(L47:L56) | O46: =SUM(O47:O56) | R46: =SUM(R47:R56) | U46: =SUM(U47:U56) | X46: =SUM(X47:X56) | AA46: =SUM(AA47:AA56) | AD46: =SUM(AD47:AD56) | AG46: =SUM(AG47:AG56) | AJ46: =SUM(AJ47:AJ56) | AM46: =C46+F46+I46+L46+O46+R46+U46+X46+AA46+AD46+AG46+AJ46
B47: SUMINISTRO | C47: 7.0431626e+08 | D47: =C47/C12 | E47: =C47/C13 | F47: 7.0270086e+08 | G47: =F47/F12 | H47: =F47/F13 | J47: =I47/I12 | K47: =I47/I13 | M47: =L47/L12 | N47: =L47/L13 | P47: =O47/O12 | Q47: =O47/O13 | S47: =R47/R12 | T47: =R47/R13 | V47: =U47/U12 | W47: =U47/U13 | Y47: =X47/X12 | Z47: =X47/X13 | AB47: =AA47/AA12 | AC47: =AA47/AA13 | AE47: =AD47/AD12 | AF47: =AD47/AD13 | AH47: =AG47/AG12 | AI47: =AG47/AG13 | AK47: =AJ47/AJ12 | AL47: =AJ47/AJ13 | AM47: =C47+F47+I47+L47+O47+R47+U47+X47+AA47+AD47+AG47+AJ47 | AN47: =AM47/$AM$12 | AO47: =AM47/AM13
AM48: =C48+F48+I48+L48+O48+R48+U48+X48+AA48+AD48+AG48+AJ48 | AN48: =AM48/AM12
AM49: =C49+F49+I49+L49+O49+R49+U49+X49+AA49+AD49+AG49+AJ49
AM50: =C50+F50+I50+L50+O50+R50+U50+X50+AA50+AD50+AG50+AJ50
AM51: =C51+F51+I51+L51+O51+R51+U51+X51+AA51+AD51+AG51+AJ51
AM52: =C52+F52+I52+L52+O52+R52+U52+X52+AA52+AD52+AG52+AJ52
AM53: =C53+F53+I53+L53+O53+R53+U53+X53+AA53+AD53+AG53+AJ53
B57: FLETES - OTROS OPERADORES | C57: =SUM(C58:C59) | D57: =C57/C12 | E57: =C57/C13 | F57: =SUM(F58:F59) | G57: =F57/F12 | H57: =F57/F13 | I57: =SUM(I58:I59) | J57: =I57/I12 | K57: =I57/I13 | L57: =SUM(L58:L59) | M57: =L57/L12 | N57: =L57/L13 | O57: =SUM(O58:O59) | P57: =O57/O12 | Q57: =O57/O13 | R57: =SUM(R58:R59) | S57: =R57/R12 | T57: =R57/R13 | U57: =SUM(U58:U59) | V57: =U57/U12 | W57: =U57/U13 | X57: =SUM(X58:X59) | Y57: =X57/X12 | Z57: =X57/X13 | AA57: =SUM(AA58:AA59) | AB57: =AA57/AA12 | AC57: =AA57/AA13 | AD57: =SUM(AD58:AD59) | AE57: =AD57/AD12 | AF57: =AD57/AD13 | AG57: =SUM(AG58:AG59) | AH57: =AG57/AG12 | AI57: =AG57/AG13 | AJ57: =SUM(AJ58:AJ59) | AK57: =AJ57/AJ12 | AL57: =AJ57/AJ13 | AM57: =C57+F57+I57+L57+O57+R57+U57+X57+AA57+AD57+AG57+AJ57 | AN57: =AM57/AM12 | AO57: =AM57/AM13
B58: ENTREGA POR RACION | C58: =[56]ENERO!$G$22 | F58: =[56]FEBRERO!$G$22 | AM58: =C58+F58+I58+L58+O58+R58+U58+X58+AA58+AD58+AG58+AJ58 | AO58: =AM58/AM$13
B59: ENTREGA MATERIA PRIMA | AM59: =C59+F59+I59+L59+O59+R59+U59+X59+AA59+AD59+AG59+AJ59 | AO59: =AM59/AM$13
B60: COSTOS PREPARADOS | C60: =+C61+C73+C74+C75+C76+C77 | F60: =+F61+F72+F75+F76+F77 | H60: =F60/F13 | I60: =+I61+I72+I75+I76+I77 | K60: =I60/I13 | L60: =+L61+L72+L75+L76+L77 | N60: =L60/L13 | O60: =+O61+O72+O75+O76+O77 | Q60: =O60/$O$13 | R60: =+R61+R72+R75+R76+R77 | T60: =R60/$O$13 | U60: =+U61+U72+U75+U76+U77 | X60: =+X61+X72+X75+X76+X77 | AA60: =+AA61+AA72+AA75+AA76+AA77 | AD60: =+AD61+AD72+AD75+AD76+AD77 | AG60: =+AG61+AG72+AG75+AG76+AG77 | AJ60: =+AJ61+AJ72+AJ75+AJ76+AJ77 | AM60: =C60+F60+I60+L60+O60+R60+U60+X60+AA60+AD60+AG60+AJ60
B61: INSUMOS | C61: =SUM(C62:C71)+C72 | F61: =SUM(F62:F71) | I61: =SUM(I62:I71) | L61: =SUM(L62:L71) | O61: =SUM(O62:O71) | P61: =O61/$O$5 | Q61: =O61/$O$13 | R61: =SUM(R62:R71) | S61: =R61/$O$5 | T61: =R61/$O$13 | U61: =SUM(U62:U71) | V61: =U61/$O$5 | W61: =U61/$O$13 | X61: =SUM(X62:X71) | AA61: =SUM(AA62:AA71) | AD61: =SUM(AD62:AD71) | AG61: =SUM(AG62:AG71) | AJ61: =SUM(AJ62:AJ71) | AM61: =C61+F61+I61+L61+O61+R61+U61+X61+AA61+AD61+AG61+AJ61
AM62: =C62+F62+I62+L62+O62+R62+U62+X62+AA62+AD62+AG62+AJ62
AM63: =C63+F63+I63+L63+O63+R63+U63+X63+AA63+AD63+AG63+AJ63
AM64: =C64+F64+I64+L64+O64+R64+U64+X64+AA64+AD64+AG64+AJ64
AM65: =C65+F65+I65+L65+O65+R65+U65+X65+AA65+AD65+AG65+AJ65
AM66: =C66+F66+I66+L66+O66+R66+U66+X66+AA66+AD66+AG66+AJ66
AM71: =C71+F71+I71+L71+O71+R71+U71+X71+AA71+AD71+AG71+AJ71
B72: FLETES - CHVS | F72: =SUM(F73:F74) | G72: =F72/F12 | H72: =F72/F13 | I72: =SUM(I73:I74) | J72: =I72/I12 | K72: =I72/I13 | L72: =SUM(L73:L74) | O72: =SUM(O73:O74) | R72: =SUM(R73:R74) | U72: =SUM(U73:U74) | V72: =U72/U12 | X72: =SUM(X73:X74) | Y72: =X72/X12 | Z72: =X72/X13 | AA72: =SUM(AA73:AA74) | AB72: =AA72/AA12 | AC72: =AA72/AA13 | AD72: =SUM(AD73:AD74) | AE72: =AD72/AD12 | AF72: =AD72/AD13 | AG72: =SUM(AG73:AG74) | AH72: =AG72/AG12 | AI72: =AG72/AG13 | AJ72: =SUM(AJ73:AJ74) | AM72: =C72+F72+I72+L72+O72+R72+U72+X72+AA72+AD72+AG72+AJ72 | AN72: =AM72/AM12 | AO72: =AM72/AM13
AM73: =C73+F73+I73+L73+O73+R73+U73+X73+AA73+AD73+AG73+AJ73
B74: TERCEROS | AM74: =C74+F74+I74+L74+O74+R74+U74+X74+AA74+AD74+AG74+AJ74
B75: Material de empaque | AM75: =C75+F75+I75+L75+O75+R75+U75+X75+AA75+AD75+AG75+AJ75
B76: Menaje | AM76: =C76+F76+I76+L76+O76+R76+U76+X76+AA76+AD76+AG76+AJ76
B77: Servicio de Gas | AM77: =C77+F77+I77+L77+O77+R77+U77+X77+AA77+AD77+AG77+AJ77
B78: MANO DE OBRA DIRECTA | C78: =SUM(C79:C81) | F78: =SUM(F79:F81) | H78: =F78/(F$13) | I78: =SUM(I79:I81) | K78: =I78/(I$13) | L78: =SUM(L79:L81) | N78: =L78/(L$13) | O78: =SUM(O79:O81) | Q78: =O78/(O$13) | R78: =SUM(R79:R81) | T78: =R78/(R$13) | U78: =SUM(U79:U81) | W78: =U78/(U$13) | X78: =SUM(X79:X81) | Z78: =X78/(X$13) | AA78: =SUM(AA79:AA81) | AC78: =AA78/(AA$13) | AD78: =SUM(AD79:AD81) | AF78: =AD78/(AD$13) | AG78: =SUM(AG79:AG81) | AI78: =AG78/(AG$13) | AJ78: =SUM(AJ79:AJ81) | AM78: =C78+F78+I78+L78+O78+R78+U78+X78+AA78+AD78+AG78+AJ78 | AO78: =AM78/(AM$13)
B79: Manipuladoras | AM79: =C79+F79+I79+L79+O79+R79+U79+X79+AA79+AD79+AG79+AJ79 | AN79: =AM79/AM12
B80: Personal Supervisor - Coordinadores | AM80: =C80+F80+I80+L80+O80+R80+U80+X80+AA80+AD80+AG80+AJ80
B81: Temporales | AM81: =C81+F81+I81+L81+O81+R81+U81+X81+AA81+AD81+AG81+AJ81
I82: =I58/I6 | L82: =L58/L6 | O82: =O58/O6 | R82: =R58/R6 | U82: =U58/U6
B83: OTROS COSTOS Y GASTOS INDIRECTOS | C83: =+C84+C89+C92+C96+C99+C109+C114+C120+C123+C127 | F83: =+F84+F89+F92+F96+F99+F109+F114+F120+F123+F127 | H83: =F83/(F$13) | I83: =+I84+I89+I92+I96+I99+I109+I114+I120+I123+I127 | K83: =I83/(I$13) | L83: =+L84+L89+L92+L96+L99+L109+L114+L120+L123+L127 | N83: =L83/(L$13) | O83: =+O84+O89+O92+O96+O99+O109+O114+O120+O123+O127 | Q83: =O83/(O$13) | R83: =+R84+R89+R92+R96+R99+R109+R114+R120+R123+R127 | T83: =R83/(R$13) | U83: =+U84+U89+U92+U96+U99+U109+U114+U120+U123+U127 | W83: =U83/(U$13) | X83: =+X84+X89+X92+X96+X99+X109+X114+X120+X123+X127 | Z83: =X83/(X$13) | AA83: =+AA84+AA89+AA92+AA96+AA99+AA109+AA114+AA120+AA123+AA127 | AC83: =AA83/(AA$13) | AD83: =+AD84+AD89+AD92+AD96+AD99+AD109+AD114+AD120+AD123+AD127 | AF83: =AD83/(AD$13) | AG83: =+AG84+AG89+AG92+AG96+AG99+AG109+AG114+AG120+AG123+AG127 | AI83: =AG83/(AG$13) | AJ83: =+AJ84+AJ89+AJ92+AJ96+AJ99+AJ109+AJ114+AJ120+AJ123+AJ127 | AM83: =C83+F83+I83+L83+O83+R83+U83+X83+AA83+AD83+AG83+AJ83 | AO83: =AM83/(AM$13)
B84: COSTOS DE PERSONAL | C84: =SUM(C85:C88) | F84: =SUM(F85:F88) | H84: =F84/(F$13) | I84: =SUM(I85:I88) | K84: =I84/(I$13) | L84: =SUM(L85:L88) | N84: =L84/(L$13) | O84: =SUM(O85:O88) | Q84: =O84/(O$13) | R84: =SUM(R85:R88) | T84: =R84/(R$13) | U84: =SUM(U85:U88) | W84: =U84/(U$13) | X84: =SUM(X85:X88) | Z84: =X84/(X$13) | AA84: =SUM(AA85:AA88) | AC84: =AA84/(AA$13) | AD84: =SUM(AD85:AD88) | AF84: =AD84/(AD$13) | AG84: =SUM(AG85:AG88) | AI84: =AG84/(AG$13) | AJ84: =SUM(AJ85:AJ88) | AM84: =C84+F84+I84+L84+O84+R84+U84+X84+AA84+AD84+AG84+AJ84 | AO84: =AM84/(AM$13)
B85: Costos Indirectos de Personal | C85: ='[22]Hoja 1'!$D$20 | F85: ='[30]Hoja 1'!$D$14+'[35]Hoja 1'!$D$15 | AM85: =C85+F85+I85+L85+O85+R85+U85+X85+AA85+AD85+AG85+AJ85 | AN85: =AM85/$AM$6 | AO85: =AM85/(AM$13)
B86: Dotación y Suministros | AM86: =C86+F86+I86+L86+O86+R86+U86+X86+AA86+AD86+AG86+AJ86
B87: Gastos Medicos | AM87: =C87+F87+I87+L87+O87+R87+U87+X87+AA87+AD87+AG87+AJ87
B88: Inacapacidades | AM88: =C88+F88+I88+L88+O88+R88+U88+X88+AA88+AD88+AG88+AJ88
B89: HONORARIOS | C89: =SUM(C90:C91) | F89: =SUM(F90:F91) | H89: =F89/(F$13) | I89: =SUM(I90:I91) | K89: =I89/(I$13) | L89: =SUM(L90:L91) | N89: =L89/(L$13) | O89: =SUM(O90:O91) | Q89: =O89/(O$13) | R89: =SUM(R90:R91) | T89: =R89/(R$13) | U89: =SUM(U90:U91) | W89: =U89/(U$13) | X89: =SUM(X90:X91) | Z89: =X89/(X$13) | AA89: =SUM(AA90:AA91) | AC89: =AA89/(AA$13) | AD89: =SUM(AD90:AD91) | AF89: =AD89/(AD$13) | AG89: =SUM(AG90:AG91) | AI89: =AG89/(AG$13) | AJ89: =SUM(AJ90:AJ91) | AM89: =C89+F89+I89+L89+O89+R89+U89+X89+AA89+AD89+AG89+AJ89 | AO89: =AM89/(AM$13)
B90: Asesoría Juridica | AM90: =C90+F90+I90+L90+O90+R90+U90+X90+AA90+AD90+AG90+AJ90
B91: Asesoría Tecnica | AM91: =C91+F91+I91+L91+O91+R91+U91+X91+AA91+AD91+AG91+AJ91
B92: ARRENDAMIENTOS | C92: =SUM(C93:C95) | F92: =SUM(F93:F95) | H92: =F92/(F$13) | I92: =SUM(I93:I95) | K92: =I92/(I$13) | L92: =SUM(L93:L95) | N92: =L92/(L$13) | O92: =SUM(O93:O95) | Q92: =O92/(O$13) | R92: =SUM(R93:R95) | T92: =R92/(R$13) | U92: =SUM(U93:U95) | W92: =U92/(U$13) | X92: =SUM(X93:X95) | Z92: =X92/(X$13) | AA92: =SUM(AA93:AA95) | AC92: =AA92/(AA$13) | AD92: =SUM(AD93:AD95) | AF92: =AD92/(AD$13) | AG92: =SUM(AG93:AG95) | AI92: =AG92/(AG$13) | AJ92: =SUM(AJ93:AJ95) | AM92: =C92+F92+I92+L92+O92+R92+U92+X92+AA92+AD92+AG92+AJ92 | AO92: =AM92/(AM$13)
B93: Construcciones y Edificaciones | AM93: =C93+F93+I93+L93+O93+R93+U93+X93+AA93+AD93+AG93+AJ93
B94: Maquinaria y Equipo | AM94: =C94+F94+I94+L94+O94+R94+U94+X94+AA94+AD94+AG94+AJ94
B95: Equipo de Oficina | AM95: =C95+F95+I95+L95+O95+R95+U95+X95+AA95+AD95+AG95+AJ95
B96: SEGUROS | C96: =SUM(C97:C98) | F96: =SUM(F97:F98) | H96: =F96/(F$13) | I96: =SUM(I97:I98) | K96: =I96/(I$13) | L96: =SUM(L97:L98) | N96: =L96/(L$13) | O96: =SUM(O97:O98) | Q96: =O96/(O$13) | R96: =SUM(R97:R98) | T96: =R96/(R$13) | U96: =SUM(U97:U98) | W96: =U96/(U$13) | X96: =SUM(X97:X98) | Z96: =X96/(X$13) | AA96: =SUM(AA97:AA98) | AC96: =AA96/(AA$13) | AD96: =SUM(AD97:AD98) | AF96: =AD96/(AD$13) | AG96: =SUM(AG97:AG98) | AI96: =AG96/(AG$13) | AJ96: =SUM(AJ97:AJ98) | AM96: =C96+F96+I96+L96+O96+R96+U96+X96+AA96+AD96+AG96+AJ96 | AO96: =AM96/(AM$13)
A97: 73301001 | B97: Cumplimiento | AM97: =C97+F97+I97+L97+O97+R97+U97+X97+AA97+AD97+AG97+AJ97
A98: 73306001 | B98: Respomsabilidad Civil Y Extracontractual | AM98: =C98+F98+I98+L98+O98+R98+U98+X98+AA98+AD98+AG98+AJ98
